Workbook
Name _low1: #REF!
Name _low1: #REF!
Name _low2: #REF!
Name _low2: #REF!
Name _LOW3: #REF!
Name _LOW3: #REF!
Name _pl1: #REF!
Name _pl1: #REF!
Name _XX37: #REF!
Name _XX37: #REF!
Name _XX39: #REF!
Name _XX39: #REF!
Name bs: #REF!
Name bs: #REF!
Name bscf1: #REF!
Name bscf1: #REF!
Name bscf2: #REF!
Name bscf2: #REF!
Name BSCF3: #REF!
Name BSCF3: #REF!
Name content: #REF!
Name content: #REF!
Name date: #REF!
Name date: #REF!
Name dicf: #REF!
Name dicf: #REF!
Name expenses: #REF!
Name expenses: #REF!
Name file: #REF!
Name file: #REF!
Name file1: #REF!
Name file1: #REF!
Name 경영현황비교2: #REF!
Name 대차대조표1: #REF!
Name 대차대조표1: #REF!
Name 대차대조표2: #REF!
Name 대차대조표2: #REF!
Name 대차대조표둘: #REF!
Name 대차대조표둘: #REF!
Name 손익계산서: #REF!
Name 손익계산서: #REF!
Name 현금흐름표: #REF!
Name 현금흐름표: #REF!

Sheet 목표
B5: 2026 매출매입 | C5: Q1 | D5: Q2 | E5: Q3 | F5: Q4 | G5: Total
B6: 목표 TST | C6: =570000000+750000000 -> 1320000000 | D6: =280000000+60000000 -> 340000000 | E6: =250000000+220000000 -> 470000000 | F6: =740000000+330000000 -> 1070000000 | G6: =SUM(C6:F6) -> 3200000000
B7: 목표 SDT | C7: 250000000 | D7: 215000000 | E7: 75000000 | F7: 410000000 | G7: =SUM(C7:F7) -> 950000000
B8: 목표 EST1 | C8: =350000000 -> 350000000 | D8: 300000000 | E8: 350000000 | F8: 400000000 | G8: =SUM(C8:F8) -> 1400000000
B9: 목표 EST2+EST3 | C9: =150000000 -> 150000000 | D9: =80000000 -> 80000000 | E9: =40000000 -> 40000000 | F9: =130000000 -> 130000000 | G9: =SUM(C9:F9) -> 400000000

Sheet 팀별실적
B1: 구분 | D1: 팀명 | E1: 1월 | F1: 2월 | G1: 3월 | H1: Q1 | I1: 4월 | J1: 5월 | K1: 6월 | L1: Q2 | M1: 7월 | N1: 8월 | O1: 9월 | P1: Q3 | Q1: 10월 | R1: 11월 | S1: 12월 | T1: Q4 | U1: 2026
B2: 매출 | D2: SDT | E2: =SDT!F12 -> 1600000 | F2: =SDT!G12 -> 30000000 | G2: =SDT!H12 -> 30000000 | H2: =SUM(E2:G2) -> 61600000 | I2: =SDT!J12 -> 30000000 | J2: =SDT!K12 -> 30000000 | K2: =SDT!L12 -> 30000000 | L2: =SUM(I2:K2) -> 90000000 | M2: =SDT!N12 -> 30000000 | N2: =SDT!O12 -> 30000000 | O2: =SDT!P12 -> 30000000 | P2: =SUM(M2:O2) -> 90000000 | Q2: =SDT!R12 -> 30000000 | R2: =SDT!S12 -> 30000000 | S2: =SDT!T12 -> 30000000 | T2: =SUM(Q2:S2) -> 90000000 | U2: =H2+L2+P2+T2 -> 331600000
D3: TST1 | E3: ='TST1'!F12 -> 535987000 | F3: ='TST1'!G12 -> 68000000 | G3: ='TST1'!H12 -> 68000000 | H3: =SUM(E3:G3) -> 671987000 | I3: ='TST1'!J12 -> 68000000 | J3: ='TST1'!K12 -> 68000000 | K3: ='TST1'!L12 -> 68000000 | L3: =SUM(I3:K3) -> 204000000 | M3: ='TST1'!N12 -> 68000000 | N3: ='TST1'!O12 -> 68000000 | O3: ='TST1'!P12 -> 68000000 | P3: =SUM(M3:O3) -> 204000000 | Q3: ='TST1'!R12 -> 68000000 | R3: ='TST1'!S12 -> 68000000 | S3: ='TST1'!T12 -> 68000000 | T3: =SUM(Q3:S3) -> 204000000 | U3: =H3+L3+P3+T3 -> 1283987000
D4: TST2 | E4: ='TST2'!F12 -> 581480000 | F4: ='TST2'!G12 -> 155000000 | G4: ='TST2'!H12 -> 155000000 | H4: =SUM(E4:G4) -> 891480000 | I4: ='TST2'!J12 -> 155000000 | J4: ='TST2'!K12 -> 155000000 | K4: ='TST2'!L12 -> 155000000 | L4: =SUM(I4:K4) -> 465000000 | M4: ='TST2'!N12 -> 155000000 | N4: ='TST2'!O12 -> 155000000 | O4: ='TST2'!P12 -> 155000000 | P4: =SUM(M4:O4) -> 465000000 | Q4: ='TST2'!R12 -> 155000000 | R4: ='TST2'!S12 -> 155000000 | S4: ='TST2'!T12 -> 155000000 | T4: =SUM(Q4:S4) -> 465000000 | U4: =H4+L4+P4+T4 -> 2286480000
D5: EST1 | E5: ='EST1'!F12 -> 0 | F5: ='EST1'!G12 -> 120000000 | G5: ='EST1'!H12 -> 120000000 | H5: =SUM(E5:G5) -> 240000000 | I5: ='EST1'!J12 -> 120000000 | J5: ='EST1'!K12 -> 120000000 | K5: ='EST1'!L12 -> 120000000 | L5: =SUM(I5:K5) -> 360000000 | M5: ='EST1'!N12 -> 120000000 | N5: ='EST1'!O12 -> 120000000 | O5: ='EST1'!P12 -> 120000000 | P5: =SUM(M5:O5) -> 360000000 | Q5: ='EST1'!R12 -> 120000000 | R5: ='EST1'!S12 -> 120000000 | S5: ='EST1'!T12 -> 120000000 | T5: =SUM(Q5:S5) -> 360000000 | U5: =H5+L5+P5+T5 -> 1320000000
D6: EST2 | E6: ='EST2'!F12 -> 0 | F6: ='EST2'!G12 -> 5000000 | G6: ='EST2'!H12 -> 5000000 | H6: =SUM(E6:G6) -> 10000000 | I6: ='EST2'!J12 -> 5000000 | J6: ='EST2'!K12 -> 5000000 | K6: ='EST2'!L12 -> 5000000 | L6: =SUM(I6:K6) -> 15000000 | M6: ='EST2'!N12 -> 5000000 | N6: ='EST2'!O12 -> 5000000 | O6: ='EST2'!P12 -> 5000000 | P6: =SUM(M6:O6) -> 15000000 | Q6: ='EST2'!R12 -> 5000000 | R6: ='EST2'!S12 -> 5000000 | S6: ='EST2'!T12 -> 5000000 | T6: =SUM(Q6:S6) -> 15000000 | U6: =H6+L6+P6+T6 -> 55000000
D7: EST3 | E7: ='EST3'!F12 -> 0 | F7: ='EST3'!G12 -> 1000000 | G7: ='EST3'!H12 -> 1000000 | H7: =SUM(E7:G7) -> 2000000 | I7: ='EST3'!J12 -> 1000000 | J7: ='EST3'!K12 -> 1000000 | K7: ='EST3'!L12 -> 1000000 | L7: =SUM(I7:K7) -> 3000000 | M7: ='EST3'!N12 -> 1000000 | N7: ='EST3'!O12 -> 1000000 | O7: ='EST3'!P12 -> 1000000 | P7: =SUM(M7:O7) -> 3000000 | Q7: ='EST3'!R12 -> 1000000 | R7: ='EST3'!S12 -> 1000000 | S7: ='EST3'!T12 -> 1000000 | T7: =SUM(Q7:S7) -> 3000000 | U7: =H7+L7+P7+T7 -> 11000000
B8: 계 | E8: =SUM(E2:E7) -> 1119067000 | F8: =SUM(F2:F7) -> 379000000 | G8: =SUM(G2:G7) -> 379000000 | H8: =SUM(H2:H7) -> 1877067000 | I8: =SUM(I2:I7) -> 379000000 | J8: =SUM(J2:J7) -> 379000000 | K8: =SUM(K2:K7) -> 379000000 | L8: =SUM(L2:L7) -> 1137000000 | ... U8: =SUM(U2:U7) -> 5288067000
B9: 매입 | D9: SDT | E9: =SDT!F26 -> 86000 | F9: =SDT!G26 -> 80000 | G9: =SDT!H26 -> 80000 | H9: =SUM(E9:G9) -> 246000 | I9: =SDT!J26 -> 80000 | J9: =SDT!K26 -> 80000 | K9: =SDT!L26 -> 80000 | L9: =SUM(I9:K9) -> 240000 | M9: =SDT!N26 -> 80000 | N9: =SDT!O26 -> 80000 | O9: =SDT!P26 -> 80000 | P9: =SUM(M9:O9) -> 240000 | Q9: =SDT!R26 -> 80000 | R9: =SDT!S26 -> 80000 | S9: =SDT!T26 -> 80000 | T9: =SUM(Q9:S9) -> 240000 | U9: =H9+L9+P9+T9 -> 966000
D10: TST1 | E10: ='TST1'!F26 -> 234537000 | F10: ='TST1'!G26 -> 30995000 | G10: ='TST1'!H26 -> 30995000 | H10: =SUM(E10:G10) -> 296527000 | I10: ='TST1'!J26 -> 30995000 | J10: ='TST1'!K26 -> 30995000 | K10: ='TST1'!L26 -> 30995000 | L10: =SUM(I10:K10) -> 92985000 | M10: ='TST1'!N26 -> 30995000 | N10: ='TST1'!O26 -> 30995000 | O10: ='TST1'!P26 -> 30995000 | P10: =SUM(M10:O10) -> 92985000 | Q10: ='TST1'!R26 -> 30995000 | R10: ='TST1'!S26 -> 30995000 | S10: ='TST1'!T26 -> 30995000 | T10: =SUM(Q10:S10) -> 92985000 | U10: =H10+L10+P10+T10 -> 575482000
D11: TST2 | E11: ='TST2'!F26 -> 101545000 | F11: ='TST2'!G26 -> 78029000 | G11: ='TST2'!H26 -> 78029000 | H11: =SUM(E11:G11) -> 257603000 | I11: ='TST2'!J26 -> 78029000 | J11: ='TST2'!K26 -> 78029000 | K11: ='TST2'!L26 -> 78029000 | L11: =SUM(I11:K11) -> 234087000 | M11: ='TST2'!N26 -> 78029000 | N11: ='TST2'!O26 -> 78029000 | O11: ='TST2'!P26 -> 78029000 | P11: =SUM(M11:O11) -> 234087000 | Q11: ='TST2'!R26 -> 78029000 | R11: ='TST2'!S26 -> 78029000 | S11: ='TST2'!T26 -> 78029000 | T11: =SUM(Q11:S11) -> 234087000 | U11: =H11+L11+P11+T11 -> 959864000
D12: EST1 | E12: ='EST1'!F26 -> 1100000 | F12: ='EST1'!G26 -> 2100000 | G12: ='EST1'!H26 -> 2100000 | H12: =SUM(E12:G12) -> 5300000 | I12: ='EST1'!J26 -> 2100000 | J12: ='EST1'!K26 -> 2100000 | K12: ='EST1'!L26 -> 2100000 | L12: =SUM(I12:K12) -> 6300000 | M12: ='EST1'!N26 -> 2100000 | N12: ='EST1'!O26 -> 2100000 | O12: ='EST1'!P26 -> 2100000 | P12: =SUM(M12:O12) -> 6300000 | Q12: ='EST1'!R26 -> 2100000 | R12: ='EST1'!S26 -> 2100000 | S12: ='EST1'!T26 -> 2100000 | T12: =SUM(Q12:S12) -> 6300000 | U12: =H12+L12+P12+T12 -> 24200000
D13: EST2 | E13: ='EST2'!F26 -> 2081000 | F13: ='EST2'!G26 -> 0 | G13: ='EST2'!H26 -> 0 | H13: =SUM(E13:G13) -> 2081000 | I13: ='EST2'!J26 -> 0 | J13: ='EST2'!K26 -> 0 | K13: ='EST2'!L26 -> 0 | L13: =SUM(I13:K13) -> 0 | M13: ='EST2'!N26 -> 0 | N13: ='EST2'!O26 -> 0 | O13: ='EST2'!P26 -> 0 | P13: =SUM(M13:O13) -> 0 | Q13: ='EST2'!R26 -> 0 | R13: ='EST2'!S26 -> 0 | S13: ='EST2'!T26 -> 0 | T13: =SUM(Q13:S13) -> 0 | U13: =H13+L13+P13+T13 -> 2081000
D14: EST3 | E14: ='EST3'!F26 -> 0 | F14: ='EST3'!G26 -> 0 | G14: ='EST3'!H26 -> 0 | H14: =SUM(E14:G14) -> 0 | I14: ='EST3'!J26 -> 0 | J14: ='EST3'!K26 -> 0 | K14: ='EST3'!L26 -> 0 | L14: =SUM(I14:K14) -> 0 | M14: ='EST3'!N26 -> 0 | N14: ='EST3'!O26 -> 0 | O14: ='EST3'!P26 -> 0 | P14: =SUM(M14:O14) -> 0 | Q14: ='EST3'!R26 -> 0 | R14: ='EST3'!S26 -> 0 | S14: ='EST3'!T26 -> 0 | T14: =SUM(Q14:S14) -> 0 | U14: =H14+L14+P14+T14 -> 0
B15: 계 | E15: =SUM(E9:E14) -> 339349000 | F15: =SUM(F9:F14) -> 111204000 | G15: =SUM(G9:G14) -> 111204000 | H15: =SUM(H9:H14) -> 561757000 | I15: =SUM(I9:I14) -> 111204000 | J15: =SUM(J9:J14) -> 111204000 | K15: =SUM(K9:K14) -> 111204000 | L15: =SUM(L9:L14) -> 333612000 | ... U15: =SUM(U9:U14) -> 1562593000
B16: 매출이익 | D16: 예산 | H16: 2070000000 | L16: 935000000 | P16: 935000000 | T16: 2010000000 | U16: =T16+P16+L16+H16 -> 5950000000
D17: SDT | E17: =E2-E9 -> 1514000 | F17: =F2-F9 -> 29920000 | G17: =G2-G9 -> 29920000 | H17: =SUM(E17:G17) -> 61354000 | I17: =I2-I9 -> 29920000 | J17: =J2-J9 -> 29920000 | K17: =K2-K9 -> 29920000 | L17: =SUM(I17:K17) -> 89760000 | M17: =M2-M9 -> 29920000 | N17: =N2-N9 -> 29920000 | O17: =O2-O9 -> 29920000 | P17: =SUM(M17:O17) -> 89760000 | Q17: =Q2-Q9 -> 29920000 | R17: =R2-R9 -> 29920000 | S17: =S2-S9 -> 29920000 | T17: =SUM(Q17:S17) -> 89760000 | U17: =H17+L17+P17+T17 -> 330634000
D18: TST1 | E18: =E3-E10 -> 301450000 | F18: =F3-F10 -> 37005000 | G18: =G3-G10 -> 37005000 | H18: =SUM(E18:G18) -> 375460000 | I18: =I3-I10 -> 37005000 | J18: =J3-J10 -> 37005000 | K18: =K3-K10 -> 37005000 | L18: =SUM(I18:K18) -> 111015000 | M18: =M3-M10 -> 37005000 | N18: =N3-N10 -> 37005000 | O18: =O3-O10 -> 37005000 | P18: =SUM(M18:O18) -> 111015000 | Q18: =Q3-Q10 -> 37005000 | R18: =R3-R10 -> 37005000 | S18: =S3-S10 -> 37005000 | T18: =SUM(Q18:S18) -> 111015000 | U18: =H18+L18+P18+T18 -> 708505000
D19: TST2 | E19: =E4-E11 -> 479935000 | F19: =F4-F11 -> 76971000 | G19: =G4-G11 -> 76971000 | H19: =SUM(E19:G19) -> 633877000 | I19: =I4-I11 -> 76971000 | J19: =J4-J11 -> 76971000 | K19: =K4-K11 -> 76971000 | L19: =SUM(I19:K19) -> 230913000 | M19: =M4-M11 -> 76971000 | N19: =N4-N11 -> 76971000 | O19: =O4-O11 -> 76971000 | P19: =SUM(M19:O19) -> 230913000 | Q19: =Q4-Q11 -> 76971000 | R19: =R4-R11 -> 76971000 | S19: =S4-S11 -> 76971000 | T19: =SUM(Q19:S19) -> 230913000 | U19: =H19+L19+P19+T19 -> 1326616000
D20: EST1 | E20: =E5-E12 -> -1100000 | F20: =F5-F12 -> 117900000 | G20: =G5-G12 -> 117900000 | H20: =SUM(E20:G20) -> 234700000 | I20: =I5-I12 -> 117900000 | J20: =J5-J12 -> 117900000 | K20: =K5-K12 -> 117900000 | L20: =SUM(I20:K20) -> 353700000 | M20: =M5-M12 -> 117900000 | N20: =N5-N12 -> 117900000 | O20: =O5-O12 -> 117900000 | P20: =SUM(M20:O20) -> 353700000 | Q20: =Q5-Q12 -> 117900000 | R20: =R5-R12 -> 117900000 | S20: =S5-S12 -> 117900000 | T20: =SUM(Q20:S20) -> 353700000 | U20: =H20+L20+P20+T20 -> 1295800000
D21: EST2 | E21: =E6-E13 -> -2081000 | F21: =F6-F13 -> 5000000 | G21: =G6-G13 -> 5000000 | H21: =SUM(E21:G21) -> 7919000 | I21: =I6-I13 -> 5000000 | J21: =J6-J13 -> 5000000 | K21: =K6-K13 -> 5000000 | L21: =SUM(I21:K21) -> 15000000 | M21: =M6-M13 -> 5000000 | N21: =N6-N13 -> 5000000 | O21: =O6-O13 -> 5000000 | P21: =SUM(M21:O21) -> 15000000 | Q21: =Q6-Q13 -> 5000000 | R21: =R6-R13 -> 5000000 | S21: =S6-S13 -> 5000000 | T21: =SUM(Q21:S21) -> 15000000 | U21: =H21+L21+P21+T21 -> 52919000
D22: EST3 | E22: =E7-E14 -> 0 | F22: =F7-F14 -> 1000000 | G22: =G7-G14 -> 1000000 | H22: =SUM(E22:G22) -> 2000000 | I22: =I7-I14 -> 1000000 | J22: =J7-J14 -> 1000000 | K22: =K7-K14 -> 1000000 | L22: =SUM(I22:K22) -> 3000000 | M22: =M7-M14 -> 1000000 | N22: =N7-N14 -> 1000000 | O22: =O7-O14 -> 1000000 | P22: =SUM(M22:O22) -> 3000000 | Q22: =Q7-Q14 -> 1000000 | R22: =R7-R14 -> 1000000 | S22: =S7-S14 -> 1000000 | T22: =SUM(Q22:S22) -> 3000000 | U22: =H22+L22+P22+T22 -> 11000000
B23: 계 | E23: =SUM(E17:E22) -> 779718000 | F23: =SUM(F17:F22) -> 267796000 | G23: =SUM(G17:G22) -> 267796000 | H23: =SUM(H17:H22) -> 1315310000 | I23: =SUM(I17:I22) -> 267796000 | J23: =SUM(J17:J22) -> 267796000 | K23: =SUM(K17:K22) -> 267796000 | L23: =SUM(L17:L22) -> 803388000 | ... U23: =SUM(U17:U22) -> 3725474000
B24: 직접 비용 | D24: SDT | E24: =SDT!F124 -> 33217000 | F24: =SDT!G124 -> 33247000 | G24: =SDT!H124 -> 33247000 | H24: =SUM(E24:G24) -> 99711000 | I24: =SDT!J124 -> 33247000 | J24: =SDT!K124 -> 33247000 | K24: =SDT!L124 -> 33247000 | L24: =SUM(I24:K24) -> 99741000 | M24: =SDT!N124 -> 33247000 | N24: =SDT!O124 -> 33247000 | O24: =SDT!P124 -> 33247000 | P24: =SUM(M24:O24) -> 99741000 | Q24: =SDT!R124 -> 33247000 | R24: =SDT!S124 -> 33247000 | S24: =SDT!T124 -> 33247000 | T24: =SUM(Q24:S24) -> 99741000 | U24: =H24+L24+P24+T24 -> 398934000
D25: TST1 | E25: ='TST1'!F124 -> 46146000 | F25: ='TST1'!G124 -> 46709000 | G25: ='TST1'!H124 -> 46709000 | H25: =SUM(E25:G25) -> 139564000 | I25: ='TST1'!J124 -> 46709000 | J25: ='TST1'!K124 -> 46709000 | K25: ='TST1'!L124 -> 46709000 | L25: =SUM(I25:K25) -> 140127000 | M25: ='TST1'!N124 -> 46709000 | N25: ='TST1'!O124 -> 46709000 | O25: ='TST1'!P124 -> 46709000 | P25: =SUM(M25:O25) -> 140127000 | Q25: ='TST1'!R124 -> 46709000 | R25: ='TST1'!S124 -> 46709000 | S25: ='TST1'!T124 -> 46709000 | T25: =SUM(Q25:S25) -> 140127000 | U25: =H25+L25+P25+T25 -> 559945000
D26: TST2 | E26: ='TST2'!F124 -> 28732000 | F26: ='TST2'!G124 -> 29254000 | G26: ='TST2'!H124 -> 29254000 | H26: =SUM(E26:G26) -> 87240000 | I26: ='TST2'!J124 -> 29254000 | J26: ='TST2'!K124 -> 29254000 | K26: ='TST2'!L124 -> 29254000 | L26: =SUM(I26:K26) -> 87762000 | M26: ='TST2'!N124 -> 29254000 | N26: ='TST2'!O124 -> 29254000 | O26: ='TST2'!P124 -> 29254000 | P26: =SUM(M26:O26) -> 87762000 | Q26: ='TST2'!R124 -> 29254000 | R26: ='TST2'!S124 -> 29254000 | S26: ='TST2'!T124 -> 29254000 | T26: =SUM(Q26:S26) -> 87762000 | U26: =H26+L26+P26+T26 -> 350526000
D27: EST1 | E27: ='EST1'!F124 -> 43911000 | F27: ='EST1'!G124 -> 43846000 | G27: ='EST1'!H124 -> 43846000 | H27: =SUM(E27:G27) -> 131603000 | I27: ='EST1'!J124 -> 43846000 | J27: ='EST1'!K124 -> 43846000 | K27: ='EST1'!L124 -> 43846000 | L27: =SUM(I27:K27) -> 131538000 | M27: ='EST1'!N124 -> 43846000 | N27: ='EST1'!O124 -> 43846000 | O27: ='EST1'!P124 -> 43846000 | P27: =SUM(M27:O27) -> 131538000 | Q27: ='EST1'!R124 -> 43846000 | R27: ='EST1'!S124 -> 43846000 | S27: ='EST1'!T124 -> 43846000 | T27: =SUM(Q27:S27) -> 131538000 | U27: =H27+L27+P27+T27 -> 526217000
D28: EST2 | E28: ='EST2'!F124 -> 30893000 | F28: ='EST2'!G124 -> 30847000 | G28: ='EST2'!H124 -> 30847000 | H28: =SUM(E28:G28) -> 92587000 | I28: ='EST2'!J124 -> 30847000 | J28: ='EST2'!K124 -> 30847000 | K28: ='EST2'!L124 -> 30847000 | L28: =SUM(I28:K28) -> 92541000 | M28: ='EST2'!N124 -> 30847000 | N28: ='EST2'!O124 -> 30847000 | O28: ='EST2'!P124 -> 30847000 | P28: =SUM(M28:O28) -> 92541000 | Q28: ='EST2'!R124 -> 30847000 | R28: ='EST2'!S124 -> 30847000 | S28: ='EST2'!T124 -> 30847000 | T28: =SUM(Q28:S28) -> 92541000 | U28: =H28+L28+P28+T28 -> 370210000
D29: EST3 | E29: ='EST3'!F124 -> 16434000 | F29: ='EST3'!G124 -> 16410000 | G29: ='EST3'!H124 -> 16410000 | H29: =SUM(E29:G29) -> 49254000 | I29: ='EST3'!J124 -> 16410000 | J29: ='EST3'!K124 -> 16410000 | K29: ='EST3'!L124 -> 16410000 | L29: =SUM(I29:K29) -> 49230000 | M29: ='EST3'!N124 -> 16410000 | N29: ='EST3'!O124 -> 16410000 | O29: ='EST3'!P124 -> 16410000 | P29: =SUM(M29:O29) -> 49230000 | Q29: ='EST3'!R124 -> 16410000 | R29: ='EST3'!S124 -> 16410000 | S29: ='EST3'!T124 -> 16410000 | T29: =SUM(Q29:S29) -> 49230000 | U29: =H29+L29+P29+T29 -> 196944000
B30: 소계 | E30: =SUM(E24:E29) -> 199333000 | F30: =SUM(F24:F29) -> 200313000 | G30: =SUM(G24:G29) -> 200313000 | H30: =SUM(H24:H29) -> 599959000 | I30: =SUM(I24:I29) -> 200313000 | J30: =SUM(J24:J29) -> 200313000 | K30: =SUM(K24:K29) -> 200313000 | L30: =SUM(L24:L29) -> 600939000 | ... U30: =SUM(U24:U29) -> 2402776000
B31: 간접 비용 | D31: SDT | E31: =ROUND((간접!$F$124*팀별실적!E24)/팀별실적!$E$30,-3) -> 9888000 | F31: =ROUND((간접!$G$124*팀별실적!F24)/팀별실적!$F$30,-3) -> 9514000 | G31: =ROUND((간접!$H$124*팀별실적!G24)/팀별실적!$G$30,-3) -> 9514000 | H31: =SUM(E31:G31) -> 28916000 | I31: =ROUND((간접!$J$124*팀별실적!I24)/팀별실적!$I$30,-3) -> 9514000 | J31: =ROUND((간접!$K$124*팀별실적!J24)/팀별실적!$J$30,-3) -> 9514000 | K31: =ROUND((간접!$L$124*팀별실적!K24)/팀별실적!$K$30,-3) -> 9514000 | L31: =SUM(I31:K31) -> 28542000 | M31: =ROUND((간접!$N$124*팀별실적!M24)/팀별실적!$M$30,-3) -> 9514000 | N31: =ROUND((간접!$O$124*팀별실적!N24)/팀별실적!$N$30,-3) -> 9514000 | O31: =ROUND((간접!$P$124*팀별실적!O24)/팀별실적!$O$30,-3) -> 9514000 | P31: =SUM(M31:O31) -> 28542000 | Q31: =ROUND((간접!$R$124*팀별실적!Q24)/팀별실적!$Q$30,-3) -> 9514000 | R31: =ROUND((간접!$S$124*팀별실적!R24)/팀별실적!$R$30,-3) -> 9514000 | S31: =ROUND((간접!$T$124*팀별실적!S24)/팀별실적!$S$30,-3) -> 9514000 | T31: =SUM(Q31:S31) -> 28542000 | U31: =H31+L31+P31+T31 -> 114542000
D32: TST1 | E32: =ROUND((간접!$F$124*팀별실적!E25)/팀별실적!$E$30,-3) -> 13736000 | F32: =ROUND((간접!$G$124*팀별실적!F25)/팀별실적!$F$30,-3) -> 13366000 | G32: =ROUND((간접!$H$124*팀별실적!G25)/팀별실적!$G$30,-3) -> 13366000 | H32: =SUM(E32:G32) -> 40468000 | I32: =ROUND((간접!$J$124*팀별실적!I25)/팀별실적!$I$30,-3) -> 13366000 | J32: =ROUND((간접!$K$124*팀별실적!J25)/팀별실적!$J$30,-3) -> 13366000 | K32: =ROUND((간접!$L$124*팀별실적!K25)/팀별실적!$K$30,-3) -> 13366000 | L32: =SUM(I32:K32) -> 40098000 | M32: =ROUND((간접!$N$124*팀별실적!M25)/팀별실적!$M$30,-3) -> 13366000 | N32: =ROUND((간접!$O$124*팀별실적!N25)/팀별실적!$N$30,-3) -> 13366000 | O32: =ROUND((간접!$P$124*팀별실적!O25)/팀별실적!$O$30,-3) -> 13366000 | P32: =SUM(M32:O32) -> 40098000 | Q32: =ROUND((간접!$R$124*팀별실적!Q25)/팀별실적!$Q$30,-3) -> 13366000 | R32: =ROUND((간접!$S$124*팀별실적!R25)/팀별실적!$R$30,-3) -> 13366000 | S32: =ROUND((간접!$T$124*팀별실적!S25)/팀별실적!$S$30,-3) -> 13366000 | T32: =SUM(Q32:S32) -> 40098000 | U32: =H32+L32+P32+T32 -> 160762000
D33: TST2 | E33: =ROUND((간접!$F$124*팀별실적!E26)/팀별실적!$E$30,-3)-1000 -> 8552000 | F33: =ROUND((간접!$G$124*팀별실적!F26)/팀별실적!$F$30,-3) -> 8371000 | G33: =ROUND((간접!$H$124*팀별실적!G26)/팀별실적!$G$30,-3) -> 8371000 | H33: =SUM(E33:G33) -> 25294000 | I33: =ROUND((간접!$J$124*팀별실적!I26)/팀별실적!$I$30,-3) -> 8371000 | J33: =ROUND((간접!$K$124*팀별실적!J26)/팀별실적!$J$30,-3) -> 8371000 | K33: =ROUND((간접!$L$124*팀별실적!K26)/팀별실적!$K$30,-3) -> 8371000 | L33: =SUM(I33:K33) -> 25113000 | M33: =ROUND((간접!$N$124*팀별실적!M26)/팀별실적!$M$30,-3) -> 8371000 | N33: =ROUND((간접!$O$124*팀별실적!N26)/팀별실적!$N$30,-3) -> 8371000 | O33: =ROUND((간접!$P$124*팀별실적!O26)/팀별실적!$O$30,-3) -> 8371000 | P33: =SUM(M33:O33) -> 25113000 | Q33: =ROUND((간접!$R$124*팀별실적!Q26)/팀별실적!$Q$30,-3) -> 8371000 | R33: =ROUND((간접!$S$124*팀별실적!R26)/팀별실적!$R$30,-3) -> 8371000 | S33: =ROUND((간접!$T$124*팀별실적!S26)/팀별실적!$S$30,-3) -> 8371000 | T33: =SUM(Q33:S33) -> 25113000 | U33: =H33+L33+P33+T33 -> 100633000
D34: EST1 | E34: =ROUND((간접!$F$124*팀별실적!E27)/팀별실적!$E$30,-3) -> 13071000 | F34: =ROUND((간접!$G$124*팀별실적!F27)/팀별실적!$F$30,-3) -> 12546000 | G34: =ROUND((간접!$H$124*팀별실적!G27)/팀별실적!$G$30,-3) -> 12546000 | H34: =SUM(E34:G34) -> 38163000 | I34: =ROUND((간접!$J$124*팀별실적!I27)/팀별실적!$I$30,-3) -> 12546000 | J34: =ROUND((간접!$K$124*팀별실적!J27)/팀별실적!$J$30,-3) -> 12546000 | K34: =ROUND((간접!$L$124*팀별실적!K27)/팀별실적!$K$30,-3) -> 12546000 | L34: =SUM(I34:K34) -> 37638000 | M34: =ROUND((간접!$N$124*팀별실적!M27)/팀별실적!$M$30,-3) -> 12546000 | N34: =ROUND((간접!$O$124*팀별실적!N27)/팀별실적!$N$30,-3) -> 12546000 | O34: =ROUND((간접!$P$124*팀별실적!O27)/팀별실적!$O$30,-3) -> 12546000 | P34: =SUM(M34:O34) -> 37638000 | Q34: =ROUND((간접!$R$124*팀별실적!Q27)/팀별실적!$Q$30,-3) -> 12546000 | R34: =ROUND((간접!$S$124*팀별실적!R27)/팀별실적!$R$30,-3) -> 12546000 | S34: =ROUND((간접!$T$124*팀별실적!S27)/팀별실적!$S$30,-3) -> 12546000 | T34: =SUM(Q34:S34) -> 37638000 | U34: =H34+L34+P34+T34 -> 151077000
D35: EST2 | E35: =ROUND((간접!$F$124*팀별실적!E28)/팀별실적!$E$30,-3) -> 9196000 | F35: =ROUND((간접!$G$124*팀별실적!F28)/팀별실적!$F$30,-3) -> 8827000 | G35: =ROUND((간접!$H$124*팀별실적!G28)/팀별실적!$G$30,-3) -> 8827000 | H35: =SUM(E35:G35) -> 26850000 | I35: =ROUND((간접!$J$124*팀별실적!I28)/팀별실적!$I$30,-3) -> 8827000 | J35: =ROUND((간접!$K$124*팀별실적!J28)/팀별실적!$J$30,-3) -> 8827000 | K35: =ROUND((간접!$L$124*팀별실적!K28)/팀별실적!$K$30,-3) -> 8827000 | L35: =SUM(I35:K35) -> 26481000 | M35: =ROUND((간접!$N$124*팀별실적!M28)/팀별실적!$M$30,-3) -> 8827000 | N35: =ROUND((간접!$O$124*팀별실적!N28)/팀별실적!$N$30,-3) -> 8827000 | O35: =ROUND((간접!$P$124*팀별실적!O28)/팀별실적!$O$30,-3) -> 8827000 | P35: =SUM(M35:O35) -> 26481000 | Q35: =ROUND((간접!$R$124*팀별실적!Q28)/팀별실적!$Q$30,-3) -> 8827000 | R35: =ROUND((간접!$S$124*팀별실적!R28)/팀별실적!$R$30,-3) -> 8827000 | S35: =ROUND((간접!$T$124*팀별실적!S28)/팀별실적!$S$30,-3) -> 8827000 | T35: =SUM(Q35:S35) -> 26481000 | U35: =H35+L35+P35+T35 -> 106293000
D36: EST3 | E36: =ROUND((간접!$F$124*팀별실적!E29)/팀별실적!$E$30,-3) -> 4892000 | F36: =ROUND((간접!$G$124*팀별실적!F29)/팀별실적!$F$30,-3) -> 4696000 | G36: =ROUND((간접!$H$124*팀별실적!G29)/팀별실적!$G$30,-3) -> 4696000 | H36: =SUM(E36:G36) -> 14284000 | I36: =ROUND((간접!$J$124*팀별실적!I29)/팀별실적!$I$30,-3) -> 4696000 | J36: =ROUND((간접!$K$124*팀별실적!J29)/팀별실적!$J$30,-3) -> 4696000 | K36: =ROUND((간접!$L$124*팀별실적!K29)/팀별실적!$K$30,-3) -> 4696000 | L36: =SUM(I36:K36) -> 14088000 | M36: =ROUND((간접!$N$124*팀별실적!M29)/팀별실적!$M$30,-3) -> 4696000 | N36: =ROUND((간접!$O$124*팀별실적!N29)/팀별실적!$N$30,-3) -> 4696000 | O36: =ROUND((간접!$P$124*팀별실적!O29)/팀별실적!$O$30,-3) -> 4696000 | P36: =SUM(M36:O36) -> 14088000 | Q36: =ROUND((간접!$R$124*팀별실적!Q29)/팀별실적!$Q$30,-3) -> 4696000 | R36: =ROUND((간접!$S$124*팀별실적!R29)/팀별실적!$R$30,-3) -> 4696000 | S36: =ROUND((간접!$T$124*팀별실적!S29)/팀별실적!$S$30,-3) -> 4696000 | T36: =SUM(Q36:S36) -> 14088000 | U36: =H36+L36+P36+T36 -> 56548000
B37: 소계 | E37: =SUM(E31:E36) -> 59335000 | F37: =SUM(F31:F36) -> 57320000 | G37: =SUM(G31:G36) -> 57320000 | H37: =SUM(H31:H36) -> 173975000 | I37: =SUM(I31:I36) -> 57320000 | J37: =SUM(J31:J36) -> 57320000 | K37: =SUM(K31:K36) -> 57320000 | L37: =SUM(L31:L36) -> 171960000 | ... U37: =SUM(U31:U36) -> 689855000
B38: 계 | E38: =E37+E30 -> 258668000 | F38: =F37+F30 -> 257633000 | G38: =G37+G30 -> 257633000 | H38: =H37+H30 -> 773934000 | I38: =I37+I30 -> 257633000 | J38: =J37+J30 -> 257633000 | K38: =K37+K30 -> 257633000 | L38: =L37+L30 -> 772899000 | ... U38: =U37+U30 -> 3092631000
B39: 전체경비 | D39: 예산 | H39: 1241410000 | L39: 1269244000 | P39: 1308090000 | T39: 1225641000 | U39: =T39+P39+L39+H39 -> 5044385000
B40: 영업이익 | D40: SDT | E40: =E17-E24-E31 -> -41591000 | F40: =F17-F24-F31 -> -12841000 | G40: =G17-G24-G31 -> -12841000 | H40: =SUM(E40:G40) -> -67273000 | I40: =I17-I24-I31 -> -12841000 | J40: =J17-J24-J31 -> -12841000 | K40: =K17-K24-K31 -> -12841000 | L40: =SUM(I40:K40) -> -38523000 | M40: =M17-M24-M31 -> -12841000 | N40: =N17-N24-N31 -> -12841000 | O40: =O17-O24-O31 -> -12841000 | P40: =SUM(M40:O40) -> -38523000 | Q40: =Q17-Q24-Q31 -> -12841000 | R40: =R17-R24-R31 -> -12841000 | S40: =S17-S24-S31 -> -12841000 | T40: =SUM(Q40:S40) -> -38523000 | U40: =H40+L40+P40+T40 -> -182842000
D41: TST1 | E41: =E18-E25-E32 -> 241568000 | F41: =F18-F25-F32 -> -23070000 | G41: =G18-G25-G32 -> -23070000 | H41: =SUM(E41:G41) -> 195428000 | I41: =I18-I25-I32 -> -23070000 | J41: =J18-J25-J32 -> -23070000 | K41: =K18-K25-K32 -> -23070000 | L41: =SUM(I41:K41) -> -69210000 | M41: =M18-M25-M32 -> -23070000 | N41: =N18-N25-N32 -> -23070000 | O41: =O18-O25-O32 -> -23070000 | P41: =SUM(M41:O41) -> -69210000 | Q41: =Q18-Q25-Q32 -> -23070000 | R41: =R18-R25-R32 -> -23070000 | S41: =S18-S25-S32 -> -23070000 | T41: =SUM(Q41:S41) -> -69210000 | U41: =H41+L41+P41+T41 -> -12202000
D42: TST2 | E42: =E19-E26-E33 -> 442651000 | F42: =F19-F26-F33 -> 39346000 | G42: =G19-G26-G33 -> 39346000 | H42: =SUM(E42:G42) -> 521343000 | I42: =I19-I26-I33 -> 39346000 | J42: =J19-J26-J33 -> 39346000 | K42: =K19-K26-K33 -> 39346000 | L42: =SUM(I42:K42) -> 118038000 | M42: =M19-M26-M33 -> 39346000 | N42: =N19-N26-N33 -> 39346000 | O42: =O19-O26-O33 -> 39346000 | P42: =SUM(M42:O42) -> 118038000 | Q42: =Q19-Q26-Q33 -> 39346000 | R42: =R19-R26-R33 -> 39346000 | S42: =S19-S26-S33 -> 39346000 | T42: =SUM(Q42:S42) -> 118038000 | U42: =H42+L42+P42+T42 -> 875457000
D43: EST1 | E43: =E20-E27-E34 -> -58082000 | F43: =F20-F27-F34 -> 61508000 | G43: =G20-G27-G34 -> 61508000 | H43: =SUM(E43:G43) -> 64934000 | I43: =I20-I27-I34 -> 61508000 | J43: =J20-J27-J34 -> 61508000 | K43: =K20-K27-K34 -> 61508000 | L43: =SUM(I43:K43) -> 184524000 | M43: =M20-M27-M34 -> 61508000 | N43: =N20-N27-N34 -> 61508000 | O43: =O20-O27-O34 -> 61508000 | P43: =SUM(M43:O43) -> 184524000 | Q43: =Q20-Q27-Q34 -> 61508000 | R43: =R20-R27-R34 -> 61508000 | S43: =S20-S27-S34 -> 61508000 | T43: =SUM(Q43:S43) -> 184524000 | U43: =H43+L43+P43+T43 -> 618506000
D44: EST2 | E44: =E21-E28-E35 -> -42170000 | F44: =F21-F28-F35 -> -34674000 | G44: =G21-G28-G35 -> -34674000 | H44: =SUM(E44:G44) -> -111518000 | I44: =I21-I28-I35 -> -34674000 | J44: =J21-J28-J35 -> -34674000 | K44: =K21-K28-K35 -> -34674000 | L44: =SUM(I44:K44) -> -104022000 | M44: =M21-M28-M35 -> -34674000 | N44: =N21-N28-N35 -> -34674000 | O44: =O21-O28-O35 -> -34674000 | P44: =SUM(M44:O44) -> -104022000 | Q44: =Q21-Q28-Q35 -> -34674000 | R44: =R21-R28-R35 -> -34674000 | S44: =S21-S28-S35 -> -34674000 | T44: =SUM(Q44:S44) -> -104022000 | U44: =H44+L44+P44+T44 -> -423584000
D45: EST3 | E45: =E22-E29-E36 -> -21326000 | F45: =F22-F29-F36 -> -20106000 | G45: =G22-G29-G36 -> -20106000 | H45: =SUM(E45:G45) -> -61538000 | I45: =I22-I29-I36 -> -20106000 | J45: =J22-J29-J36 -> -20106000 | K45: =K22-K29-K36 -> -20106000 | L45: =SUM(I45:K45) -> -60318000 | M45: =M22-M29-M36 -> -20106000 | N45: =N22-N29-N36 -> -20106000 | O45: =O22-O29-O36 -> -20106000 | P45: =SUM(M45:O45) -> -60318000 | Q45: =Q22-Q29-Q36 -> -20106000 | R45: =R22-R29-R36 -> -20106000 | S45: =S22-S29-S36 -> -20106000 | T45: =SUM(Q45:S45) -> -60318000 | U45: =H45+L45+P45+T45 -> -242492000
B46: 계 | E46: =SUM(E40:E45) -> 521050000 | F46: =SUM(F40:F45) -> 10163000 | G46: =SUM(G40:G45) -> 10163000 | H46: =SUM(H40:H45) -> 541376000 | I46: =SUM(I40:I45) -> 10163000 | J46: =SUM(J40:J45) -> 10163000 | K46: =SUM(K40:K45) -> 10163000 | L46: =SUM(L40:L45) -> 30489000 | ... U46: =SUM(U40:U45) -> 632843000
E47: =E23-E38-E46 -> 0 | F47: =F23-F38-F46 -> 0 | G47: =G23-G38-G46 -> 0 | H47: =H23-H38-H46 -> 0 | I47: =I23-I38-I46 -> 0 | J47: =J23-J38-J46 -> 0 | K47: =K23-K38-K46 -> 0 | L47: =L23-L38-L46 -> 0 | ... U47: =U23-U38-U46 -> 0
B49: 올림처리 수식으로 인한 차액발생은 특정팀에 +- 수기처리함(TST1/TST2) | E49: 기준 (1) 임대료 수입 및 대출이자는 수익과 비용에 반영하지 않는다. (2) 신입직원 1년 인건비 공제는 그대로 적용한다.

Sheet SDT
F1: 1월 | G1: 2월 | H1: 3월 | I1: Q1 | J1: 4월 | K1: 5월 | L1: 6월 | M1: Q2 | N1: 7월 | O1: 8월 | P1: 9월 | Q1: Q3 | R1: 10월 | S1: 11월 | T1: 12월 | U1: Q4 | V1: 2026
F2: Actual | G2: Actual | H2: Actual | I2: Total | J2: Actual | K2: Actual | L2: Actual | M2: Total | N2: Actual | O2: Actual | P2: Actual | Q2: Total | R2: Actual | S2: Actual | T2: Actual | U2: Total | V2: Total
A3: 매 출
B4: Solution Business
D5: Lease | E5: 1 | I5: =H5+G5+F5 -> 0 | M5: =L5+K5+J5 -> 0 | Q5: =P5+O5+N5 -> 0 | U5: =T5+S5+R5 -> 0 | V5: =U5+Q5+M5+I5 -> 0
D6: E&S | E6: 1 | I6: =H6+G6+F6 -> 0 | M6: =L6+K6+J6 -> 0 | Q6: =P6+O6+N6 -> 0 | U6: =T6+S6+R6 -> 0 | V6: =U6+Q6+M6+I6 -> 0
D7: Paid-up | E7: 1 | I7: =H7+G7+F7 -> 0 | M7: =L7+K7+J7 -> 0 | Q7: =P7+O7+N7 -> 0 | U7: =T7+S7+R7 -> 0 | V7: =U7+Q7+M7+I7 -> 0
D8: 기타_HW Transfer | I8: =H8+G8+F8 -> 0 | M8: =L8+K8+J8 -> 0 | Q8: =P8+O8+N8 -> 0 | U8: =T8+S8+R8 -> 0 | V8: =U8+Q8+M8+I8 -> 0
D9: Service | F9: 1600000 | G9: 30000000 | H9: 30000000 | I9: =H9+G9+F9 -> 61600000 | J9: 30000000 | K9: 30000000 | L9: 30000000 | M9: =L9+K9+J9 -> 90000000 | N9: 30000000 | O9: 30000000 | P9: 30000000 | Q9: =P9+O9+N9 -> 90000000 | R9: 30000000 | S9: 30000000 | T9: 30000000 | U9: =T9+S9+R9 -> 90000000 | V9: =U9+Q9+M9+I9 -> 331600000
D10: Seminar/Training | F10: 0 | I10: =H10+G10+F10 -> 0 | M10: =L10+K10+J10 -> 0 | Q10: =P10+O10+N10 -> 0 | U10: =T10+S10+R10 -> 0 | V10: =U10+Q10+M10+I10 -> 0
A12: 매 출 합 계 | F12: =SUM(F5:F10) -> 1600000 | G12: =SUM(G5:G10) -> 30000000 | H12: =SUM(H5:H10) -> 30000000 | I12: =SUM(I5:I10) -> 61600000 | J12: =SUM(J5:J10) -> 30000000 | K12: =SUM(K5:K10) -> 30000000 | L12: =SUM(L5:L10) -> 30000000 | M12: =SUM(M5:M10) -> 90000000 | ... V12: =SUM(V5:V10) -> 331600000
A14: 매 출 원 가
C15: Royalty
D16: MSC Software | E16: 0 | I16: =H16+G16+F16 -> 0 | M16: =L16+K16+J16 -> 0 | Q16: =P16+O16+N16 -> 0 | U16: =T16+S16+R16 -> 0 | V16: =U16+Q16+M16+I16 -> 0
D17: Altair Software | I17: =H17+G17+F17 -> 0 | M17: =L17+K17+J17 -> 0 | Q17: =P17+O17+N17 -> 0 | U17: =T17+S17+R17 -> 0 | V17: =U17+Q17+M17+I17 -> 0
D18: SVD Software | I18: =H18+G18+F18 -> 0 | M18: =L18+K18+J18 -> 0 | Q18: =P18+O18+N18 -> 0 | U18: =T18+S18+R18 -> 0 | V18: =U18+Q18+M18+I18 -> 0
D19: TSV+KTM+그외 | I19: =H19+G19+F19 -> 0 | M19: =L19+K19+J19 -> 0 | Q19: =P19+O19+N19 -> 0 | U19: =T19+S19+R19 -> 0 | V19: =U19+Q19+M19+I19 -> 0
D20: 기타_System | E20: 0 | I20: =H20+G20+F20 -> 0 | M20: =L20+K20+J20 -> 0 | Q20: =P20+O20+N20 -> 0 | U20: =T20+S20+R20 -> 0 | V20: =U20+Q20+M20+I20 -> 0
C21: Outside Consultant | I21: =H21+G21+F21 -> 0 | M21: =L21+K21+J21 -> 0 | Q21: =P21+O21+N21 -> 0 | U21: =T21+S21+R21 -> 0 | V21: =U21+Q21+M21+I21 -> 0
C22: Finder commission | I22: =H22+G22+F22 -> 0 | M22: =L22+K22+J22 -> 0 | Q22: =P22+O22+N22 -> 0 | U22: =T22+S22+R22 -> 0 | V22: =U22+Q22+M22+I22 -> 0
C23: S/W+H/W 감가상각 | F23: 23000 | G23: 20000 | H23: 20000 | I23: =H23+G23+F23 -> 63000 | J23: 20000 | K23: 20000 | L23: 20000 | M23: =L23+K23+J23 -> 60000 | N23: 20000 | O23: 20000 | P23: 20000 | Q23: =P23+O23+N23 -> 60000 | R23: 20000 | S23: 20000 | T23: 20000 | U23: =T23+S23+R23 -> 60000 | V23: =U23+Q23+M23+I23 -> 243000
C24: 지급수수료_기타+임차료 | F24: =30000+33000 -> 63000 | G24: 60000 | H24: 60000 | I24: =H24+G24+F24 -> 183000 | J24: 60000 | K24: 60000 | L24: 60000 | M24: =L24+K24+J24 -> 180000 | N24: 60000 | O24: 60000 | P24: 60000 | Q24: =P24+O24+N24 -> 180000 | R24: 60000 | S24: 60000 | T24: 60000 | U24: =T24+S24+R24 -> 180000 | V24: =U24+Q24+M24+I24 -> 723000
C25: 보증보험+세금과공과 | E25: 0 | I25: =H25+G25+F25 -> 0 | M25: =L25+K25+J25 -> 0 | Q25: =P25+O25+N25 -> 0 | U25: =T25+S25+R25 -> 0 | V25: =U25+Q25+M25+I25 -> 0
A26: 매 출 원 가 합 계 | F26: =SUM(F16:F25) -> 86000 | G26: =SUM(G16:G25) -> 80000 | H26: =SUM(H16:H25) -> 80000 | I26: =SUM(I16:I25) -> 246000 | J26: =SUM(J16:J25) -> 80000 | K26: =SUM(K16:K25) -> 80000 | L26: =SUM(L16:L25) -> 80000 | M26: =SUM(M16:M25) -> 240000 | ... V26: =SUM(V16:V25) -> 966000
A28: 매 출 이 익 (%)
C29: 총 매출이익 | F29: =F12-F26 -> 1514000 | G29: =G12-G26 -> 29920000 | H29: =H12-H26 -> 29920000 | I29: =I12-I26 -> 61354000 | J29: =J12-J26 -> 29920000 | K29: =K12-K26 -> 29920000 | L29: =L12-L26 -> 29920000 | M29: =M12-M26 -> 89760000 | ... V29: =V12-V26 -> 330634000
D30: 총매출이익률 | F30: =IF(F12=0,0,F29/F12) -> 0.94625 | G30: =IF(G12=0,0,G29/G12) -> 0.99733333 | H30: =IF(H12=0,0,H29/H12) -> 0.99733333 | I30: =IF(I12=0,0,I29/I12) -> 0.99600649 | J30: =IF(J12=0,0,J29/J12) -> 0.99733333 | K30: =IF(K12=0,0,K29/K12) -> 0.99733333 | L30: =IF(L12=0,0,L29/L12) -> 0.99733333 | M30: =IF(M12=0,0,M29/M12) -> 0.99733333 | ... V30: =IF(V12=0,0,V29/V12) -> 0.99708685
A31: CONTROLLABLE EXPENSE
C32: Salary & Wages
D33: 직원급여 | E33: 0 | F33: 20000000 | G33: 20000000 | H33: 20000000 | I33: =SUM(F33:H33) -> 60000000 | J33: 20000000 | K33: 20000000 | L33: 20000000 | M33: =SUM(J33:L33) -> 60000000 | N33: 20000000 | O33: 20000000 | P33: 20000000 | Q33: =SUM(N33:P33) -> 60000000 | R33: 20000000 | S33: 20000000 | T33: 20000000 | U33: =SUM(R33:T33) -> 60000000 | V33: =I33+M33+Q33+U33 -> 240000000
D34: 특별상여 | F34: 0 | G34: 0 | H34: 0 | I34: =SUM(F34:H34) -> 0 | J34: 0 | K34: 0 | L34: 0 | M34: =SUM(J34:L34) -> 0 | N34: 0 | O34: 0 | P34: 0 | Q34: =SUM(N34:P34) -> 0 | R34: 0 | S34: 0 | T34: 0 | U34: =SUM(R34:T34) -> 0 | V34: =I34+M34+Q34+U34 -> 0
D35: 기타-연차 | E35: 0 | I35: =SUM(F35:H35) -> 0 | M35: =SUM(J35:L35) -> 0 | Q35: =SUM(N35:P35) -> 0 | U35: =SUM(R35:T35) -> 0 | V35: =I35+M35+Q35+U35 -> 0
D36: 퇴직급여 | E36: 0 | F36: 3000000 | G36: 3000000 | H36: 3000000 | I36: =SUM(F36:H36) -> 9000000 | J36: 3000000 | K36: 3000000 | L36: 3000000 | M36: =SUM(J36:L36) -> 9000000 | N36: 3000000 | O36: 3000000 | P36: 3000000 | Q36: =SUM(N36:P36) -> 9000000 | R36: 3000000 | S36: 3000000 | T36: 3000000 | U36: =SUM(R36:T36) -> 9000000 | V36: =I36+M36+Q36+U36 -> 36000000
B37: Total Salary & Wages | F37: =SUM(F33:F36) -> 23000000 | G37: =SUM(G33:G36) -> 23000000 | H37: =SUM(H33:H36) -> 23000000 | I37: =SUM(I33:I36) -> 69000000 | J37: =SUM(J33:J36) -> 23000000 | K37: =SUM(K33:K36) -> 23000000 | L37: =SUM(L33:L36) -> 23000000 | M37: =SUM(M33:M36) -> 69000000 | ... U37: =SUM(U33:U36) -> 69000000 | V37: =I37+M37+Q37+U37 -> 276000000
C38: Benefits
D39: 국민연금 | E39: 0 | F39: 1000000 | G39: 1000000 | H39: 1000000 | I39: =SUM(F39:H39) -> 3000000 | J39: 1000000 | K39: 1000000 | L39: 1000000 | M39: =SUM(J39:L39) -> 3000000 | N39: 1000000 | O39: 1000000 | P39: 1000000 | Q39: =SUM(N39:P39) -> 3000000 | R39: 1000000 | S39: 1000000 | T39: 1000000 | U39: =SUM(R39:T39) -> 3000000 | V39: =I39+M39+Q39+U39 -> 12000000
D40: 건강보험 | E40: 0 | F40: 1000000 | G40: 1000000 | H40: 1000000 | I40: =SUM(F40:H40) -> 3000000 | J40: 1000000 | K40: 1000000 | L40: 1000000 | M40: =SUM(J40:L40) -> 3000000 | N40: 1000000 | O40: 1000000 | P40: 1000000 | Q40: =SUM(N40:P40) -> 3000000 | R40: 1000000 | S40: 1000000 | T40: 1000000 | U40: =SUM(R40:T40) -> 3000000 | V40: =I40+M40+Q40+U40 -> 12000000
D41: 고용보험 | E41: 0 | F41: 200000 | G41: 200000 | H41: 200000 | I41: =SUM(F41:H41) -> 600000 | J41: 200000 | K41: 200000 | L41: 200000 | M41: =SUM(J41:L41) -> 600000 | N41: 200000 | O41: 200000 | P41: 200000 | Q41: =SUM(N41:P41) -> 600000 | R41: 200000 | S41: 200000 | T41: 200000 | U41: =SUM(R41:T41) -> 600000 | V41: =I41+M41+Q41+U41 -> 2400000
D42: 산재보험 | E42: 0 | F42: 120000 | G42: 120000 | H42: 120000 | I42: =SUM(F42:H42) -> 360000 | J42: 120000 | K42: 120000 | L42: 120000 | M42: =SUM(J42:L42) -> 360000 | N42: 120000 | O42: 120000 | P42: 120000 | Q42: =SUM(N42:P42) -> 360000 | R42: 120000 | S42: 120000 | T42: 120000 | U42: =SUM(R42:T42) -> 360000 | V42: =I42+M42+Q42+U42 -> 1440000
D43: 야근식대 | E43: 0 | F43: 8000 | G43: 8000 | H43: 8000 | I43: =SUM(F43:H43) -> 24000 | J43: 8000 | K43: 8000 | L43: 8000 | M43: =SUM(J43:L43) -> 24000 | N43: 8000 | O43: 8000 | P43: 8000 | Q43: =SUM(N43:P43) -> 24000 | R43: 8000 | S43: 8000 | T43: 8000 | U43: =SUM(R43:T43) -> 24000 | V43: =I43+M43+Q43+U43 -> 96000
D44: 회식대 | F44: 37000 | G44: 37000 | H44: 37000 | I44: =SUM(F44:H44) -> 111000 | J44: 37000 | K44: 37000 | L44: 37000 | M44: =SUM(J44:L44) -> 111000 | N44: 37000 | O44: 37000 | P44: 37000 | Q44: =SUM(N44:P44) -> 111000 | R44: 37000 | S44: 37000 | T44: 37000 | U44: =SUM(R44:T44) -> 111000 | V44: =I44+M44+Q44+U44 -> 444000
D45: 경조사 | E45: 0 | I45: =SUM(F45:H45) -> 0 | M45: =SUM(J45:L45) -> 0 | Q45: =SUM(N45:P45) -> 0 | U45: =SUM(R45:T45) -> 0 | V45: =I45+M45+Q45+U45 -> 0
D46: 교육지원비 | E46: 0 | I46: =SUM(F46:H46) -> 0 | M46: =SUM(J46:L46) -> 0 | Q46: =SUM(N46:P46) -> 0 | U46: =SUM(R46:T46) -> 0 | V46: =I46+M46+Q46+U46 -> 0
D47: 직원상해보험 | E47: 0 | I47: =SUM(F47:H47) -> 0 | M47: =SUM(J47:L47) -> 0 | Q47: =SUM(N47:P47) -> 0 | U47: =SUM(R47:T47) -> 0 | V47: =I47+M47+Q47+U47 -> 0
D48: 건강검진 | E48: 0 | I48: =SUM(F48:H48) -> 0 | M48: =SUM(J48:L48) -> 0 | Q48: =SUM(N48:P48) -> 0 | U48: =SUM(R48:T48) -> 0 | V48: =I48+M48+Q48+U48 -> 0
D49: 통신비(핸드폰) | F49: 150000 | G49: 150000 | H49: 150000 | I49: =SUM(F49:H49) -> 450000 | J49: 150000 | K49: 150000 | L49: 150000 | M49: =SUM(J49:L49) -> 450000 | N49: 150000 | O49: 150000 | P49: 150000 | Q49: =SUM(N49:P49) -> 450000 | R49: 150000 | S49: 150000 | T49: 150000 | U49: =SUM(R49:T49) -> 450000 | V49: =I49+M49+Q49+U49 -> 1800000
D50: 체력단련비 | F50: 133000 | G50: 133000 | H50: 133000 | I50: =SUM(F50:H50) -> 399000 | J50: 133000 | K50: 133000 | L50: 133000 | M50: =SUM(J50:L50) -> 399000 | N50: 133000 | O50: 133000 | P50: 133000 | Q50: =SUM(N50:P50) -> 399000 | R50: 133000 | S50: 133000 | T50: 133000 | U50: =SUM(R50:T50) -> 399000 | V50: =I50+M50+Q50+U50 -> 1596000
B51: Total Benefits | F51: =SUM(F39:F50) -> 2648000 | G51: =SUM(G39:G50) -> 2648000 | H51: =SUM(H39:H50) -> 2648000 | I51: =SUM(I39:I50) -> 7944000 | J51: =SUM(J39:J50) -> 2648000 | K51: =SUM(K39:K50) -> 2648000 | L51: =SUM(L39:L50) -> 2648000 | M51: =SUM(M39:M50) -> 7944000 | ... U51: =SUM(U39:U50) -> 7944000 | V51: =I51+M51+Q51+U51 -> 31776000
B52: Total Compensation & Benefits | F52: =F37+F51 -> 25648000 | G52: =G37+G51 -> 25648000 | H52: =H37+H51 -> 25648000 | I52: =I51+I37 -> 76944000 | J52: =J37+J51 -> 25648000 | K52: =K37+K51 -> 25648000 | L52: =L37+L51 -> 25648000 | M52: =M51+M37 -> 76944000 | N52: =N37+N51 -> 25648000 | O52: =O37+O51 -> 25648000 | P52: =P37+P51 -> 25648000 | Q52: =Q51+Q37 -> 76944000 | R52: =R37+R51 -> 25648000 | S52: =S37+S51 -> 25648000 | T52: =T37+T51 -> 25648000 | U52: =U51+U37 -> 76944000 | V52: =I52+M52+Q52+U52 -> 307776000
B53: Unfunded Consulting Expenses | E53: 0 | F53: 0 | G53: 0 | H53: 0 | I53: 0 | J53: 0 | K53: 0 | L53: 0 | M53: 0 | N53: 0 | O53: 0 | P53: 0 | Q53: 0 | R53: 0 | S53: 0 | T53: 0 | U53: 0 | V53: =I53+M53+Q53+U53 -> 0
B54: Travel & Entertainment
C55: 여비교통비(출장일비) | E55: 0 | I55: =SUM(F55:H55) -> 0 | M55: =SUM(J55:L55) -> 0 | Q55: =SUM(N55:P55) -> 0 | U55: =SUM(R55:T55) -> 0 | V55: =I55+M55+Q55+U55 -> 0
C56: 여비교통비(출장식대) | F56: 113000 | G56: 113000 | H56: 113000 | I56: =SUM(F56:H56) -> 339000 | J56: 113000 | K56: 113000 | L56: 113000 | M56: =SUM(J56:L56) -> 339000 | N56: 113000 | O56: 113000 | P56: 113000 | Q56: =SUM(N56:P56) -> 339000 | R56: 113000 | S56: 113000 | T56: 113000 | U56: =SUM(R56:T56) -> 339000 | V56: =I56+M56+Q56+U56 -> 1356000
C57: 여비교통비(통행,주차) | F57: 15000 | G57: 15000 | H57: 15000 | I57: =SUM(F57:H57) -> 45000 | J57: 15000 | K57: 15000 | L57: 15000 | M57: =SUM(J57:L57) -> 45000 | N57: 15000 | O57: 15000 | P57: 15000 | Q57: =SUM(N57:P57) -> 45000 | R57: 15000 | S57: 15000 | T57: 15000 | U57: =SUM(R57:T57) -> 45000 | V57: =I57+M57+Q57+U57 -> 180000
C58: 여비교통비(항공,고속버스등) | F58: 317000 | G58: 317000 | H58: 317000 | I58: =SUM(F58:H58) -> 951000 | J58: 317000 | K58: 317000 | L58: 317000 | M58: =SUM(J58:L58) -> 951000 | N58: 317000 | O58: 317000 | P58: 317000 | Q58: =SUM(N58:P58) -> 951000 | R58: 317000 | S58: 317000 | T58: 317000 | U58: =SUM(R58:T58) -> 951000 | V58: =I58+M58+Q58+U58 -> 3804000
C59: 여비교통비(숙박) | F59: 512000 | G59: 512000 | H59: 512000 | I59: =SUM(F59:H59) -> 1536000 | J59: 512000 | K59: 512000 | L59: 512000 | M59: =SUM(J59:L59) -> 1536000 | N59: 512000 | O59: 512000 | P59: 512000 | Q59: =SUM(N59:P59) -> 1536000 | R59: 512000 | S59: 512000 | T59: 512000 | U59: =SUM(R59:T59) -> 1536000 | V59: =I59+M59+Q59+U59 -> 6144000
C60: 여비교통비(차량지원) | F60: 111000 | G60: 111000 | H60: 111000 | I60: =SUM(F60:H60) -> 333000 | J60: 111000 | K60: 111000 | L60: 111000 | M60: =SUM(J60:L60) -> 333000 | N60: 111000 | O60: 111000 | P60: 111000 | Q60: =SUM(N60:P60) -> 333000 | R60: 111000 | S60: 111000 | T60: 111000 | U60: =SUM(R60:T60) -> 333000 | V60: =I60+M60+Q60+U60 -> 1332000
C61: 여비교통비(국책과제_연구활동비) | I61: =SUM(F61:H61) -> 0 | M61: =SUM(J61:L61) -> 0 | Q61: =SUM(N61:P61) -> 0 | U61: =SUM(R61:T61) -> 0 | V61: =I61+M61+Q61+U61 -> 0
C62: 차량유지비 | E62: 0 | I62: =SUM(F62:H62) -> 0 | M62: =SUM(J62:L62) -> 0 | Q62: =SUM(N62:P62) -> 0 | U62: =SUM(R62:T62) -> 0 | V62: =I62+M62+Q62+U62 -> 0
C63: 해외출장비 | E63: 0 | I63: =SUM(F63:H63) -> 0 | M63: =SUM(J63:L63) -> 0 | Q63: =SUM(N63:P63) -> 0 | U63: =SUM(R63:T63) -> 0 | V63: =I63+M63+Q63+U63 -> 0
C64: 회의비 | E64: 0 | F64: 167000 | G64: 167000 | H64: 167000 | I64: =SUM(F64:H64) -> 501000 | J64: 167000 | K64: 167000 | L64: 167000 | M64: =SUM(J64:L64) -> 501000 | N64: 167000 | O64: 167000 | P64: 167000 | Q64: =SUM(N64:P64) -> 501000 | R64: 167000 | S64: 167000 | T64: 167000 | U64: =SUM(R64:T64) -> 501000 | V64: =I64+M64+Q64+U64 -> 2004000
C65: 접대비 | E65: 0 | F65: 20000 | G65: 20000 | H65: 20000 | I65: =SUM(F65:H65) -> 60000 | J65: 20000 | K65: 20000 | L65: 20000 | M65: =SUM(J65:L65) -> 60000 | N65: 20000 | O65: 20000 | P65: 20000 | Q65: =SUM(N65:P65) -> 60000 | R65: 20000 | S65: 20000 | T65: 20000 | U65: =SUM(R65:T65) -> 60000 | V65: =I65+M65+Q65+U65 -> 240000
B66: Total Travel & Entertainment | F66: =SUM(F55:F65) -> 1255000 | G66: =SUM(G55:G65) -> 1255000 | H66: =SUM(H55:H65) -> 1255000 | I66: =SUM(I55:I65) -> 3765000 | J66: =SUM(J55:J65) -> 1255000 | K66: =SUM(K55:K65) -> 1255000 | L66: =SUM(L55:L65) -> 1255000 | M66: =SUM(M55:M65) -> 3765000 | ... U66: =SUM(U55:U65) -> 3765000 | V66: =I66+M66+Q66+U66 -> 15060000
B67: Product Marketing
C68: 행사비 | E68: 0 | I68: =SUM(F68:H68) -> 0 | M68: =SUM(J68:L68) -> 0 | Q68: =SUM(N68:P68) -> 0 | U68: =SUM(R68:T68) -> 0 | V68: =I68+M68+Q68+U68 -> 0
C69: 마케팅 | E69: 0 | I69: =SUM(F69:H69) -> 0 | M69: =SUM(J69:L69) -> 0 | Q69: =SUM(N69:P69) -> 0 | U69: =SUM(R69:T69) -> 0 | V69: =I69+M69+Q69+U69 -> 0
C70: 기타 | E70: 0 | I70: =SUM(F70:H70) -> 0 | M70: =SUM(J70:L70) -> 0 | Q70: =SUM(N70:P70) -> 0 | U70: =SUM(R70:T70) -> 0 | V70: =I70+M70+Q70+U70 -> 0
B71: Total Product Marketing | F71: =SUM(F68:F70) -> 0 | G71: =SUM(G68:G70) -> 0 | H71: =SUM(H68:H70) -> 0 | I71: =SUM(I68:I70) -> 0 | J71: =SUM(J68:J70) -> 0 | K71: =SUM(K68:K70) -> 0 | L71: =SUM(L68:L70) -> 0 | M71: =SUM(M68:M70) -> 0 | ... U71: =SUM(U68:U70) -> 0 | V71: =I71+M71+Q71+U71 -> 0
B72: Sales Activities
C73: 고객교육훈련비 | E73: 0 | I73: =SUM(F73:H73) -> 0 | M73: =SUM(J73:L73) -> 0 | Q73: =SUM(N73:P73) -> 0 | U73: =SUM(R73:T73) -> 0 | V73: =I73+M73+Q73+U73 -> 0
C74: Sales Promotions | E74: 0 | I74: =SUM(F74:H74) -> 0 | M74: =SUM(J74:L74) -> 0 | Q74: =SUM(N74:P74) -> 0 | U74: =SUM(R74:T74) -> 0 | V74: =I74+M74+Q74+U74 -> 0
C75: Other Sales Activities | E75: 0 | I75: =SUM(F75:H75) -> 0 | M75: =SUM(J75:L75) -> 0 | Q75: =SUM(N75:P75) -> 0 | U75: =SUM(R75:T75) -> 0 | V75: =I75+M75+Q75+U75 -> 0
B76: Total Sales Activities | F76: =SUM(F73:F75) -> 0 | G76: =SUM(G73:G75) -> 0 | H76: =SUM(H73:H75) -> 0 | I76: =SUM(I73:I75) -> 0 | J76: =SUM(J73:J75) -> 0 | K76: =SUM(K73:K75) -> 0 | L76: =SUM(L73:L75) -> 0 | M76: =SUM(M73:M75) -> 0 | ... U76: =SUM(U73:U75) -> 0 | V76: =I76+M76+Q76+U76 -> 0
D77: TOTAL CONTROLLABLE EXP. | F77: =F52+F53+F66+F71+F76 -> 26903000 | G77: =G52+G53+G66+G71+G76 -> 26903000 | H77: =H52+H53+H66+H71+H76 -> 26903000 | I77: =I76+I71+I66+I53+I52 -> 80709000 | J77: =J52+J53+J66+J71+J76 -> 26903000 | K77: =K52+K53+K66+K71+K76 -> 26903000 | L77: =L52+L53+L66+L71+L76 -> 26903000 | M77: =M76+M71+M66+M53+M52 -> 80709000 | N77: =N52+N53+N66+N71+N76 -> 26903000 | O77: =O52+O53+O66+O71+O76 -> 26903000 | P77: =P52+P53+P66+P71+P76 -> 26903000 | Q77: =Q76+Q71+Q66+Q53+Q52 -> 80709000 | R77: =R52+R53+R66+R71+R76 -> 26903000 | S77: =S52+S53+S66+S71+S76 -> 26903000 | T77: =T52+T53+T66+T71+T76 -> 26903000 | U77: =U76+U71+U66+U53+U52 -> 80709000 | V77: =I77+M77+Q77+U77 -> 322836000
A78: FIXED EXPENSE
B79: Facility & Equipment
C80: 사무실-임차료 | E80: 0 | I80: =SUM(F80:H80) -> 0 | M80: =SUM(J80:L80) -> 0 | Q80: =SUM(N80:P80) -> 0 | U80: =SUM(R80:T80) -> 0 | V80: =I80+M80+Q80+U80 -> 0
C81: 사무실-관리비 | E81: 0 | I81: =SUM(F81:H81) -> 0 | M81: =SUM(J81:L81) -> 0 | Q81: =SUM(N81:P81) -> 0 | U81: =SUM(R81:T81) -> 0 | V81: =I81+M81+Q81+U81 -> 0
C82: 비품 감가상각 | E82: 0 | I82: =SUM(F82:H82) -> 0 | M82: =SUM(J82:L82) -> 0 | Q82: =SUM(N82:P82) -> 0 | U82: =SUM(R82:T82) -> 0 | V82: =I82+M82+Q82+U82 -> 0
C83: 시설물 감가상각 | I83: =SUM(F83:H83) -> 0 | M83: =SUM(J83:L83) -> 0 | Q83: =SUM(N83:P83) -> 0 | U83: =SUM(R83:T83) -> 0 | V83: =I83+M83+Q83+U83 -> 0
C84: 기계설비 임차료 | I84: =SUM(F84:H84) -> 0 | M84: =SUM(J84:L84) -> 0 | Q84: =SUM(N84:P84) -> 0 | U84: =SUM(R84:T84) -> 0 | V84: =I84+M84+Q84+U84 -> 0
C85: 전화요금 | E85: 0 | I85: =SUM(F85:H85) -> 0 | M85: =SUM(J85:L85) -> 0 | Q85: =SUM(N85:P85) -> 0 | U85: =SUM(R85:T85) -> 0 | V85: =I85+M85+Q85+U85 -> 0
C86: 사무실관리비 | E86: 0 | I86: =SUM(F86:H86) -> 0 | M86: =SUM(J86:L86) -> 0 | Q86: =SUM(N86:P86) -> 0 | U86: =SUM(R86:T86) -> 0 | V86: =I86+M86+Q86+U86 -> 0
C87: 기타_프로그램임차 | E87: 0 | F87: 3210000 | G87: 2000000 | H87: 2000000 | I87: =SUM(F87:H87) -> 7210000 | J87: 2000000 | K87: 2000000 | L87: 2000000 | M87: =SUM(J87:L87) -> 6000000 | N87: 2000000 | O87: 2000000 | P87: 2000000 | Q87: =SUM(N87:P87) -> 6000000 | R87: 2000000 | S87: 2000000 | T87: 2000000 | U87: =SUM(R87:T87) -> 6000000 | V87: =I87+M87+Q87+U87 -> 25210000
B88: Total Facility Expense | F88: =SUM(F80:F87) -> 3210000 | G88: =SUM(G80:G87) -> 2000000 | H88: =SUM(H80:H87) -> 2000000 | I88: =SUM(I80:I87) -> 7210000 | J88: =SUM(J80:J87) -> 2000000 | K88: =SUM(K80:K87) -> 2000000 | L88: =SUM(L80:L87) -> 2000000 | M88: =SUM(M80:M87) -> 6000000 | ... U88: =SUM(U80:U87) -> 6000000 | V88: =I88+M88+Q88+U88 -> 25210000
B89: Total Software License for Internal Use | E89: 0 | F89: 0 | G89: 0 | H89: 0 | I89: =SUM(I81:I88) -> 14420000 | J89: 0 | K89: 0 | L89: 0 | M89: =SUM(M81:M88) -> 12000000 | N89: 0 | O89: 0 | P89: 0 | Q89: =SUM(Q81:Q88) -> 12000000 | R89: 0 | S89: 0 | T89: 0 | U89: =SUM(U81:U88) -> 12000000 | V89: =I89+M89+Q89+U89 -> 50420000
B90: Office Expense | I90: =SUM(F90:H90) -> 0 | M90: =SUM(J90:L90) -> 0 | Q90: =SUM(N90:P90) -> 0 | U90: =SUM(R90:T90) -> 0 | V90: =I90+M90+Q90+U90 -> 0
C91: 도서인쇄비 | E91: 0 | I91: =SUM(F91:H91) -> 0 | M91: =SUM(J91:L91) -> 0 | Q91: =SUM(N91:P91) -> 0 | U91: =SUM(R91:T91) -> 0 | V91: =I91+M91+Q91+U91 -> 0
C92: 사무용품비 | E92: 0 | G92: 10000 | H92: 10000 | I92: =SUM(F92:H92) -> 20000 | J92: 10000 | K92: 10000 | L92: 10000 | M92: =SUM(J92:L92) -> 30000 | N92: 10000 | O92: 10000 | P92: 10000 | Q92: =SUM(N92:P92) -> 30000 | R92: 10000 | S92: 10000 | T92: 10000 | U92: =SUM(R92:T92) -> 30000 | V92: =I92+M92+Q92+U92 -> 110000
C93: 소모품비 | E93: 0 | I93: =SUM(F93:H93) -> 0 | M93: =SUM(J93:L93) -> 0 | Q93: =SUM(N93:P93) -> 0 | U93: =SUM(R93:T93) -> 0 | V93: =I93+M93+Q93+U93 -> 0
C94: 우편료 | E94: 0 | F94: 3000 | I94: =SUM(F94:H94) -> 3000 | M94: =SUM(J94:L94) -> 0 | Q94: =SUM(N94:P94) -> 0 | U94: =SUM(R94:T94) -> 0 | V94: =I94+M94+Q94+U94 -> 3000
C95: 운반비 | E95: 0 | I95: =SUM(F95:H95) -> 0 | M95: =SUM(J95:L95) -> 0 | Q95: =SUM(N95:P95) -> 0 | U95: =SUM(R95:T95) -> 0 | V95: =I95+M95+Q95+U95 -> 0
C96: 수선비 | E96: 0 | I96: =SUM(F96:H96) -> 0 | M96: =SUM(J96:L96) -> 0 | Q96: =SUM(N96:P96) -> 0 | U96: =SUM(R96:T96) -> 0 | V96: =I96+M96+Q96+U96 -> 0
B97: Total Office Expense | F97: =SUM(F91:F96) -> 3000 | G97: =SUM(G91:G96) -> 10000 | H97: =SUM(H91:H96) -> 10000 | I97: =SUM(I91:I96) -> 23000 | J97: =SUM(J91:J96) -> 10000 | K97: =SUM(K91:K96) -> 10000 | L97: =SUM(L91:L96) -> 10000 | M97: =SUM(M91:M96) -> 30000 | ... U97: =SUM(U91:U96) -> 30000 | V97: =I97+M97+Q97+U97 -> 113000
B98: Business Expense
C99: 기술고문료 | E99: 0 | I99: =SUM(F99:H99) -> 0 | M99: =SUM(J99:L99) -> 0 | Q99: =SUM(N99:P99) -> 0 | U99: =SUM(R99:T99) -> 0 | V99: =I99+M99+Q99+U99 -> 0
C100: 세무감사료 | E100: 0 | I100: =SUM(F100:H100) -> 0 | M100: =SUM(J100:L100) -> 0 | Q100: =SUM(N100:P100) -> 0 | U100: =SUM(R100:T100) -> 0 | V100: =I100+M100+Q100+U100 -> 0
C101: 홈페이지관리외 | E101: 0 | I101: =SUM(F101:H101) -> 0 | M101: =SUM(J101:L101) -> 0 | Q101: =SUM(N101:P101) -> 0 | U101: =SUM(R101:T101) -> 0 | V101: =I101+M101+Q101+U101 -> 0
C102: 보증보험 | E102: 0 | I102: =SUM(F102:H102) -> 0 | M102: =SUM(J102:L102) -> 0 | Q102: =SUM(N102:P102) -> 0 | U102: =SUM(R102:T102) -> 0 | V102: =I102+M102+Q102+U102 -> 0
C103: 보험료-차량+여행자 | E103: 0 | I103: =SUM(F103:H103) -> 0 | M103: =SUM(J103:L103) -> 0 | Q103: =SUM(N103:P103) -> 0 | U103: =SUM(R103:T103) -> 0 | V103: =I103+M103+Q103+U103 -> 0
...

Sheet TST1
F1: 1월 | G1: 2월 | H1: 3월 | I1: Q1 | J1: 4월 | K1: 5월 | L1: 6월 | M1: Q2 | N1: 7월 | O1: 8월 | P1: 9월 | Q1: Q3 | R1: 10월 | S1: 11월 | T1: 12월 | U1: Q4 | V1: 2026
F2: Actual | G2: Actual | H2: Actual | I2: Total | J2: Actual | K2: Actual | L2: Actual | M2: Total | N2: Actual | O2: Actual | P2: Actual | Q2: Total | R2: Actual | S2: Actual | T2: Actual | U2: Total | V2: Total
A3: 매 출
B4: Solution Business
D5: Lease | E5: 1 | F5: 128975000 | G5: 28000000 | H5: 28000000 | I5: =H5+G5+F5 -> 184975000 | J5: 28000000 | K5: 28000000 | L5: 28000000 | M5: =L5+K5+J5 -> 84000000 | N5: 28000000 | O5: 28000000 | P5: 28000000 | Q5: =P5+O5+N5 -> 84000000 | R5: 28000000 | S5: 28000000 | T5: 28000000 | U5: =T5+S5+R5 -> 84000000 | V5: =U5+Q5+M5+I5 -> 436975000
D6: E&S | E6: 1 | F6: 407012000 | G6: 40000000 | H6: 40000000 | I6: =H6+G6+F6 -> 487012000 | J6: 40000000 | K6: 40000000 | L6: 40000000 | M6: =L6+K6+J6 -> 120000000 | N6: 40000000 | O6: 40000000 | P6: 40000000 | Q6: =P6+O6+N6 -> 120000000 | R6: 40000000 | S6: 40000000 | T6: 40000000 | U6: =T6+S6+R6 -> 120000000 | V6: =U6+Q6+M6+I6 -> 847012000
D7: Paid-up | E7: 1 | F7: 0 | G7: 0 | H7: 0 | I7: =H7+G7+F7 -> 0 | J7: 0 | K7: 0 | L7: 0 | M7: =L7+K7+J7 -> 0 | N7: 0 | O7: 0 | P7: 0 | Q7: =P7+O7+N7 -> 0 | R7: 0 | S7: 0 | T7: 0 | U7: =T7+S7+R7 -> 0 | V7: =U7+Q7+M7+I7 -> 0
D8: 기타_HW Transfer | I8: =H8+G8+F8 -> 0 | M8: =L8+K8+J8 -> 0 | Q8: =P8+O8+N8 -> 0 | U8: =T8+S8+R8 -> 0 | V8: =U8+Q8+M8+I8 -> 0
D9: Service | I9: =H9+G9+F9 -> 0 | M9: =L9+K9+J9 -> 0 | Q9: =P9+O9+N9 -> 0 | U9: =T9+S9+R9 -> 0 | V9: =U9+Q9+M9+I9 -> 0
D10: Seminar/Training | I10: =H10+G10+F10 -> 0 | M10: =L10+K10+J10 -> 0 | Q10: =P10+O10+N10 -> 0 | U10: =T10+S10+R10 -> 0 | V10: =U10+Q10+M10+I10 -> 0
A12: 매 출 합 계 | F12: =SUM(F5:F10) -> 535987000 | G12: =SUM(G5:G10) -> 68000000 | H12: =SUM(H5:H10) -> 68000000 | I12: =SUM(I5:I10) -> 671987000 | J12: =SUM(J5:J10) -> 68000000 | K12: =SUM(K5:K10) -> 68000000 | L12: =SUM(L5:L10) -> 68000000 | M12: =SUM(M5:M10) -> 204000000 | ... V12: =SUM(V5:V10) -> 1283987000
A14: 매 출 원 가
C15: Royalty
D16: MSC Software | E16: 0 | F16: 75564000 | G16: 25000000 | H16: 25000000 | I16: =H16+G16+F16 -> 125564000 | J16: 25000000 | K16: 25000000 | L16: 25000000 | M16: =L16+K16+J16 -> 75000000 | N16: 25000000 | O16: 25000000 | P16: 25000000 | Q16: =P16+O16+N16 -> 75000000 | R16: 25000000 | S16: 25000000 | T16: 25000000 | U16: =T16+S16+R16 -> 75000000 | V16: =U16+Q16+M16+I16 -> 350564000
D17: SVD Software | F17: 157978000 | G17: 5000000 | H17: 5000000 | I17: =H17+G17+F17 -> 167978000 | J17: 5000000 | K17: 5000000 | L17: 5000000 | M17: =L17+K17+J17 -> 15000000 | N17: 5000000 | O17: 5000000 | P17: 5000000 | Q17: =P17+O17+N17 -> 15000000 | R17: 5000000 | S17: 5000000 | T17: 5000000 | U17: =T17+S17+R17 -> 15000000 | V17: =U17+Q17+M17+I17 -> 212978000
D18: TechSoft3D | I18: =H18+G18+F18 -> 0 | M18: =L18+K18+J18 -> 0 | Q18: =P18+O18+N18 -> 0 | U18: =T18+S18+R18 -> 0 | V18: =U18+Q18+M18+I18 -> 0
D19: TSV+KTM+그외 | I19: =H19+G19+F19 -> 0 | M19: =L19+K19+J19 -> 0 | Q19: =P19+O19+N19 -> 0 | U19: =T19+S19+R19 -> 0 | V19: =U19+Q19+M19+I19 -> 0
D20: 기타_System | E20: 0 | I20: =H20+G20+F20 -> 0 | M20: =L20+K20+J20 -> 0 | Q20: =P20+O20+N20 -> 0 | U20: =T20+S20+R20 -> 0 | V20: =U20+Q20+M20+I20 -> 0
C21: Outside Consultant | I21: =H21+G21+F21 -> 0 | M21: =L21+K21+J21 -> 0 | Q21: =P21+O21+N21 -> 0 | U21: =T21+S21+R21 -> 0 | V21: =U21+Q21+M21+I21 -> 0
C22: Finder commission | I22: =H22+G22+F22 -> 0 | M22: =L22+K22+J22 -> 0 | Q22: =P22+O22+N22 -> 0 | U22: =T22+S22+R22 -> 0 | V22: =U22+Q22+M22+I22 -> 0
C23: S/W+H/W 감가상각 | F23: 57000 | G23: 57000 | H23: 57000 | I23: =H23+G23+F23 -> 171000 | J23: 57000 | K23: 57000 | L23: 57000 | M23: =L23+K23+J23 -> 171000 | N23: 57000 | O23: 57000 | P23: 57000 | Q23: =P23+O23+N23 -> 171000 | R23: 57000 | S23: 57000 | T23: 57000 | U23: =T23+S23+R23 -> 171000 | V23: =U23+Q23+M23+I23 -> 684000
C24: 지급수수료_기타+임차료 | F24: =938000 -> 938000 | G24: =938000 -> 938000 | H24: =938000 -> 938000 | I24: =H24+G24+F24 -> 2814000 | J24: =938000 -> 938000 | K24: =938000 -> 938000 | L24: =938000 -> 938000 | M24: =L24+K24+J24 -> 2814000 | N24: =938000 -> 938000 | O24: =938000 -> 938000 | P24: =938000 -> 938000 | Q24: =P24+O24+N24 -> 2814000 | R24: =938000 -> 938000 | S24: =938000 -> 938000 | T24: =938000 -> 938000 | U24: =T24+S24+R24 -> 2814000 | V24: =U24+Q24+M24+I24 -> 11256000
C25: 보증보험+세금과공과 | E25: 0 | I25: =H25+G25+F25 -> 0 | M25: =L25+K25+J25 -> 0 | Q25: =P25+O25+N25 -> 0 | U25: =T25+S25+R25 -> 0 | V25: =U25+Q25+M25+I25 -> 0
A26: 매 출 원 가 합 계 | F26: =SUM(F16:F25) -> 234537000 | G26: =SUM(G16:G25) -> 30995000 | H26: =SUM(H16:H25) -> 30995000 | I26: =SUM(I16:I25) -> 296527000 | J26: =SUM(J16:J25) -> 30995000 | K26: =SUM(K16:K25) -> 30995000 | L26: =SUM(L16:L25) -> 30995000 | M26: =SUM(M16:M25) -> 92985000 | ... V26: =SUM(V16:V25) -> 575482000
A28: 매 출 이 익 (%)
C29: 총 매출이익 | F29: =F12-F26 -> 301450000 | G29: =G12-G26 -> 37005000 | H29: =H12-H26 -> 37005000 | I29: =I12-I26 -> 375460000 | J29: =J12-J26 -> 37005000 | K29: =K12-K26 -> 37005000 | L29: =L12-L26 -> 37005000 | M29: =M12-M26 -> 111015000 | ... V29: =V12-V26 -> 708505000
D30: 총매출이익률 | F30: =IF(F12=0,0,F29/F12) -> 0.56242036 | G30: =IF(G12=0,0,G29/G12) -> 0.54419118 | H30: =IF(H12=0,0,H29/H12) -> 0.54419118 | I30: =IF(I12=0,0,I29/I12) -> 0.55873105 | J30: =IF(J12=0,0,J29/J12) -> 0.54419118 | K30: =IF(K12=0,0,K29/K12) -> 0.54419118 | L30: =IF(L12=0,0,L29/L12) -> 0.54419118 | M30: =IF(M12=0,0,M29/M12) -> 0.54419118 | ... V30: =IF(V12=0,0,V29/V12) -> 0.55180076
A31: CONTROLLABLE EXPENSE
C32: Salary & Wages
D33: 직원급여 | E33: 0 | F33: 18000000 | G33: 18000000 | H33: 18000000 | I33: =SUM(F33:H33) -> 54000000 | J33: 18000000 | K33: 18000000 | L33: 18000000 | M33: =SUM(J33:L33) -> 54000000 | N33: 18000000 | O33: 18000000 | P33: 18000000 | Q33: =SUM(N33:P33) -> 54000000 | R33: 18000000 | S33: 18000000 | T33: 18000000 | U33: =SUM(R33:T33) -> 54000000 | V33: =I33+M33+Q33+U33 -> 216000000
D34: 특별상여 | F34: 0 | G34: 0 | H34: 0 | I34: =SUM(F34:H34) -> 0 | J34: 0 | K34: 0 | L34: 0 | M34: =SUM(J34:L34) -> 0 | N34: 0 | O34: 0 | P34: 0 | Q34: =SUM(N34:P34) -> 0 | R34: 0 | S34: 0 | T34: 0 | U34: =SUM(R34:T34) -> 0 | V34: =I34+M34+Q34+U34 -> 0
D35: 기타-연차 | E35: 0 | I35: =SUM(F35:H35) -> 0 | M35: =SUM(J35:L35) -> 0 | Q35: =SUM(N35:P35) -> 0 | U35: =SUM(R35:T35) -> 0 | V35: =I35+M35+Q35+U35 -> 0
D36: 퇴직급여 | E36: 0 | F36: 2000000 | G36: 2000000 | H36: 2000000 | I36: =SUM(F36:H36) -> 6000000 | J36: 2000000 | K36: 2000000 | L36: 2000000 | M36: =SUM(J36:L36) -> 6000000 | N36: 2000000 | O36: 2000000 | P36: 2000000 | Q36: =SUM(N36:P36) -> 6000000 | R36: 2000000 | S36: 2000000 | T36: 2000000 | U36: =SUM(R36:T36) -> 6000000 | V36: =I36+M36+Q36+U36 -> 24000000
B37: Total Salary & Wages | F37: =SUM(F33:F36) -> 20000000 | G37: =SUM(G33:G36) -> 20000000 | H37: =SUM(H33:H36) -> 20000000 | I37: =SUM(I33:I36) -> 60000000 | J37: =SUM(J33:J36) -> 20000000 | K37: =SUM(K33:K36) -> 20000000 | L37: =SUM(L33:L36) -> 20000000 | M37: =SUM(M33:M36) -> 60000000 | ... U37: =SUM(U33:U36) -> 60000000 | V37: =I37+M37+Q37+U37 -> 240000000
C38: Benefits
D39: 국민연금 | E39: 0 | F39: 500000 | G39: 500000 | H39: 500000 | I39: =SUM(F39:H39) -> 1500000 | J39: 500000 | K39: 500000 | L39: 500000 | M39: =SUM(J39:L39) -> 1500000 | N39: 500000 | O39: 500000 | P39: 500000 | Q39: =SUM(N39:P39) -> 1500000 | R39: 500000 | S39: 500000 | T39: 500000 | U39: =SUM(R39:T39) -> 1500000 | V39: =I39+M39+Q39+U39 -> 6000000
D40: 건강보험 | E40: 0 | F40: 1000000 | G40: 1000000 | H40: 1000000 | I40: =SUM(F40:H40) -> 3000000 | J40: 1000000 | K40: 1000000 | L40: 1000000 | M40: =SUM(J40:L40) -> 3000000 | N40: 1000000 | O40: 1000000 | P40: 1000000 | Q40: =SUM(N40:P40) -> 3000000 | R40: 1000000 | S40: 1000000 | T40: 1000000 | U40: =SUM(R40:T40) -> 3000000 | V40: =I40+M40+Q40+U40 -> 12000000
D41: 고용보험 | E41: 0 | F41: 300000 | G41: 300000 | H41: 300000 | I41: =SUM(F41:H41) -> 900000 | J41: 300000 | K41: 300000 | L41: 300000 | M41: =SUM(J41:L41) -> 900000 | N41: 300000 | O41: 300000 | P41: 300000 | Q41: =SUM(N41:P41) -> 900000 | R41: 300000 | S41: 300000 | T41: 300000 | U41: =SUM(R41:T41) -> 900000 | V41: =I41+M41+Q41+U41 -> 3600000
D42: 산재보험 | E42: 0 | F42: 100000 | G42: 100000 | H42: 100000 | I42: =SUM(F42:H42) -> 300000 | J42: 100000 | K42: 100000 | L42: 100000 | M42: =SUM(J42:L42) -> 300000 | N42: 100000 | O42: 100000 | P42: 100000 | Q42: =SUM(N42:P42) -> 300000 | R42: 100000 | S42: 100000 | T42: 100000 | U42: =SUM(R42:T42) -> 300000 | V42: =I42+M42+Q42+U42 -> 1200000
D43: 야근식대 | E43: 0 | F43: 26000 | G43: 26000 | H43: 26000 | I43: =SUM(F43:H43) -> 78000 | J43: 26000 | K43: 26000 | L43: 26000 | M43: =SUM(J43:L43) -> 78000 | N43: 26000 | O43: 26000 | P43: 26000 | Q43: =SUM(N43:P43) -> 78000 | R43: 26000 | S43: 26000 | T43: 26000 | U43: =SUM(R43:T43) -> 78000 | V43: =I43+M43+Q43+U43 -> 312000
D44: 회식대 | I44: =SUM(F44:H44) -> 0 | M44: =SUM(J44:L44) -> 0 | Q44: =SUM(N44:P44) -> 0 | U44: =SUM(R44:T44) -> 0 | V44: =I44+M44+Q44+U44 -> 0
D45: 경조사 | E45: 0 | I45: =SUM(F45:H45) -> 0 | M45: =SUM(J45:L45) -> 0 | Q45: =SUM(N45:P45) -> 0 | U45: =SUM(R45:T45) -> 0 | V45: =I45+M45+Q45+U45 -> 0
D46: 교육지원비 | E46: 0 | I46: =SUM(F46:H46) -> 0 | M46: =SUM(J46:L46) -> 0 | Q46: =SUM(N46:P46) -> 0 | U46: =SUM(R46:T46) -> 0 | V46: =I46+M46+Q46+U46 -> 0
D47: 직원상해보험 | E47: 0 | I47: =SUM(F47:H47) -> 0 | M47: =SUM(J47:L47) -> 0 | Q47: =SUM(N47:P47) -> 0 | U47: =SUM(R47:T47) -> 0 | V47: =I47+M47+Q47+U47 -> 0
D48: 건강검진 | E48: 0 | I48: =SUM(F48:H48) -> 0 | M48: =SUM(J48:L48) -> 0 | Q48: =SUM(N48:P48) -> 0 | U48: =SUM(R48:T48) -> 0 | V48: =I48+M48+Q48+U48 -> 0
D49: 통신비(핸드폰) | F49: 195000 | G49: 195000 | H49: 195000 | I49: =SUM(F49:H49) -> 585000 | J49: 195000 | K49: 195000 | L49: 195000 | M49: =SUM(J49:L49) -> 585000 | N49: 195000 | O49: 195000 | P49: 195000 | Q49: =SUM(N49:P49) -> 585000 | R49: 195000 | S49: 195000 | T49: 195000 | U49: =SUM(R49:T49) -> 585000 | V49: =I49+M49+Q49+U49 -> 2340000
D50: 체력단련비 | F50: 48000 | G50: 48000 | H50: 48000 | I50: =SUM(F50:H50) -> 144000 | J50: 48000 | K50: 48000 | L50: 48000 | M50: =SUM(J50:L50) -> 144000 | N50: 48000 | O50: 48000 | P50: 48000 | Q50: =SUM(N50:P50) -> 144000 | R50: 48000 | S50: 48000 | T50: 48000 | U50: =SUM(R50:T50) -> 144000 | V50: =I50+M50+Q50+U50 -> 576000
B51: Total Benefits | F51: =SUM(F39:F50) -> 2169000 | G51: =SUM(G39:G50) -> 2169000 | H51: =SUM(H39:H50) -> 2169000 | I51: =SUM(I39:I50) -> 6507000 | J51: =SUM(J39:J50) -> 2169000 | K51: =SUM(K39:K50) -> 2169000 | L51: =SUM(L39:L50) -> 2169000 | M51: =SUM(M39:M50) -> 6507000 | ... U51: =SUM(U39:U50) -> 6507000 | V51: =I51+M51+Q51+U51 -> 26028000
B52: Total Compensation & Benefits | F52: =F37+F51 -> 22169000 | G52: =G37+G51 -> 22169000 | H52: =H37+H51 -> 22169000 | I52: =I51+I37 -> 66507000 | J52: =J37+J51 -> 22169000 | K52: =K37+K51 -> 22169000 | L52: =L37+L51 -> 22169000 | M52: =M51+M37 -> 66507000 | N52: =N37+N51 -> 22169000 | O52: =O37+O51 -> 22169000 | P52: =P37+P51 -> 22169000 | Q52: =Q51+Q37 -> 66507000 | R52: =R37+R51 -> 22169000 | S52: =S37+S51 -> 22169000 | T52: =T37+T51 -> 22169000 | U52: =U51+U37 -> 66507000 | V52: =I52+M52+Q52+U52 -> 266028000
B53: Unfunded Consulting Expenses | E53: 0 | F53: 0 | G53: 0 | H53: 0 | I53: 0 | J53: 0 | K53: 0 | L53: 0 | M53: 0 | N53: 0 | O53: 0 | P53: 0 | Q53: 0 | R53: 0 | S53: 0 | T53: 0 | U53: 0 | V53: =I53+M53+Q53+U53 -> 0
B54: Travel & Entertainment
C55: 여비교통비(출장일비) | E55: 0 | I55: =SUM(F55:H55) -> 0 | M55: =SUM(J55:L55) -> 0 | Q55: =SUM(N55:P55) -> 0 | U55: =SUM(R55:T55) -> 0 | V55: =I55+M55+Q55+U55 -> 0
C56: 여비교통비(출장식대) | F56: 228000 | G56: 228000 | H56: 228000 | I56: =SUM(F56:H56) -> 684000 | J56: 228000 | K56: 228000 | L56: 228000 | M56: =SUM(J56:L56) -> 684000 | N56: 228000 | O56: 228000 | P56: 228000 | Q56: =SUM(N56:P56) -> 684000 | R56: 228000 | S56: 228000 | T56: 228000 | U56: =SUM(R56:T56) -> 684000 | V56: =I56+M56+Q56+U56 -> 2736000
C57: 여비교통비(통행,주차) | F57: 156000 | G57: 156000 | H57: 156000 | I57: =SUM(F57:H57) -> 468000 | J57: 156000 | K57: 156000 | L57: 156000 | M57: =SUM(J57:L57) -> 468000 | N57: 156000 | O57: 156000 | P57: 156000 | Q57: =SUM(N57:P57) -> 468000 | R57: 156000 | S57: 156000 | T57: 156000 | U57: =SUM(R57:T57) -> 468000 | V57: =I57+M57+Q57+U57 -> 1872000
C58: 여비교통비(항공,고속버스등) | F58: 253000 | G58: 253000 | H58: 253000 | I58: =SUM(F58:H58) -> 759000 | J58: 253000 | K58: 253000 | L58: 253000 | M58: =SUM(J58:L58) -> 759000 | N58: 253000 | O58: 253000 | P58: 253000 | Q58: =SUM(N58:P58) -> 759000 | R58: 253000 | S58: 253000 | T58: 253000 | U58: =SUM(R58:T58) -> 759000 | V58: =I58+M58+Q58+U58 -> 3036000
C59: 여비교통비(숙박) | F59: 147000 | G59: 147000 | H59: 147000 | I59: =SUM(F59:H59) -> 441000 | J59: 147000 | K59: 147000 | L59: 147000 | M59: =SUM(J59:L59) -> 441000 | N59: 147000 | O59: 147000 | P59: 147000 | Q59: =SUM(N59:P59) -> 441000 | R59: 147000 | S59: 147000 | T59: 147000 | U59: =SUM(R59:T59) -> 441000 | V59: =I59+M59+Q59+U59 -> 1764000
C60: 여비교통비(차량지원) | F60: 919000 | G60: 919000 | H60: 919000 | I60: =SUM(F60:H60) -> 2757000 | J60: 919000 | K60: 919000 | L60: 919000 | M60: =SUM(J60:L60) -> 2757000 | N60: 919000 | O60: 919000 | P60: 919000 | Q60: =SUM(N60:P60) -> 2757000 | R60: 919000 | S60: 919000 | T60: 919000 | U60: =SUM(R60:T60) -> 2757000 | V60: =I60+M60+Q60+U60 -> 11028000
C61: 여비교통비(국책과제_연구활동비) | I61: =SUM(F61:H61) -> 0 | M61: =SUM(J61:L61) -> 0 | Q61: =SUM(N61:P61) -> 0 | U61: =SUM(R61:T61) -> 0 | V61: =I61+M61+Q61+U61 -> 0
C62: 차량유지비 | E62: 0 | F62: 504000 | G62: 504000 | H62: 504000 | I62: =SUM(F62:H62) -> 1512000 | J62: 504000 | K62: 504000 | L62: 504000 | M62: =SUM(J62:L62) -> 1512000 | N62: 504000 | O62: 504000 | P62: 504000 | Q62: =SUM(N62:P62) -> 1512000 | R62: 504000 | S62: 504000 | T62: 504000 | U62: =SUM(R62:T62) -> 1512000 | V62: =I62+M62+Q62+U62 -> 6048000
C63: 해외출장비 | E63: 0 | I63: =SUM(F63:H63) -> 0 | M63: =SUM(J63:L63) -> 0 | Q63: =SUM(N63:P63) -> 0 | U63: =SUM(R63:T63) -> 0 | V63: =I63+M63+Q63+U63 -> 0
C64: 회의비 | E64: 0 | F64: 245000 | G64: 245000 | H64: 245000 | I64: =SUM(F64:H64) -> 735000 | J64: 245000 | K64: 245000 | L64: 245000 | M64: =SUM(J64:L64) -> 735000 | N64: 245000 | O64: 245000 | P64: 245000 | Q64: =SUM(N64:P64) -> 735000 | R64: 245000 | S64: 245000 | T64: 245000 | U64: =SUM(R64:T64) -> 735000 | V64: =I64+M64+Q64+U64 -> 2940000
C65: 접대비 | E65: 0 | F65: 1171000 | G65: 1171000 | H65: 1171000 | I65: =SUM(F65:H65) -> 3513000 | J65: 1171000 | K65: 1171000 | L65: 1171000 | M65: =SUM(J65:L65) -> 3513000 | N65: 1171000 | O65: 1171000 | P65: 1171000 | Q65: =SUM(N65:P65) -> 3513000 | R65: 1171000 | S65: 1171000 | T65: 1171000 | U65: =SUM(R65:T65) -> 3513000 | V65: =I65+M65+Q65+U65 -> 14052000
B66: Total Travel & Entertainment | F66: =SUM(F55:F65) -> 3623000 | G66: =SUM(G55:G65) -> 3623000 | H66: =SUM(H55:H65) -> 3623000 | I66: =SUM(I55:I65) -> 10869000 | J66: =SUM(J55:J65) -> 3623000 | K66: =SUM(K55:K65) -> 3623000 | L66: =SUM(L55:L65) -> 3623000 | M66: =SUM(M55:M65) -> 10869000 | ... U66: =SUM(U55:U65) -> 10869000 | V66: =I66+M66+Q66+U66 -> 43476000
B67: Product Marketing
C68: 행사비 | E68: 0 | I68: =SUM(F68:H68) -> 0 | M68: =SUM(J68:L68) -> 0 | Q68: =SUM(N68:P68) -> 0 | U68: =SUM(R68:T68) -> 0 | V68: =I68+M68+Q68+U68 -> 0
C69: 마케팅 | E69: 0 | I69: =SUM(F69:H69) -> 0 | M69: =SUM(J69:L69) -> 0 | Q69: =SUM(N69:P69) -> 0 | U69: =SUM(R69:T69) -> 0 | V69: =I69+M69+Q69+U69 -> 0
C70: 기타 | E70: 0 | I70: =SUM(F70:H70) -> 0 | M70: =SUM(J70:L70) -> 0 | Q70: =SUM(N70:P70) -> 0 | U70: =SUM(R70:T70) -> 0 | V70: =I70+M70+Q70+U70 -> 0
B71: Total Product Marketing | F71: =SUM(F68:F70) -> 0 | G71: =SUM(G68:G70) -> 0 | H71: =SUM(H68:H70) -> 0 | I71: =SUM(I68:I70) -> 0 | J71: =SUM(J68:J70) -> 0 | K71: =SUM(K68:K70) -> 0 | L71: =SUM(L68:L70) -> 0 | M71: =SUM(M68:M70) -> 0 | ... U71: =SUM(U68:U70) -> 0 | V71: =I71+M71+Q71+U71 -> 0
B72: Sales Activities
C73: 고객교육훈련비 | E73: 0 | I73: =SUM(F73:H73) -> 0 | M73: =SUM(J73:L73) -> 0 | Q73: =SUM(N73:P73) -> 0 | U73: =SUM(R73:T73) -> 0 | V73: =I73+M73+Q73+U73 -> 0
C74: Sales Promotions | E74: 0 | I74: =SUM(F74:H74) -> 0 | M74: =SUM(J74:L74) -> 0 | Q74: =SUM(N74:P74) -> 0 | U74: =SUM(R74:T74) -> 0 | V74: =I74+M74+Q74+U74 -> 0
C75: Other Sales Activities | E75: 0 | I75: =SUM(F75:H75) -> 0 | M75: =SUM(J75:L75) -> 0 | Q75: =SUM(N75:P75) -> 0 | U75: =SUM(R75:T75) -> 0 | V75: =I75+M75+Q75+U75 -> 0
B76: Total Sales Activities | F76: =SUM(F73:F75) -> 0 | G76: =SUM(G73:G75) -> 0 | H76: =SUM(H73:H75) -> 0 | I76: =SUM(I73:I75) -> 0 | J76: =SUM(J73:J75) -> 0 | K76: =SUM(K73:K75) -> 0 | L76: =SUM(L73:L75) -> 0 | M76: =SUM(M73:M75) -> 0 | ... U76: =SUM(U73:U75) -> 0 | V76: =I76+M76+Q76+U76 -> 0
D77: TOTAL CONTROLLABLE EXP. | F77: =F52+F53+F66+F71+F76 -> 25792000 | G77: =G52+G53+G66+G71+G76 -> 25792000 | H77: =H52+H53+H66+H71+H76 -> 25792000 | I77: =I76+I71+I66+I53+I52 -> 77376000 | J77: =J52+J53+J66+J71+J76 -> 25792000 | K77: =K52+K53+K66+K71+K76 -> 25792000 | L77: =L52+L53+L66+L71+L76 -> 25792000 | M77: =M76+M71+M66+M53+M52 -> 77376000 | N77: =N52+N53+N66+N71+N76 -> 25792000 | O77: =O52+O53+O66+O71+O76 -> 25792000 | P77: =P52+P53+P66+P71+P76 -> 25792000 | Q77: =Q76+Q71+Q66+Q53+Q52 -> 77376000 | R77: =R52+R53+R66+R71+R76 -> 25792000 | S77: =S52+S53+S66+S71+S76 -> 25792000 | T77: =T52+T53+T66+T71+T76 -> 25792000 | U77: =U76+U71+U66+U53+U52 -> 77376000 | V77: =I77+M77+Q77+U77 -> 309504000
A78: FIXED EXPENSE
B79: Facility & Equipment
C80: 사무실-임차료 | E80: 0 | I80: =SUM(F80:H80) -> 0 | M80: =SUM(J80:L80) -> 0 | Q80: =SUM(N80:P80) -> 0 | U80: =SUM(R80:T80) -> 0 | V80: =I80+M80+Q80+U80 -> 0
C81: 사무실-관리비 | E81: 0 | I81: =SUM(F81:H81) -> 0 | M81: =SUM(J81:L81) -> 0 | Q81: =SUM(N81:P81) -> 0 | U81: =SUM(R81:T81) -> 0 | V81: =I81+M81+Q81+U81 -> 0
C82: 비품 감가상각 | E82: 0 | I82: =SUM(F82:H82) -> 0 | M82: =SUM(J82:L82) -> 0 | Q82: =SUM(N82:P82) -> 0 | U82: =SUM(R82:T82) -> 0 | V82: =I82+M82+Q82+U82 -> 0
C83: 시설물 감가상각 | I83: =SUM(F83:H83) -> 0 | M83: =SUM(J83:L83) -> 0 | Q83: =SUM(N83:P83) -> 0 | U83: =SUM(R83:T83) -> 0 | V83: =I83+M83+Q83+U83 -> 0
C84: 기계설비 임차료 | I84: =SUM(F84:H84) -> 0 | M84: =SUM(J84:L84) -> 0 | Q84: =SUM(N84:P84) -> 0 | U84: =SUM(R84:T84) -> 0 | V84: =I84+M84+Q84+U84 -> 0
C85: 전화요금 | E85: 0 | I85: =SUM(F85:H85) -> 0 | M85: =SUM(J85:L85) -> 0 | Q85: =SUM(N85:P85) -> 0 | U85: =SUM(R85:T85) -> 0 | V85: =I85+M85+Q85+U85 -> 0
C86: 사무실관리비 | E86: 0 | I86: =SUM(F86:H86) -> 0 | M86: =SUM(J86:L86) -> 0 | Q86: =SUM(N86:P86) -> 0 | U86: =SUM(R86:T86) -> 0 | V86: =I86+M86+Q86+U86 -> 0
C87: 기타_프로그램임차 | E87: 0 | I87: =SUM(F87:H87) -> 0 | M87: =SUM(J87:L87) -> 0 | Q87: =SUM(N87:P87) -> 0 | U87: =SUM(R87:T87) -> 0 | V87: =I87+M87+Q87+U87 -> 0
B88: Total Facility Expense | F88: =SUM(F80:F87) -> 0 | G88: =SUM(G80:G87) -> 0 | H88: =SUM(H80:H87) -> 0 | I88: =SUM(I80:I87) -> 0 | J88: =SUM(J80:J87) -> 0 | K88: =SUM(K80:K87) -> 0 | L88: =SUM(L80:L87) -> 0 | M88: =SUM(M80:M87) -> 0 | ... U88: =SUM(U80:U87) -> 0 | V88: =I88+M88+Q88+U88 -> 0
B89: Total Software License for Internal Use | E89: 0 | F89: 0 | G89: 0 | H89: 0 | I89: =SUM(I81:I88) -> 0 | J89: 0 | K89: 0 | L89: 0 | M89: =SUM(M81:M88) -> 0 | N89: 0 | O89: 0 | P89: 0 | Q89: =SUM(Q81:Q88) -> 0 | R89: 0 | S89: 0 | T89: 0 | U89: =SUM(U81:U88) -> 0 | V89: =I89+M89+Q89+U89 -> 0
B90: Office Expense | I90: =SUM(F90:H90) -> 0 | M90: =SUM(J90:L90) -> 0 | Q90: =SUM(N90:P90) -> 0 | U90: =SUM(R90:T90) -> 0 | V90: =I90+M90+Q90+U90 -> 0
C91: 도서인쇄비 | E91: 0 | I91: =SUM(F91:H91) -> 0 | M91: =SUM(J91:L91) -> 0 | Q91: =SUM(N91:P91) -> 0 | U91: =SUM(R91:T91) -> 0 | V91: =I91+M91+Q91+U91 -> 0
C92: 사무용품비 | E92: 0 | F92: 0 | G92: 0 | H92: 0 | I92: =SUM(F92:H92) -> 0 | J92: 0 | K92: 0 | L92: 0 | M92: =SUM(J92:L92) -> 0 | N92: 0 | O92: 0 | P92: 0 | Q92: =SUM(N92:P92) -> 0 | R92: 0 | S92: 0 | T92: 0 | U92: =SUM(R92:T92) -> 0 | V92: =I92+M92+Q92+U92 -> 0
C93: 소모품비 | E93: 0 | I93: =SUM(F93:H93) -> 0 | M93: =SUM(J93:L93) -> 0 | Q93: =SUM(N93:P93) -> 0 | U93: =SUM(R93:T93) -> 0 | V93: =I93+M93+Q93+U93 -> 0
C94: 우편료 | E94: 0 | F94: 8000 | G94: 8000 | H94: 8000 | I94: =SUM(F94:H94) -> 24000 | J94: 8000 | K94: 8000 | L94: 8000 | M94: =SUM(J94:L94) -> 24000 | N94: 8000 | O94: 8000 | P94: 8000 | Q94: =SUM(N94:P94) -> 24000 | R94: 8000 | S94: 8000 | T94: 8000 | U94: =SUM(R94:T94) -> 24000 | V94: =I94+M94+Q94+U94 -> 96000
C95: 운반비 | E95: 0 | I95: =SUM(F95:H95) -> 0 | M95: =SUM(J95:L95) -> 0 | Q95: =SUM(N95:P95) -> 0 | U95: =SUM(R95:T95) -> 0 | V95: =I95+M95+Q95+U95 -> 0
C96: 수선비 | E96: 0 | I96: =SUM(F96:H96) -> 0 | M96: =SUM(J96:L96) -> 0 | Q96: =SUM(N96:P96) -> 0 | U96: =SUM(R96:T96) -> 0 | V96: =I96+M96+Q96+U96 -> 0
B97: Total Office Expense | F97: =SUM(F91:F96) -> 8000 | G97: =SUM(G91:G96) -> 8000 | H97: =SUM(H91:H96) -> 8000 | I97: =SUM(I91:I96) -> 24000 | J97: =SUM(J91:J96) -> 8000 | K97: =SUM(K91:K96) -> 8000 | L97: =SUM(L91:L96) -> 8000 | M97: =SUM(M91:M96) -> 24000 | ... U97: =SUM(U91:U96) -> 24000 | V97: =I97+M97+Q97+U97 -> 96000
B98: Business Expense
C99: 기술고문료 | E99: 0 | I99: =SUM(F99:H99) -> 0 | M99: =SUM(J99:L99) -> 0 | Q99: =SUM(N99:P99) -> 0 | U99: =SUM(R99:T99) -> 0 | V99: =I99+M99+Q99+U99 -> 0
C100: 세무감사료 | E100: 0 | I100: =SUM(F100:H100) -> 0 | M100: =SUM(J100:L100) -> 0 | Q100: =SUM(N100:P100) -> 0 | U100: =SUM(R100:T100) -> 0 | V100: =I100+M100+Q100+U100 -> 0
C101: 홈페이지관리외 | E101: 0 | I101: =SUM(F101:H101) -> 0 | M101: =SUM(J101:L101) -> 0 | Q101: =SUM(N101:P101) -> 0 | U101: =SUM(R101:T101) -> 0 | V101: =I101+M101+Q101+U101 -> 0
C102: 보증보험 | E102: 0 | I102: =SUM(F102:H102) -> 0 | M102: =SUM(J102:L102) -> 0 | Q102: =SUM(N102:P102) -> 0 | U102: =SUM(R102:T102) -> 0 | V102: =I102+M102+Q102+U102 -> 0
C103: 보험료-차량+여행자 | E103: 0 | I103: =SUM(F103:H103) -> 0 | M103: =SUM(J103:L103) -> 0 | Q103: =SUM(N103:P103) -> 0 | U103: =SUM(R103:T103) -> 0 | V103: =I103+M103+Q103+U103 -> 0
...

Sheet TST2
F1: 1월 | G1: 2월 | H1: 3월 | I1: Q1 | J1: 4월 | K1: 5월 | L1: 6월 | M1: Q2 | N1: 7월 | O1: 8월 | P1: 9월 | Q1: Q3 | R1: 10월 | S1: 11월 | T1: 12월 | U1: Q4 | V1: 2026
F2: Actual | G2: Actual | H2: Actual | I2: Total | J2: Actual | K2: Actual | L2: Actual | M2: Total | N2: Actual | O2: Actual | P2: Actual | Q2: Total | R2: Actual | S2: Actual | T2: Actual | U2: Total | V2: Total
A3: 매 출
B4: Solution Business
D5: Lease | E5: 1 | F5: 222000000 | G5: 0 | H5: 0 | I5: =H5+G5+F5 -> 222000000 | J5: 0 | K5: 0 | L5: 0 | M5: =L5+K5+J5 -> 0 | N5: 0 | O5: 0 | P5: 0 | Q5: =P5+O5+N5 -> 0 | R5: 0 | S5: 0 | T5: 0 | U5: =T5+S5+R5 -> 0 | V5: =U5+Q5+M5+I5 -> 222000000
D6: E&S | E6: 1 | F6: 265871000 | G6: 65000000 | H6: 65000000 | I6: =H6+G6+F6 -> 395871000 | J6: 65000000 | K6: 65000000 | L6: 65000000 | M6: =L6+K6+J6 -> 195000000 | N6: 65000000 | O6: 65000000 | P6: 65000000 | Q6: =P6+O6+N6 -> 195000000 | R6: 65000000 | S6: 65000000 | T6: 65000000 | U6: =T6+S6+R6 -> 195000000 | V6: =U6+Q6+M6+I6 -> 980871000
D7: Paid-up | E7: 1 | F7: 93609000 | G7: 90000000 | H7: 90000000 | I7: =H7+G7+F7 -> 273609000 | J7: 90000000 | K7: 90000000 | L7: 90000000 | M7: =L7+K7+J7 -> 270000000 | N7: 90000000 | O7: 90000000 | P7: 90000000 | Q7: =P7+O7+N7 -> 270000000 | R7: 90000000 | S7: 90000000 | T7: 90000000 | U7: =T7+S7+R7 -> 270000000 | V7: =U7+Q7+M7+I7 -> 1083609000
D8: 기타_HW Transfer | I8: =H8+G8+F8 -> 0 | M8: =L8+K8+J8 -> 0 | Q8: =P8+O8+N8 -> 0 | U8: =T8+S8+R8 -> 0 | V8: =U8+Q8+M8+I8 -> 0
D9: Service | I9: =H9+G9+F9 -> 0 | M9: =L9+K9+J9 -> 0 | Q9: =P9+O9+N9 -> 0 | U9: =T9+S9+R9 -> 0 | V9: =U9+Q9+M9+I9 -> 0
D10: Seminar/Training | I10: =H10+G10+F10 -> 0 | M10: =L10+K10+J10 -> 0 | Q10: =P10+O10+N10 -> 0 | U10: =T10+S10+R10 -> 0 | V10: =U10+Q10+M10+I10 -> 0
A12: 매 출 합 계 | F12: =SUM(F5:F10) -> 581480000 | G12: =SUM(G5:G10) -> 155000000 | H12: =SUM(H5:H10) -> 155000000 | I12: =SUM(I5:I10) -> 891480000 | J12: =SUM(J5:J10) -> 155000000 | K12: =SUM(K5:K10) -> 155000000 | L12: =SUM(L5:L10) -> 155000000 | M12: =SUM(M5:M10) -> 465000000 | ... V12: =SUM(V5:V10) -> 2286480000
A14: 매 출 원 가
C15: Royalty
D16: MSC Software | E16: 0 | F16: 49068000 | G16: 40000000 | H16: 40000000 | I16: =H16+G16+F16 -> 129068000 | J16: 40000000 | K16: 40000000 | L16: 40000000 | M16: =L16+K16+J16 -> 120000000 | N16: 40000000 | O16: 40000000 | P16: 40000000 | Q16: =P16+O16+N16 -> 120000000 | R16: 40000000 | S16: 40000000 | T16: 40000000 | U16: =T16+S16+R16 -> 120000000 | V16: =U16+Q16+M16+I16 -> 489068000
D17: SVD Software | F17: 43358000 | G17: 38000000 | H17: 38000000 | I17: =H17+G17+F17 -> 119358000 | J17: 38000000 | K17: 38000000 | L17: 38000000 | M17: =L17+K17+J17 -> 114000000 | N17: 38000000 | O17: 38000000 | P17: 38000000 | Q17: =P17+O17+N17 -> 114000000 | R17: 38000000 | S17: 38000000 | T17: 38000000 | U17: =T17+S17+R17 -> 114000000 | V17: =U17+Q17+M17+I17 -> 461358000
D18: TechSoft3D | I18: =H18+G18+F18 -> 0 | M18: =L18+K18+J18 -> 0 | Q18: =P18+O18+N18 -> 0 | U18: =T18+S18+R18 -> 0 | V18: =U18+Q18+M18+I18 -> 0
D19: TSV+KTM+그외 | F19: 9090000 | G19: 0 | H19: 0 | I19: =H19+G19+F19 -> 9090000 | J19: 0 | K19: 0 | L19: 0 | M19: =L19+K19+J19 -> 0 | N19: 0 | O19: 0 | P19: 0 | Q19: =P19+O19+N19 -> 0 | R19: 0 | S19: 0 | T19: 0 | U19: =T19+S19+R19 -> 0 | V19: =U19+Q19+M19+I19 -> 9090000
D20: 기타_System | E20: 0 | I20: =H20+G20+F20 -> 0 | M20: =L20+K20+J20 -> 0 | Q20: =P20+O20+N20 -> 0 | U20: =T20+S20+R20 -> 0 | V20: =U20+Q20+M20+I20 -> 0
C21: Outside Consultant | I21: =H21+G21+F21 -> 0 | M21: =L21+K21+J21 -> 0 | Q21: =P21+O21+N21 -> 0 | U21: =T21+S21+R21 -> 0 | V21: =U21+Q21+M21+I21 -> 0
C22: Finder commission | I22: =H22+G22+F22 -> 0 | M22: =L22+K22+J22 -> 0 | Q22: =P22+O22+N22 -> 0 | U22: =T22+S22+R22 -> 0 | V22: =U22+Q22+M22+I22 -> 0
C23: S/W+H/W 감가상각 | I23: =H23+G23+F23 -> 0 | M23: =L23+K23+J23 -> 0 | Q23: =P23+O23+N23 -> 0 | U23: =T23+S23+R23 -> 0 | V23: =U23+Q23+M23+I23 -> 0
C24: 지급수수료_기타+임차료 | F24: 29000 | G24: 29000 | H24: 29000 | I24: =H24+G24+F24 -> 87000 | J24: 29000 | K24: 29000 | L24: 29000 | M24: =L24+K24+J24 -> 87000 | N24: 29000 | O24: 29000 | P24: 29000 | Q24: =P24+O24+N24 -> 87000 | R24: 29000 | S24: 29000 | T24: 29000 | U24: =T24+S24+R24 -> 87000 | V24: =U24+Q24+M24+I24 -> 348000
C25: 보증보험+세금과공과 | E25: 0 | I25: =H25+G25+F25 -> 0 | M25: =L25+K25+J25 -> 0 | Q25: =P25+O25+N25 -> 0 | U25: =T25+S25+R25 -> 0 | V25: =U25+Q25+M25+I25 -> 0
A26: 매 출 원 가 합 계 | F26: =SUM(F16:F25) -> 101545000 | G26: =SUM(G16:G25) -> 78029000 | H26: =SUM(H16:H25) -> 78029000 | I26: =SUM(I16:I25) -> 257603000 | J26: =SUM(J16:J25) -> 78029000 | K26: =SUM(K16:K25) -> 78029000 | L26: =SUM(L16:L25) -> 78029000 | M26: =SUM(M16:M25) -> 234087000 | ... V26: =SUM(V16:V25) -> 959864000
A28: 매 출 이 익 (%)
C29: 총 매출이익 | F29: =F12-F26 -> 479935000 | G29: =G12-G26 -> 76971000 | H29: =H12-H26 -> 76971000 | I29: =I12-I26 -> 633877000 | J29: =J12-J26 -> 76971000 | K29: =K12-K26 -> 76971000 | L29: =L12-L26 -> 76971000 | M29: =M12-M26 -> 230913000 | ... V29: =V12-V26 -> 1326616000
D30: 총매출이익률 | F30: =IF(F12=0,0,F29/F12) -> 0.82536803 | G30: =IF(G12=0,0,G29/G12) -> 0.4965871 | H30: =IF(H12=0,0,H29/H12) -> 0.4965871 | I30: =IF(I12=0,0,I29/I12) -> 0.71103895 | J30: =IF(J12=0,0,J29/J12) -> 0.4965871 | K30: =IF(K12=0,0,K29/K12) -> 0.4965871 | L30: =IF(L12=0,0,L29/L12) -> 0.4965871 | M30: =IF(M12=0,0,M29/M12) -> 0.4965871 | ... V30: =IF(V12=0,0,V29/V12) -> 0.58020013
A31: CONTROLLABLE EXPENSE
C32: Salary & Wages
D33: 직원급여 | E33: 0 | F33: 10000000 | G33: 10000000 | H33: 10000000 | I33: =SUM(F33:H33) -> 30000000 | J33: 10000000 | K33: 10000000 | L33: 10000000 | M33: =SUM(J33:L33) -> 30000000 | N33: 10000000 | O33: 10000000 | P33: 10000000 | Q33: =SUM(N33:P33) -> 30000000 | R33: 10000000 | S33: 10000000 | T33: 10000000 | U33: =SUM(R33:T33) -> 30000000 | V33: =I33+M33+Q33+U33 -> 120000000
D34: 특별상여 | F34: 0 | G34: 0 | H34: 0 | I34: =SUM(F34:H34) -> 0 | J34: 0 | K34: 0 | L34: 0 | M34: =SUM(J34:L34) -> 0 | N34: 0 | O34: 0 | P34: 0 | Q34: =SUM(N34:P34) -> 0 | R34: 0 | S34: 0 | T34: 0 | U34: =SUM(R34:T34) -> 0 | V34: =I34+M34+Q34+U34 -> 0
D35: 기타-연차 | E35: 0 | I35: =SUM(F35:H35) -> 0 | M35: =SUM(J35:L35) -> 0 | Q35: =SUM(N35:P35) -> 0 | U35: =SUM(R35:T35) -> 0 | V35: =I35+M35+Q35+U35 -> 0
D36: 퇴직급여 | E36: 0 | F36: 1500000 | G36: 1500000 | H36: 1500000 | I36: =SUM(F36:H36) -> 4500000 | J36: 1500000 | K36: 1500000 | L36: 1500000 | M36: =SUM(J36:L36) -> 4500000 | N36: 1500000 | O36: 1500000 | P36: 1500000 | Q36: =SUM(N36:P36) -> 4500000 | R36: 1500000 | S36: 1500000 | T36: 1500000 | U36: =SUM(R36:T36) -> 4500000 | V36: =I36+M36+Q36+U36 -> 18000000
B37: Total Salary & Wages | F37: =SUM(F33:F36) -> 11500000 | G37: =SUM(G33:G36) -> 11500000 | H37: =SUM(H33:H36) -> 11500000 | I37: =SUM(I33:I36) -> 34500000 | J37: =SUM(J33:J36) -> 11500000 | K37: =SUM(K33:K36) -> 11500000 | L37: =SUM(L33:L36) -> 11500000 | M37: =SUM(M33:M36) -> 34500000 | ... U37: =SUM(U33:U36) -> 34500000 | V37: =I37+M37+Q37+U37 -> 138000000
C38: Benefits
D39: 국민연금 | E39: 0 | F39: 400000 | G39: 400000 | H39: 400000 | I39: =SUM(F39:H39) -> 1200000 | J39: 400000 | K39: 400000 | L39: 400000 | M39: =SUM(J39:L39) -> 1200000 | N39: 400000 | O39: 400000 | P39: 400000 | Q39: =SUM(N39:P39) -> 1200000 | R39: 400000 | S39: 400000 | T39: 400000 | U39: =SUM(R39:T39) -> 1200000 | V39: =I39+M39+Q39+U39 -> 4800000
D40: 건강보험 | E40: 0 | F40: 200000 | G40: 200000 | H40: 200000 | I40: =SUM(F40:H40) -> 600000 | J40: 200000 | K40: 200000 | L40: 200000 | M40: =SUM(J40:L40) -> 600000 | N40: 200000 | O40: 200000 | P40: 200000 | Q40: =SUM(N40:P40) -> 600000 | R40: 200000 | S40: 200000 | T40: 200000 | U40: =SUM(R40:T40) -> 600000 | V40: =I40+M40+Q40+U40 -> 2400000
D41: 고용보험 | E41: 0 | F41: 100000 | G41: 100000 | H41: 100000 | I41: =SUM(F41:H41) -> 300000 | J41: 100000 | K41: 100000 | L41: 100000 | M41: =SUM(J41:L41) -> 300000 | N41: 100000 | O41: 100000 | P41: 100000 | Q41: =SUM(N41:P41) -> 300000 | R41: 100000 | S41: 100000 | T41: 100000 | U41: =SUM(R41:T41) -> 300000 | V41: =I41+M41+Q41+U41 -> 1200000
D42: 산재보험 | E42: 0 | F42: 50000 | G42: 50000 | H42: 50000 | I42: =SUM(F42:H42) -> 150000 | J42: 50000 | K42: 50000 | L42: 50000 | M42: =SUM(J42:L42) -> 150000 | N42: 50000 | O42: 50000 | P42: 50000 | Q42: =SUM(N42:P42) -> 150000 | R42: 50000 | S42: 50000 | T42: 50000 | U42: =SUM(R42:T42) -> 150000 | V42: =I42+M42+Q42+U42 -> 600000
D43: 야근식대 | E43: 0 | F43: 64000 | G43: 64000 | H43: 64000 | I43: =SUM(F43:H43) -> 192000 | J43: 64000 | K43: 64000 | L43: 64000 | M43: =SUM(J43:L43) -> 192000 | N43: 64000 | O43: 64000 | P43: 64000 | Q43: =SUM(N43:P43) -> 192000 | R43: 64000 | S43: 64000 | T43: 64000 | U43: =SUM(R43:T43) -> 192000 | V43: =I43+M43+Q43+U43 -> 768000
D44: 회식대 | I44: =SUM(F44:H44) -> 0 | M44: =SUM(J44:L44) -> 0 | Q44: =SUM(N44:P44) -> 0 | U44: =SUM(R44:T44) -> 0 | V44: =I44+M44+Q44+U44 -> 0
D45: 경조사 | E45: 0 | I45: =SUM(F45:H45) -> 0 | M45: =SUM(J45:L45) -> 0 | Q45: =SUM(N45:P45) -> 0 | U45: =SUM(R45:T45) -> 0 | V45: =I45+M45+Q45+U45 -> 0
D46: 교육지원비 | E46: 0 | I46: =SUM(F46:H46) -> 0 | M46: =SUM(J46:L46) -> 0 | Q46: =SUM(N46:P46) -> 0 | U46: =SUM(R46:T46) -> 0 | V46: =I46+M46+Q46+U46 -> 0
D47: 직원상해보험 | E47: 0 | I47: =SUM(F47:H47) -> 0 | M47: =SUM(J47:L47) -> 0 | Q47: =SUM(N47:P47) -> 0 | U47: =SUM(R47:T47) -> 0 | V47: =I47+M47+Q47+U47 -> 0
D48: 건강검진 | E48: 0 | I48: =SUM(F48:H48) -> 0 | M48: =SUM(J48:L48) -> 0 | Q48: =SUM(N48:P48) -> 0 | U48: =SUM(R48:T48) -> 0 | V48: =I48+M48+Q48+U48 -> 0
D49: 통신비(핸드폰) | F49: 130000 | G49: 130000 | H49: 130000 | I49: =SUM(F49:H49) -> 390000 | J49: 130000 | K49: 130000 | L49: 130000 | M49: =SUM(J49:L49) -> 390000 | N49: 130000 | O49: 130000 | P49: 130000 | Q49: =SUM(N49:P49) -> 390000 | R49: 130000 | S49: 130000 | T49: 130000 | U49: =SUM(R49:T49) -> 390000 | V49: =I49+M49+Q49+U49 -> 1560000
D50: 체력단련비 | F50: 60000 | G50: 60000 | H50: 60000 | I50: =SUM(F50:H50) -> 180000 | J50: 60000 | K50: 60000 | L50: 60000 | M50: =SUM(J50:L50) -> 180000 | N50: 60000 | O50: 60000 | P50: 60000 | Q50: =SUM(N50:P50) -> 180000 | R50: 60000 | S50: 60000 | T50: 60000 | U50: =SUM(R50:T50) -> 180000 | V50: =I50+M50+Q50+U50 -> 720000
B51: Total Benefits | F51: =SUM(F39:F50) -> 1004000 | G51: =SUM(G39:G50) -> 1004000 | H51: =SUM(H39:H50) -> 1004000 | I51: =SUM(I39:I50) -> 3012000 | J51: =SUM(J39:J50) -> 1004000 | K51: =SUM(K39:K50) -> 1004000 | L51: =SUM(L39:L50) -> 1004000 | M51: =SUM(M39:M50) -> 3012000 | ... U51: =SUM(U39:U50) -> 3012000 | V51: =I51+M51+Q51+U51 -> 12048000
B52: Total Compensation & Benefits | F52: =F37+F51 -> 12504000 | G52: =G37+G51 -> 12504000 | H52: =H37+H51 -> 12504000 | I52: =I51+I37 -> 37512000 | J52: =J37+J51 -> 12504000 | K52: =K37+K51 -> 12504000 | L52: =L37+L51 -> 12504000 | M52: =M51+M37 -> 37512000 | N52: =N37+N51 -> 12504000 | O52: =O37+O51 -> 12504000 | P52: =P37+P51 -> 12504000 | Q52: =Q51+Q37 -> 37512000 | R52: =R37+R51 -> 12504000 | S52: =S37+S51 -> 12504000 | T52: =T37+T51 -> 12504000 | U52: =U51+U37 -> 37512000 | V52: =I52+M52+Q52+U52 -> 150048000
B53: Unfunded Consulting Expenses | E53: 0 | F53: 0 | G53: 0 | H53: 0 | I53: 0 | J53: 0 | K53: 0 | L53: 0 | M53: 0 | N53: 0 | O53: 0 | P53: 0 | Q53: 0 | R53: 0 | S53: 0 | T53: 0 | U53: 0 | V53: =I53+M53+Q53+U53 -> 0
B54: Travel & Entertainment
C55: 여비교통비(출장일비) | E55: 0 | I55: =SUM(F55:H55) -> 0 | M55: =SUM(J55:L55) -> 0 | Q55: =SUM(N55:P55) -> 0 | U55: =SUM(R55:T55) -> 0 | V55: =I55+M55+Q55+U55 -> 0
C56: 여비교통비(출장식대) | F56: 166000 | G56: 166000 | H56: 166000 | I56: =SUM(F56:H56) -> 498000 | J56: 166000 | K56: 166000 | L56: 166000 | M56: =SUM(J56:L56) -> 498000 | N56: 166000 | O56: 166000 | P56: 166000 | Q56: =SUM(N56:P56) -> 498000 | R56: 166000 | S56: 166000 | T56: 166000 | U56: =SUM(R56:T56) -> 498000 | V56: =I56+M56+Q56+U56 -> 1992000
C57: 여비교통비(통행,주차) | F57: 105000 | G57: 105000 | H57: 105000 | I57: =SUM(F57:H57) -> 315000 | J57: 105000 | K57: 105000 | L57: 105000 | M57: =SUM(J57:L57) -> 315000 | N57: 105000 | O57: 105000 | P57: 105000 | Q57: =SUM(N57:P57) -> 315000 | R57: 105000 | S57: 105000 | T57: 105000 | U57: =SUM(R57:T57) -> 315000 | V57: =I57+M57+Q57+U57 -> 1260000
C58: 여비교통비(항공,고속버스등) | F58: 222000 | G58: 222000 | H58: 222000 | I58: =SUM(F58:H58) -> 666000 | J58: 222000 | K58: 222000 | L58: 222000 | M58: =SUM(J58:L58) -> 666000 | N58: 222000 | O58: 222000 | P58: 222000 | Q58: =SUM(N58:P58) -> 666000 | R58: 222000 | S58: 222000 | T58: 222000 | U58: =SUM(R58:T58) -> 666000 | V58: =I58+M58+Q58+U58 -> 2664000
C59: 여비교통비(숙박) | I59: =SUM(F59:H59) -> 0 | M59: =SUM(J59:L59) -> 0 | Q59: =SUM(N59:P59) -> 0 | U59: =SUM(R59:T59) -> 0 | V59: =I59+M59+Q59+U59 -> 0
C60: 여비교통비(차량지원) | F60: 231000 | G60: 231000 | H60: 231000 | I60: =SUM(F60:H60) -> 693000 | J60: 231000 | K60: 231000 | L60: 231000 | M60: =SUM(J60:L60) -> 693000 | N60: 231000 | O60: 231000 | P60: 231000 | Q60: =SUM(N60:P60) -> 693000 | R60: 231000 | S60: 231000 | T60: 231000 | U60: =SUM(R60:T60) -> 693000 | V60: =I60+M60+Q60+U60 -> 2772000
C61: 여비교통비(국책과제_연구활동비) | I61: =SUM(F61:H61) -> 0 | M61: =SUM(J61:L61) -> 0 | Q61: =SUM(N61:P61) -> 0 | U61: =SUM(R61:T61) -> 0 | V61: =I61+M61+Q61+U61 -> 0
C62: 차량유지비 | E62: 0 | I62: =SUM(F62:H62) -> 0 | M62: =SUM(J62:L62) -> 0 | Q62: =SUM(N62:P62) -> 0 | U62: =SUM(R62:T62) -> 0 | V62: =I62+M62+Q62+U62 -> 0
C63: 해외출장비 | E63: 0 | F63: 724000 | G63: 724000 | H63: 724000 | I63: =SUM(F63:H63) -> 2172000 | J63: 724000 | K63: 724000 | L63: 724000 | M63: =SUM(J63:L63) -> 2172000 | N63: 724000 | O63: 724000 | P63: 724000 | Q63: =SUM(N63:P63) -> 2172000 | R63: 724000 | S63: 724000 | T63: 724000 | U63: =SUM(R63:T63) -> 2172000 | V63: =I63+M63+Q63+U63 -> 8688000
C64: 회의비 | E64: 0 | F64: 362000 | G64: 362000 | H64: 362000 | I64: =SUM(F64:H64) -> 1086000 | J64: 362000 | K64: 362000 | L64: 362000 | M64: =SUM(J64:L64) -> 1086000 | N64: 362000 | O64: 362000 | P64: 362000 | Q64: =SUM(N64:P64) -> 1086000 | R64: 362000 | S64: 362000 | T64: 362000 | U64: =SUM(R64:T64) -> 1086000 | V64: =I64+M64+Q64+U64 -> 4344000
C65: 접대비 | E65: 0 | F65: 570000 | G65: 570000 | H65: 570000 | I65: =SUM(F65:H65) -> 1710000 | J65: 570000 | K65: 570000 | L65: 570000 | M65: =SUM(J65:L65) -> 1710000 | N65: 570000 | O65: 570000 | P65: 570000 | Q65: =SUM(N65:P65) -> 1710000 | R65: 570000 | S65: 570000 | T65: 570000 | U65: =SUM(R65:T65) -> 1710000 | V65: =I65+M65+Q65+U65 -> 6840000
B66: Total Travel & Entertainment | F66: =SUM(F55:F65) -> 2380000 | G66: =SUM(G55:G65) -> 2380000 | H66: =SUM(H55:H65) -> 2380000 | I66: =SUM(I55:I65) -> 7140000 | J66: =SUM(J55:J65) -> 2380000 | K66: =SUM(K55:K65) -> 2380000 | L66: =SUM(L55:L65) -> 2380000 | M66: =SUM(M55:M65) -> 7140000 | ... U66: =SUM(U55:U65) -> 7140000 | V66: =I66+M66+Q66+U66 -> 28560000
B67: Product Marketing
C68: 행사비 | E68: 0 | I68: =SUM(F68:H68) -> 0 | M68: =SUM(J68:L68) -> 0 | Q68: =SUM(N68:P68) -> 0 | U68: =SUM(R68:T68) -> 0 | V68: =I68+M68+Q68+U68 -> 0
C69: 마케팅 | E69: 0 | I69: =SUM(F69:H69) -> 0 | M69: =SUM(J69:L69) -> 0 | Q69: =SUM(N69:P69) -> 0 | U69: =SUM(R69:T69) -> 0 | V69: =I69+M69+Q69+U69 -> 0
C70: 기타 | E70: 0 | I70: =SUM(F70:H70) -> 0 | M70: =SUM(J70:L70) -> 0 | Q70: =SUM(N70:P70) -> 0 | U70: =SUM(R70:T70) -> 0 | V70: =I70+M70+Q70+U70 -> 0
B71: Total Product Marketing | F71: =SUM(F68:F70) -> 0 | G71: =SUM(G68:G70) -> 0 | H71: =SUM(H68:H70) -> 0 | I71: =SUM(I68:I70) -> 0 | J71: =SUM(J68:J70) -> 0 | K71: =SUM(K68:K70) -> 0 | L71: =SUM(L68:L70) -> 0 | M71: =SUM(M68:M70) -> 0 | ... U71: =SUM(U68:U70) -> 0 | V71: =I71+M71+Q71+U71 -> 0
B72: Sales Activities
C73: 고객교육훈련비 | E73: 0 | I73: =SUM(F73:H73) -> 0 | M73: =SUM(J73:L73) -> 0 | Q73: =SUM(N73:P73) -> 0 | U73: =SUM(R73:T73) -> 0 | V73: =I73+M73+Q73+U73 -> 0
C74: Sales Promotions | E74: 0 | I74: =SUM(F74:H74) -> 0 | M74: =SUM(J74:L74) -> 0 | Q74: =SUM(N74:P74) -> 0 | U74: =SUM(R74:T74) -> 0 | V74: =I74+M74+Q74+U74 -> 0
C75: Other Sales Activities | E75: 0 | I75: =SUM(F75:H75) -> 0 | M75: =SUM(J75:L75) -> 0 | Q75: =SUM(N75:P75) -> 0 | U75: =SUM(R75:T75) -> 0 | V75: =I75+M75+Q75+U75 -> 0
B76: Total Sales Activities | F76: =SUM(F73:F75) -> 0 | G76: =SUM(G73:G75) -> 0 | H76: =SUM(H73:H75) -> 0 | I76: =SUM(I73:I75) -> 0 | J76: =SUM(J73:J75) -> 0 | K76: =SUM(K73:K75) -> 0 | L76: =SUM(L73:L75) -> 0 | M76: =SUM(M73:M75) -> 0 | ... U76: =SUM(U73:U75) -> 0 | V76: =I76+M76+Q76+U76 -> 0
D77: TOTAL CONTROLLABLE EXP. | F77: =F52+F53+F66+F71+F76 -> 14884000 | G77: =G52+G53+G66+G71+G76 -> 14884000 | H77: =H52+H53+H66+H71+H76 -> 14884000 | I77: =I76+I71+I66+I53+I52 -> 44652000 | J77: =J52+J53+J66+J71+J76 -> 14884000 | K77: =K52+K53+K66+K71+K76 -> 14884000 | L77: =L52+L53+L66+L71+L76 -> 14884000 | M77: =M76+M71+M66+M53+M52 -> 44652000 | N77: =N52+N53+N66+N71+N76 -> 14884000 | O77: =O52+O53+O66+O71+O76 -> 14884000 | P77: =P52+P53+P66+P71+P76 -> 14884000 | Q77: =Q76+Q71+Q66+Q53+Q52 -> 44652000 | R77: =R52+R53+R66+R71+R76 -> 14884000 | S77: =S52+S53+S66+S71+S76 -> 14884000 | T77: =T52+T53+T66+T71+T76 -> 14884000 | U77: =U76+U71+U66+U53+U52 -> 44652000 | V77: =I77+M77+Q77+U77 -> 178608000
A78: FIXED EXPENSE
B79: Facility & Equipment
C80: 사무실-임차료 | E80: 0 | I80: =SUM(F80:H80) -> 0 | M80: =SUM(J80:L80) -> 0 | Q80: =SUM(N80:P80) -> 0 | U80: =SUM(R80:T80) -> 0 | V80: =I80+M80+Q80+U80 -> 0
C81: 사무실-관리비 | E81: 0 | I81: =SUM(F81:H81) -> 0 | M81: =SUM(J81:L81) -> 0 | Q81: =SUM(N81:P81) -> 0 | U81: =SUM(R81:T81) -> 0 | V81: =I81+M81+Q81+U81 -> 0
C82: 비품 감가상각 | E82: 0 | I82: =SUM(F82:H82) -> 0 | M82: =SUM(J82:L82) -> 0 | Q82: =SUM(N82:P82) -> 0 | U82: =SUM(R82:T82) -> 0 | V82: =I82+M82+Q82+U82 -> 0
C83: 시설물 감가상각 | I83: =SUM(F83:H83) -> 0 | M83: =SUM(J83:L83) -> 0 | Q83: =SUM(N83:P83) -> 0 | U83: =SUM(R83:T83) -> 0 | V83: =I83+M83+Q83+U83 -> 0
C84: 기계설비 임차료 | I84: =SUM(F84:H84) -> 0 | M84: =SUM(J84:L84) -> 0 | Q84: =SUM(N84:P84) -> 0 | U84: =SUM(R84:T84) -> 0 | V84: =I84+M84+Q84+U84 -> 0
C85: 전화요금 | E85: 0 | I85: =SUM(F85:H85) -> 0 | M85: =SUM(J85:L85) -> 0 | Q85: =SUM(N85:P85) -> 0 | U85: =SUM(R85:T85) -> 0 | V85: =I85+M85+Q85+U85 -> 0
C86: 사무실관리비 | E86: 0 | I86: =SUM(F86:H86) -> 0 | M86: =SUM(J86:L86) -> 0 | Q86: =SUM(N86:P86) -> 0 | U86: =SUM(R86:T86) -> 0 | V86: =I86+M86+Q86+U86 -> 0
C87: 기타_프로그램임차 | E87: 0 | I87: =SUM(F87:H87) -> 0 | M87: =SUM(J87:L87) -> 0 | Q87: =SUM(N87:P87) -> 0 | U87: =SUM(R87:T87) -> 0 | V87: =I87+M87+Q87+U87 -> 0
B88: Total Facility Expense | F88: =SUM(F80:F87) -> 0 | G88: =SUM(G80:G87) -> 0 | H88: =SUM(H80:H87) -> 0 | I88: =SUM(I80:I87) -> 0 | J88: =SUM(J80:J87) -> 0 | K88: =SUM(K80:K87) -> 0 | L88: =SUM(L80:L87) -> 0 | M88: =SUM(M80:M87) -> 0 | ... U88: =SUM(U80:U87) -> 0 | V88: =I88+M88+Q88+U88 -> 0
B89: Total Software License for Internal Use | E89: 0 | F89: 0 | G89: 0 | H89: 0 | I89: =SUM(I81:I88) -> 0 | J89: 0 | K89: 0 | L89: 0 | M89: =SUM(M81:M88) -> 0 | N89: 0 | O89: 0 | P89: 0 | Q89: =SUM(Q81:Q88) -> 0 | R89: 0 | S89: 0 | T89: 0 | U89: =SUM(U81:U88) -> 0 | V89: =I89+M89+Q89+U89 -> 0
B90: Office Expense | I90: =SUM(F90:H90) -> 0 | M90: =SUM(J90:L90) -> 0 | Q90: =SUM(N90:P90) -> 0 | U90: =SUM(R90:T90) -> 0 | V90: =I90+M90+Q90+U90 -> 0
C91: 도서인쇄비 | E91: 0 | I91: =SUM(F91:H91) -> 0 | M91: =SUM(J91:L91) -> 0 | Q91: =SUM(N91:P91) -> 0 | U91: =SUM(R91:T91) -> 0 | V91: =I91+M91+Q91+U91 -> 0
C92: 사무용품비 | E92: 0 | F92: 7000 | G92: 7000 | H92: 7000 | I92: =SUM(F92:H92) -> 21000 | J92: 7000 | K92: 7000 | L92: 7000 | M92: =SUM(J92:L92) -> 21000 | N92: 7000 | O92: 7000 | P92: 7000 | Q92: =SUM(N92:P92) -> 21000 | R92: 7000 | S92: 7000 | T92: 7000 | U92: =SUM(R92:T92) -> 21000 | V92: =I92+M92+Q92+U92 -> 84000
C93: 소모품비 | E93: 0 | I93: =SUM(F93:H93) -> 0 | M93: =SUM(J93:L93) -> 0 | Q93: =SUM(N93:P93) -> 0 | U93: =SUM(R93:T93) -> 0 | V93: =I93+M93+Q93+U93 -> 0
C94: 우편료 | E94: 0 | F94: 4000 | G94: 4000 | H94: 4000 | I94: =SUM(F94:H94) -> 12000 | J94: 4000 | K94: 4000 | L94: 4000 | M94: =SUM(J94:L94) -> 12000 | N94: 4000 | O94: 4000 | P94: 4000 | Q94: =SUM(N94:P94) -> 12000 | R94: 4000 | S94: 4000 | T94: 4000 | U94: =SUM(R94:T94) -> 12000 | V94: =I94+M94+Q94+U94 -> 48000
C95: 운반비 | E95: 0 | F95: 103000 | G95: 103000 | H95: 103000 | I95: =SUM(F95:H95) -> 309000 | J95: 103000 | K95: 103000 | L95: 103000 | M95: =SUM(J95:L95) -> 309000 | N95: 103000 | O95: 103000 | P95: 103000 | Q95: =SUM(N95:P95) -> 309000 | R95: 103000 | S95: 103000 | T95: 103000 | U95: =SUM(R95:T95) -> 309000 | V95: =I95+M95+Q95+U95 -> 1236000
C96: 수선비 | E96: 0 | I96: =SUM(F96:H96) -> 0 | M96: =SUM(J96:L96) -> 0 | Q96: =SUM(N96:P96) -> 0 | U96: =SUM(R96:T96) -> 0 | V96: =I96+M96+Q96+U96 -> 0
B97: Total Office Expense | F97: =SUM(F91:F96) -> 114000 | G97: =SUM(G91:G96) -> 114000 | H97: =SUM(H91:H96) -> 114000 | I97: =SUM(I91:I96) -> 342000 | J97: =SUM(J91:J96) -> 114000 | K97: =SUM(K91:K96) -> 114000 | L97: =SUM(L91:L96) -> 114000 | M97: =SUM(M91:M96) -> 342000 | ... U97: =SUM(U91:U96) -> 342000 | V97: =I97+M97+Q97+U97 -> 1368000
B98: Business Expense
C99: 기술고문료 | E99: 0 | I99: =SUM(F99:H99) -> 0 | M99: =SUM(J99:L99) -> 0 | Q99: =SUM(N99:P99) -> 0 | U99: =SUM(R99:T99) -> 0 | V99: =I99+M99+Q99+U99 -> 0
C100: 세무감사료 | E100: 0 | I100: =SUM(F100:H100) -> 0 | M100: =SUM(J100:L100) -> 0 | Q100: =SUM(N100:P100) -> 0 | U100: =SUM(R100:T100) -> 0 | V100: =I100+M100+Q100+U100 -> 0
C101: 홈페이지관리외 | E101: 0 | I101: =SUM(F101:H101) -> 0 | M101: =SUM(J101:L101) -> 0 | Q101: =SUM(N101:P101) -> 0 | U101: =SUM(R101:T101) -> 0 | V101: =I101+M101+Q101+U101 -> 0
C102: 보증보험 | E102: 0 | I102: =SUM(F102:H102) -> 0 | M102: =SUM(J102:L102) -> 0 | Q102: =SUM(N102:P102) -> 0 | U102: =SUM(R102:T102) -> 0 | V102: =I102+M102+Q102+U102 -> 0
C103: 보험료-차량+여행자 | E103: 0 | I103: =SUM(F103:H103) -> 0 | M103: =SUM(J103:L103) -> 0 | Q103: =SUM(N103:P103) -> 0 | U103: =SUM(R103:T103) -> 0 | V103: =I103+M103+Q103+U103 -> 0
...

Sheet MKT
F1: 1월 | G1: 2월 | H1: 3월 | I1: Q1 | J1: 4월 | K1: 5월 | L1: 6월 | M1: Q2 | N1: 7월 | O1: 8월 | P1: 9월 | Q1: Q3 | R1: 10월 | S1: 11월 | T1: 12월 | U1: Q4 | V1: 2026
F2: Actual | G2: Actual | H2: Actual | I2: Total | J2: Actual | K2: Actual | L2: Actual | M2: Total | N2: Actual | O2: Actual | P2: Actual | Q2: Total | R2: Actual | S2: Actual | T2: Actual | U2: Total | V2: Total
A3: 매 출
B4: Solution Business
D5: Lease | E5: 1 | I5: =H5+G5+F5 -> 0 | M5: =L5+K5+J5 -> 0 | Q5: =P5+O5+N5 -> 0 | U5: =T5+S5+R5 -> 0 | V5: =U5+Q5+M5+I5 -> 0
D6: E&S | E6: 1 | I6: =H6+G6+F6 -> 0 | M6: =L6+K6+J6 -> 0 | Q6: =P6+O6+N6 -> 0 | U6: =T6+S6+R6 -> 0 | V6: =U6+Q6+M6+I6 -> 0
D7: Paid-up | E7: 1 | I7: =H7+G7+F7 -> 0 | M7: =L7+K7+J7 -> 0 | Q7: =P7+O7+N7 -> 0 | U7: =T7+S7+R7 -> 0 | V7: =U7+Q7+M7+I7 -> 0
D8: 기타_HW Transfer | I8: =H8+G8+F8 -> 0 | M8: =L8+K8+J8 -> 0 | Q8: =P8+O8+N8 -> 0 | U8: =T8+S8+R8 -> 0 | V8: =U8+Q8+M8+I8 -> 0
D9: Service | I9: =H9+G9+F9 -> 0 | M9: =L9+K9+J9 -> 0 | Q9: =P9+O9+N9 -> 0 | U9: =T9+S9+R9 -> 0 | V9: =U9+Q9+M9+I9 -> 0
D10: Seminar/Training | I10: =H10+G10+F10 -> 0 | M10: =L10+K10+J10 -> 0 | Q10: =P10+O10+N10 -> 0 | U10: =T10+S10+R10 -> 0 | V10: =U10+Q10+M10+I10 -> 0
A12: 매 출 합 계 | F12: =SUM(F5:F10) -> 0 | G12: =SUM(G5:G10) -> 0 | H12: =SUM(H5:H10) -> 0 | I12: =SUM(I5:I10) -> 0 | J12: =SUM(J5:J10) -> 0 | K12: =SUM(K5:K10) -> 0 | L12: =SUM(L5:L10) -> 0 | M12: =SUM(M5:M10) -> 0 | ... V12: =SUM(V5:V10) -> 0
A14: 매 출 원 가
C15: Royalty
D16: MSC Software | E16: 0 | I16: =H16+G16+F16 -> 0 | M16: =L16+K16+J16 -> 0 | Q16: =P16+O16+N16 -> 0 | U16: =T16+S16+R16 -> 0 | V16: =U16+Q16+M16+I16 -> 0
D17: SVD Software | I17: =H17+G17+F17 -> 0 | M17: =L17+K17+J17 -> 0 | Q17: =P17+O17+N17 -> 0 | U17: =T17+S17+R17 -> 0 | V17: =U17+Q17+M17+I17 -> 0
D18: TechSoft3D | I18: =H18+G18+F18 -> 0 | M18: =L18+K18+J18 -> 0 | Q18: =P18+O18+N18 -> 0 | U18: =T18+S18+R18 -> 0 | V18: =U18+Q18+M18+I18 -> 0
D19: TSV+KTM+그외 | I19: =H19+G19+F19 -> 0 | M19: =L19+K19+J19 -> 0 | Q19: =P19+O19+N19 -> 0 | U19: =T19+S19+R19 -> 0 | V19: =U19+Q19+M19+I19 -> 0
D20: 기타_System | E20: 0 | I20: =H20+G20+F20 -> 0 | M20: =L20+K20+J20 -> 0 | Q20: =P20+O20+N20 -> 0 | U20: =T20+S20+R20 -> 0 | V20: =U20+Q20+M20+I20 -> 0
C21: Outside Consultant | I21: =H21+G21+F21 -> 0 | M21: =L21+K21+J21 -> 0 | Q21: =P21+O21+N21 -> 0 | U21: =T21+S21+R21 -> 0 | V21: =U21+Q21+M21+I21 -> 0
C22: Finder commission | I22: =H22+G22+F22 -> 0 | M22: =L22+K22+J22 -> 0 | Q22: =P22+O22+N22 -> 0 | U22: =T22+S22+R22 -> 0 | V22: =U22+Q22+M22+I22 -> 0
C23: S/W+H/W 감가상각 | I23: =H23+G23+F23 -> 0 | M23: =L23+K23+J23 -> 0 | Q23: =P23+O23+N23 -> 0 | U23: =T23+S23+R23 -> 0 | V23: =U23+Q23+M23+I23 -> 0
C24: 지급수수료_기타+임차료 | I24: =H24+G24+F24 -> 0 | M24: =L24+K24+J24 -> 0 | Q24: =P24+O24+N24 -> 0 | U24: =T24+S24+R24 -> 0 | V24: =U24+Q24+M24+I24 -> 0
C25: 보증보험+세금과공과 | E25: 0 | I25: =H25+G25+F25 -> 0 | M25: =L25+K25+J25 -> 0 | Q25: =P25+O25+N25 -> 0 | U25: =T25+S25+R25 -> 0 | V25: =U25+Q25+M25+I25 -> 0
A26: 매 출 원 가 합 계 | F26: =SUM(F16:F25) -> 0 | G26: =SUM(G16:G25) -> 0 | H26: =SUM(H16:H25) -> 0 | I26: =SUM(I16:I25) -> 0 | J26: =SUM(J16:J25) -> 0 | K26: =SUM(K16:K25) -> 0 | L26: =SUM(L16:L25) -> 0 | M26: =SUM(M16:M25) -> 0 | ... V26: =SUM(V16:V25) -> 0
A28: 매 출 이 익 (%)
C29: 총 매출이익 | F29: =F12-F26 -> 0 | G29: =G12-G26 -> 0 | H29: =H12-H26 -> 0 | I29: =I12-I26 -> 0 | J29: =J12-J26 -> 0 | K29: =K12-K26 -> 0 | L29: =L12-L26 -> 0 | M29: =M12-M26 -> 0 | ... V29: =V12-V26 -> 0
D30: 총매출이익률 | F30: =IF(F12=0,0,F29/F12) -> 0 | G30: =IF(G12=0,0,G29/G12) -> 0 | H30: =IF(H12=0,0,H29/H12) -> 0 | I30: =IF(I12=0,0,I29/I12) -> 0 | J30: =IF(J12=0,0,J29/J12) -> 0 | K30: =IF(K12=0,0,K29/K12) -> 0 | L30: =IF(L12=0,0,L29/L12) -> 0 | M30: =IF(M12=0,0,M29/M12) -> 0 | ... V30: =IF(V12=0,0,V29/V12) -> 0
A31: CONTROLLABLE EXPENSE
C32: Salary & Wages
D33: 직원급여 | E33: 0 | F33: 10000000 | G33: 10000000 | H33: 10000000 | I33: =SUM(F33:H33) -> 30000000 | J33: 10000000 | K33: 10000000 | L33: 10000000 | M33: =SUM(J33:L33) -> 30000000 | N33: 10000000 | O33: 10000000 | P33: 10000000 | Q33: =SUM(N33:P33) -> 30000000 | R33: 10000000 | S33: 10000000 | T33: 10000000 | U33: =SUM(R33:T33) -> 30000000 | V33: =I33+M33+Q33+U33 -> 120000000
D34: 특별상여 | F34: 0 | G34: 0 | H34: 0 | I34: =SUM(F34:H34) -> 0 | J34: 0 | K34: 0 | L34: 0 | M34: =SUM(J34:L34) -> 0 | N34: 0 | O34: 0 | P34: 0 | Q34: =SUM(N34:P34) -> 0 | R34: 0 | S34: 0 | T34: 0 | U34: =SUM(R34:T34) -> 0 | V34: =I34+M34+Q34+U34 -> 0
D35: 기타-연차 | E35: 0 | I35: =SUM(F35:H35) -> 0 | M35: =SUM(J35:L35) -> 0 | Q35: =SUM(N35:P35) -> 0 | U35: =SUM(R35:T35) -> 0 | V35: =I35+M35+Q35+U35 -> 0
D36: 퇴직급여 | E36: 0 | F36: 1500000 | G36: 1500000 | H36: 1500000 | I36: =SUM(F36:H36) -> 4500000 | J36: 1500000 | K36: 1500000 | L36: 1500000 | M36: =SUM(J36:L36) -> 4500000 | N36: 1500000 | O36: 1500000 | P36: 1500000 | Q36: =SUM(N36:P36) -> 4500000 | R36: 1500000 | S36: 1500000 | T36: 1500000 | U36: =SUM(R36:T36) -> 4500000 | V36: =I36+M36+Q36+U36 -> 18000000
B37: Total Salary & Wages | F37: =SUM(F33:F36) -> 11500000 | G37: =SUM(G33:G36) -> 11500000 | H37: =SUM(H33:H36) -> 11500000 | I37: =SUM(I33:I36) -> 34500000 | J37: =SUM(J33:J36) -> 11500000 | K37: =SUM(K33:K36) -> 11500000 | L37: =SUM(L33:L36) -> 11500000 | M37: =SUM(M33:M36) -> 34500000 | ... U37: =SUM(U33:U36) -> 34500000 | V37: =I37+M37+Q37+U37 -> 138000000
C38: Benefits
D39: 국민연금 | E39: 0 | F39: 600000 | G39: 600000 | H39: 600000 | I39: =SUM(F39:H39) -> 1800000 | J39: 600000 | K39: 600000 | L39: 600000 | M39: =SUM(J39:L39) -> 1800000 | N39: 600000 | O39: 600000 | P39: 600000 | Q39: =SUM(N39:P39) -> 1800000 | R39: 600000 | S39: 600000 | T39: 600000 | U39: =SUM(R39:T39) -> 1800000 | V39: =I39+M39+Q39+U39 -> 7200000
D40: 건강보험 | E40: 0 | F40: 500000 | G40: 500000 | H40: 500000 | I40: =SUM(F40:H40) -> 1500000 | J40: 500000 | K40: 500000 | L40: 500000 | M40: =SUM(J40:L40) -> 1500000 | N40: 500000 | O40: 500000 | P40: 500000 | Q40: =SUM(N40:P40) -> 1500000 | R40: 500000 | S40: 500000 | T40: 500000 | U40: =SUM(R40:T40) -> 1500000 | V40: =I40+M40+Q40+U40 -> 6000000
D41: 고용보험 | E41: 0 | F41: 150000 | G41: 150000 | H41: 150000 | I41: =SUM(F41:H41) -> 450000 | J41: 150000 | K41: 150000 | L41: 150000 | M41: =SUM(J41:L41) -> 450000 | N41: 150000 | O41: 150000 | P41: 150000 | Q41: =SUM(N41:P41) -> 450000 | R41: 150000 | S41: 150000 | T41: 150000 | U41: =SUM(R41:T41) -> 450000 | V41: =I41+M41+Q41+U41 -> 1800000
D42: 산재보험 | E42: 0 | F42: 100000 | G42: 100000 | H42: 100000 | I42: =SUM(F42:H42) -> 300000 | J42: 100000 | K42: 100000 | L42: 100000 | M42: =SUM(J42:L42) -> 300000 | N42: 100000 | O42: 100000 | P42: 100000 | Q42: =SUM(N42:P42) -> 300000 | R42: 100000 | S42: 100000 | T42: 100000 | U42: =SUM(R42:T42) -> 300000 | V42: =I42+M42+Q42+U42 -> 1200000
D43: 야근식대 | E43: 0 | F43: 18000 | G43: 18000 | H43: 18000 | I43: =SUM(F43:H43) -> 54000 | J43: 18000 | K43: 18000 | L43: 18000 | M43: =SUM(J43:L43) -> 54000 | N43: 18000 | O43: 18000 | P43: 18000 | Q43: =SUM(N43:P43) -> 54000 | R43: 18000 | S43: 18000 | T43: 18000 | U43: =SUM(R43:T43) -> 54000 | V43: =I43+M43+Q43+U43 -> 216000
D44: 회식대 | F44: 187000 | G44: 187000 | H44: 187000 | I44: =SUM(F44:H44) -> 561000 | J44: 187000 | K44: 187000 | L44: 187000 | M44: =SUM(J44:L44) -> 561000 | N44: 187000 | O44: 187000 | P44: 187000 | Q44: =SUM(N44:P44) -> 561000 | R44: 187000 | S44: 187000 | T44: 187000 | U44: =SUM(R44:T44) -> 561000 | V44: =I44+M44+Q44+U44 -> 2244000
D45: 경조사 | E45: 0 | F45: 100000 | G45: 100000 | H45: 100000 | I45: =SUM(F45:H45) -> 300000 | J45: 100000 | K45: 100000 | L45: 100000 | M45: =SUM(J45:L45) -> 300000 | N45: 100000 | O45: 100000 | P45: 100000 | Q45: =SUM(N45:P45) -> 300000 | R45: 100000 | S45: 100000 | T45: 100000 | U45: =SUM(R45:T45) -> 300000 | V45: =I45+M45+Q45+U45 -> 1200000
D46: 교육지원비 | E46: 0 | I46: =SUM(F46:H46) -> 0 | M46: =SUM(J46:L46) -> 0 | Q46: =SUM(N46:P46) -> 0 | U46: =SUM(R46:T46) -> 0 | V46: =I46+M46+Q46+U46 -> 0
D47: 직원상해보험 | E47: 0 | I47: =SUM(F47:H47) -> 0 | M47: =SUM(J47:L47) -> 0 | Q47: =SUM(N47:P47) -> 0 | U47: =SUM(R47:T47) -> 0 | V47: =I47+M47+Q47+U47 -> 0
D48: 건강검진 | E48: 0 | I48: =SUM(F48:H48) -> 0 | M48: =SUM(J48:L48) -> 0 | Q48: =SUM(N48:P48) -> 0 | U48: =SUM(R48:T48) -> 0 | V48: =I48+M48+Q48+U48 -> 0
D49: 통신비(핸드폰) | F49: 90000 | G49: 90000 | H49: 90000 | I49: =SUM(F49:H49) -> 270000 | J49: 90000 | K49: 90000 | L49: 90000 | M49: =SUM(J49:L49) -> 270000 | N49: 90000 | O49: 90000 | P49: 90000 | Q49: =SUM(N49:P49) -> 270000 | R49: 90000 | S49: 90000 | T49: 90000 | U49: =SUM(R49:T49) -> 270000 | V49: =I49+M49+Q49+U49 -> 1080000
D50: 체력단련비 | F50: 20000 | G50: 20000 | H50: 20000 | I50: =SUM(F50:H50) -> 60000 | J50: 20000 | K50: 20000 | L50: 20000 | M50: =SUM(J50:L50) -> 60000 | N50: 20000 | O50: 20000 | P50: 20000 | Q50: =SUM(N50:P50) -> 60000 | R50: 20000 | S50: 20000 | T50: 20000 | U50: =SUM(R50:T50) -> 60000 | V50: =I50+M50+Q50+U50 -> 240000
B51: Total Benefits | F51: =SUM(F39:F50) -> 1765000 | G51: =SUM(G39:G50) -> 1765000 | H51: =SUM(H39:H50) -> 1765000 | I51: =SUM(I39:I50) -> 5295000 | J51: =SUM(J39:J50) -> 1765000 | K51: =SUM(K39:K50) -> 1765000 | L51: =SUM(L39:L50) -> 1765000 | M51: =SUM(M39:M50) -> 5295000 | ... U51: =SUM(U39:U50) -> 5295000 | V51: =I51+M51+Q51+U51 -> 21180000
B52: Total Compensation & Benefits | F52: =F37+F51 -> 13265000 | G52: =G37+G51 -> 13265000 | H52: =H37+H51 -> 13265000 | I52: =I51+I37 -> 39795000 | J52: =J37+J51 -> 13265000 | K52: =K37+K51 -> 13265000 | L52: =L37+L51 -> 13265000 | M52: =M51+M37 -> 39795000 | N52: =N37+N51 -> 13265000 | O52: =O37+O51 -> 13265000 | P52: =P37+P51 -> 13265000 | Q52: =Q51+Q37 -> 39795000 | R52: =R37+R51 -> 13265000 | S52: =S37+S51 -> 13265000 | T52: =T37+T51 -> 13265000 | U52: =U51+U37 -> 39795000 | V52: =I52+M52+Q52+U52 -> 159180000
B53: Unfunded Consulting Expenses | E53: 0 | F53: 0 | G53: 0 | H53: 0 | I53: 0 | J53: 0 | K53: 0 | L53: 0 | M53: 0 | N53: 0 | O53: 0 | P53: 0 | Q53: 0 | R53: 0 | S53: 0 | T53: 0 | U53: 0 | V53: =I53+M53+Q53+U53 -> 0
B54: Travel & Entertainment
C55: 여비교통비(출장일비) | E55: 0 | I55: =SUM(F55:H55) -> 0 | M55: =SUM(J55:L55) -> 0 | Q55: =SUM(N55:P55) -> 0 | U55: =SUM(R55:T55) -> 0 | V55: =I55+M55+Q55+U55 -> 0
C56: 여비교통비(출장식대) | F56: 163000 | G56: 163000 | H56: 163000 | I56: =SUM(F56:H56) -> 489000 | J56: 163000 | K56: 163000 | L56: 163000 | M56: =SUM(J56:L56) -> 489000 | N56: 163000 | O56: 163000 | P56: 163000 | Q56: =SUM(N56:P56) -> 489000 | R56: 163000 | S56: 163000 | T56: 163000 | U56: =SUM(R56:T56) -> 489000 | V56: =I56+M56+Q56+U56 -> 1956000
C57: 여비교통비(통행,주차) | I57: =SUM(F57:H57) -> 0 | M57: =SUM(J57:L57) -> 0 | Q57: =SUM(N57:P57) -> 0 | U57: =SUM(R57:T57) -> 0 | V57: =I57+M57+Q57+U57 -> 0
C58: 여비교통비(항공,고속버스등) | F58: 399000 | G58: 399000 | H58: 399000 | I58: =SUM(F58:H58) -> 1197000 | J58: 399000 | K58: 399000 | L58: 399000 | M58: =SUM(J58:L58) -> 1197000 | N58: 399000 | O58: 399000 | P58: 399000 | Q58: =SUM(N58:P58) -> 1197000 | R58: 399000 | S58: 399000 | T58: 399000 | U58: =SUM(R58:T58) -> 1197000 | V58: =I58+M58+Q58+U58 -> 4788000
C59: 여비교통비(숙박) | F59: 420000 | G59: 420000 | H59: 420000 | I59: =SUM(F59:H59) -> 1260000 | J59: 420000 | K59: 420000 | L59: 420000 | M59: =SUM(J59:L59) -> 1260000 | N59: 420000 | O59: 420000 | P59: 420000 | Q59: =SUM(N59:P59) -> 1260000 | R59: 420000 | S59: 420000 | T59: 420000 | U59: =SUM(R59:T59) -> 1260000 | V59: =I59+M59+Q59+U59 -> 5040000
C60: 여비교통비(차량지원) | I60: =SUM(F60:H60) -> 0 | M60: =SUM(J60:L60) -> 0 | Q60: =SUM(N60:P60) -> 0 | U60: =SUM(R60:T60) -> 0 | V60: =I60+M60+Q60+U60 -> 0
C61: 여비교통비(국책과제_연구활동비) | I61: =SUM(F61:H61) -> 0 | M61: =SUM(J61:L61) -> 0 | Q61: =SUM(N61:P61) -> 0 | U61: =SUM(R61:T61) -> 0 | V61: =I61+M61+Q61+U61 -> 0
C62: 차량유지비 | E62: 0 | I62: =SUM(F62:H62) -> 0 | M62: =SUM(J62:L62) -> 0 | Q62: =SUM(N62:P62) -> 0 | U62: =SUM(R62:T62) -> 0 | V62: =I62+M62+Q62+U62 -> 0
C63: 해외출장비 | E63: 0 | F63: 724000 | G63: 724000 | H63: 724000 | I63: =SUM(F63:H63) -> 2172000 | J63: 724000 | K63: 724000 | L63: 724000 | M63: =SUM(J63:L63) -> 2172000 | N63: 724000 | O63: 724000 | P63: 724000 | Q63: =SUM(N63:P63) -> 2172000 | R63: 724000 | S63: 724000 | T63: 724000 | U63: =SUM(R63:T63) -> 2172000 | V63: =I63+M63+Q63+U63 -> 8688000
C64: 회의비 | E64: 0 | F64: 82000 | G64: 82000 | H64: 82000 | I64: =SUM(F64:H64) -> 246000 | J64: 82000 | K64: 82000 | L64: 82000 | M64: =SUM(J64:L64) -> 246000 | N64: 82000 | O64: 82000 | P64: 82000 | Q64: =SUM(N64:P64) -> 246000 | R64: 82000 | S64: 82000 | T64: 82000 | U64: =SUM(R64:T64) -> 246000 | V64: =I64+M64+Q64+U64 -> 984000
C65: 접대비 | E65: 0 | I65: =SUM(F65:H65) -> 0 | M65: =SUM(J65:L65) -> 0 | Q65: =SUM(N65:P65) -> 0 | U65: =SUM(R65:T65) -> 0 | V65: =I65+M65+Q65+U65 -> 0
B66: Total Travel & Entertainment | F66: =SUM(F55:F65) -> 1788000 | G66: =SUM(G55:G65) -> 1788000 | H66: =SUM(H55:H65) -> 1788000 | I66: =SUM(I55:I65) -> 5364000 | J66: =SUM(J55:J65) -> 1788000 | K66: =SUM(K55:K65) -> 1788000 | L66: =SUM(L55:L65) -> 1788000 | M66: =SUM(M55:M65) -> 5364000 | ... U66: =SUM(U55:U65) -> 5364000 | V66: =I66+M66+Q66+U66 -> 21456000
B67: Product Marketing
C68: 행사비 | E68: 0 | F68: 0 | I68: =SUM(F68:H68) -> 0 | M68: =SUM(J68:L68) -> 0 | Q68: =SUM(N68:P68) -> 0 | U68: =SUM(R68:T68) -> 0 | V68: =I68+M68+Q68+U68 -> 0
C69: 마케팅 | E69: 0 | F69: 15000 | G69: 1000000 | H69: 1000000 | I69: =SUM(F69:H69) -> 2015000 | J69: 1000000 | K69: 1000000 | L69: 1000000 | M69: =SUM(J69:L69) -> 3000000 | N69: 1000000 | O69: 1000000 | P69: 1000000 | Q69: =SUM(N69:P69) -> 3000000 | R69: 1000000 | S69: 1000000 | T69: 1000000 | U69: =SUM(R69:T69) -> 3000000 | V69: =I69+M69+Q69+U69 -> 11015000
C70: 기타 | E70: 0 | I70: =SUM(F70:H70) -> 0 | M70: =SUM(J70:L70) -> 0 | Q70: =SUM(N70:P70) -> 0 | U70: =SUM(R70:T70) -> 0 | V70: =I70+M70+Q70+U70 -> 0
B71: Total Product Marketing | F71: =SUM(F68:F70) -> 15000 | G71: =SUM(G68:G70) -> 1000000 | H71: =SUM(H68:H70) -> 1000000 | I71: =SUM(I68:I70) -> 2015000 | J71: =SUM(J68:J70) -> 1000000 | K71: =SUM(K68:K70) -> 1000000 | L71: =SUM(L68:L70) -> 1000000 | M71: =SUM(M68:M70) -> 3000000 | ... U71: =SUM(U68:U70) -> 3000000 | V71: =I71+M71+Q71+U71 -> 11015000
B72: Sales Activities
C73: 고객교육훈련비 | E73: 0 | I73: =SUM(F73:H73) -> 0 | M73: =SUM(J73:L73) -> 0 | Q73: =SUM(N73:P73) -> 0 | U73: =SUM(R73:T73) -> 0 | V73: =I73+M73+Q73+U73 -> 0
C74: Sales Promotions | E74: 0 | I74: =SUM(F74:H74) -> 0 | M74: =SUM(J74:L74) -> 0 | Q74: =SUM(N74:P74) -> 0 | U74: =SUM(R74:T74) -> 0 | V74: =I74+M74+Q74+U74 -> 0
C75: Other Sales Activities | E75: 0 | I75: =SUM(F75:H75) -> 0 | M75: =SUM(J75:L75) -> 0 | Q75: =SUM(N75:P75) -> 0 | U75: =SUM(R75:T75) -> 0 | V75: =I75+M75+Q75+U75 -> 0
B76: Total Sales Activities | F76: =SUM(F73:F75) -> 0 | G76: =SUM(G73:G75) -> 0 | H76: =SUM(H73:H75) -> 0 | I76: =SUM(I73:I75) -> 0 | J76: =SUM(J73:J75) -> 0 | K76: =SUM(K73:K75) -> 0 | L76: =SUM(L73:L75) -> 0 | M76: =SUM(M73:M75) -> 0 | ... U76: =SUM(U73:U75) -> 0 | V76: =I76+M76+Q76+U76 -> 0
D77: TOTAL CONTROLLABLE EXP. | F77: =F52+F53+F66+F71+F76 -> 15068000 | G77: =G52+G53+G66+G71+G76 -> 16053000 | H77: =H52+H53+H66+H71+H76 -> 16053000 | I77: =I76+I71+I66+I53+I52 -> 47174000 | J77: =J52+J53+J66+J71+J76 -> 16053000 | K77: =K52+K53+K66+K71+K76 -> 16053000 | L77: =L52+L53+L66+L71+L76 -> 16053000 | M77: =M76+M71+M66+M53+M52 -> 48159000 | N77: =N52+N53+N66+N71+N76 -> 16053000 | O77: =O52+O53+O66+O71+O76 -> 16053000 | P77: =P52+P53+P66+P71+P76 -> 16053000 | Q77: =Q76+Q71+Q66+Q53+Q52 -> 48159000 | R77: =R52+R53+R66+R71+R76 -> 16053000 | S77: =S52+S53+S66+S71+S76 -> 16053000 | T77: =T52+T53+T66+T71+T76 -> 16053000 | U77: =U76+U71+U66+U53+U52 -> 48159000 | V77: =I77+M77+Q77+U77 -> 191651000
A78: FIXED EXPENSE
B79: Facility & Equipment
C80: 사무실-임차료 | E80: 0 | I80: =SUM(F80:H80) -> 0 | M80: =SUM(J80:L80) -> 0 | Q80: =SUM(N80:P80) -> 0 | U80: =SUM(R80:T80) -> 0 | V80: =I80+M80+Q80+U80 -> 0
C81: 사무실-관리비 | E81: 0 | I81: =SUM(F81:H81) -> 0 | M81: =SUM(J81:L81) -> 0 | Q81: =SUM(N81:P81) -> 0 | U81: =SUM(R81:T81) -> 0 | V81: =I81+M81+Q81+U81 -> 0
C82: 비품 감가상각 | E82: 0 | I82: =SUM(F82:H82) -> 0 | M82: =SUM(J82:L82) -> 0 | Q82: =SUM(N82:P82) -> 0 | U82: =SUM(R82:T82) -> 0 | V82: =I82+M82+Q82+U82 -> 0
C83: 시설물 감가상각 | I83: =SUM(F83:H83) -> 0 | M83: =SUM(J83:L83) -> 0 | Q83: =SUM(N83:P83) -> 0 | U83: =SUM(R83:T83) -> 0 | V83: =I83+M83+Q83+U83 -> 0
C84: 기계설비 임차료 | I84: =SUM(F84:H84) -> 0 | M84: =SUM(J84:L84) -> 0 | Q84: =SUM(N84:P84) -> 0 | U84: =SUM(R84:T84) -> 0 | V84: =I84+M84+Q84+U84 -> 0
C85: 전화요금 | E85: 0 | I85: =SUM(F85:H85) -> 0 | M85: =SUM(J85:L85) -> 0 | Q85: =SUM(N85:P85) -> 0 | U85: =SUM(R85:T85) -> 0 | V85: =I85+M85+Q85+U85 -> 0
C86: 사무실관리비 | E86: 0 | I86: =SUM(F86:H86) -> 0 | M86: =SUM(J86:L86) -> 0 | Q86: =SUM(N86:P86) -> 0 | U86: =SUM(R86:T86) -> 0 | V86: =I86+M86+Q86+U86 -> 0
C87: 기타_프로그램임차 | E87: 0 | I87: =SUM(F87:H87) -> 0 | M87: =SUM(J87:L87) -> 0 | Q87: =SUM(N87:P87) -> 0 | U87: =SUM(R87:T87) -> 0 | V87: =I87+M87+Q87+U87 -> 0
B88: Total Facility Expense | F88: =SUM(F80:F87) -> 0 | G88: =SUM(G80:G87) -> 0 | H88: =SUM(H80:H87) -> 0 | I88: =SUM(I80:I87) -> 0 | J88: =SUM(J80:J87) -> 0 | K88: =SUM(K80:K87) -> 0 | L88: =SUM(L80:L87) -> 0 | M88: =SUM(M80:M87) -> 0 | ... U88: =SUM(U80:U87) -> 0 | V88: =I88+M88+Q88+U88 -> 0
B89: Total Software License for Internal Use | E89: 0 | F89: 0 | G89: 0 | H89: 0 | I89: =SUM(I81:I88) -> 0 | J89: 0 | K89: 0 | L89: 0 | M89: =SUM(M81:M88) -> 0 | N89: 0 | O89: 0 | P89: 0 | Q89: =SUM(Q81:Q88) -> 0 | R89: 0 | S89: 0 | T89: 0 | U89: =SUM(U81:U88) -> 0 | V89: =I89+M89+Q89+U89 -> 0
B90: Office Expense | I90: =SUM(F90:H90) -> 0 | M90: =SUM(J90:L90) -> 0 | Q90: =SUM(N90:P90) -> 0 | U90: =SUM(R90:T90) -> 0 | V90: =I90+M90+Q90+U90 -> 0
C91: 도서인쇄비 | E91: 0 | I91: =SUM(F91:H91) -> 0 | M91: =SUM(J91:L91) -> 0 | Q91: =SUM(N91:P91) -> 0 | U91: =SUM(R91:T91) -> 0 | V91: =I91+M91+Q91+U91 -> 0
C92: 사무용품비 | E92: 0 | F92: 82000 | I92: =SUM(F92:H92) -> 82000 | M92: =SUM(J92:L92) -> 0 | Q92: =SUM(N92:P92) -> 0 | U92: =SUM(R92:T92) -> 0 | V92: =I92+M92+Q92+U92 -> 82000
C93: 소모품비 | E93: 0 | I93: =SUM(F93:H93) -> 0 | M93: =SUM(J93:L93) -> 0 | Q93: =SUM(N93:P93) -> 0 | U93: =SUM(R93:T93) -> 0 | V93: =I93+M93+Q93+U93 -> 0
C94: 우편료 | E94: 0 | I94: =SUM(F94:H94) -> 0 | M94: =SUM(J94:L94) -> 0 | Q94: =SUM(N94:P94) -> 0 | U94: =SUM(R94:T94) -> 0 | V94: =I94+M94+Q94+U94 -> 0
C95: 운반비 | E95: 0 | F95: 14000 | I95: =SUM(F95:H95) -> 14000 | M95: =SUM(J95:L95) -> 0 | Q95: =SUM(N95:P95) -> 0 | U95: =SUM(R95:T95) -> 0 | V95: =I95+M95+Q95+U95 -> 14000
C96: 수선비 | E96: 0 | I96: =SUM(F96:H96) -> 0 | M96: =SUM(J96:L96) -> 0 | Q96: =SUM(N96:P96) -> 0 | U96: =SUM(R96:T96) -> 0 | V96: =I96+M96+Q96+U96 -> 0
B97: Total Office Expense | F97: =SUM(F91:F96) -> 96000 | G97: =SUM(G91:G96) -> 0 | H97: =SUM(H91:H96) -> 0 | I97: =SUM(I91:I96) -> 96000 | J97: =SUM(J91:J96) -> 0 | K97: =SUM(K91:K96) -> 0 | L97: =SUM(L91:L96) -> 0 | M97: =SUM(M91:M96) -> 0 | ... U97: =SUM(U91:U96) -> 0 | V97: =I97+M97+Q97+U97 -> 96000
B98: Business Expense
C99: 기술고문료 | E99: 0 | I99: =SUM(F99:H99) -> 0 | M99: =SUM(J99:L99) -> 0 | Q99: =SUM(N99:P99) -> 0 | U99: =SUM(R99:T99) -> 0 | V99: =I99+M99+Q99+U99 -> 0
C100: 세무감사료 | E100: 0 | I100: =SUM(F100:H100) -> 0 | M100: =SUM(J100:L100) -> 0 | Q100: =SUM(N100:P100) -> 0 | U100: =SUM(R100:T100) -> 0 | V100: =I100+M100+Q100+U100 -> 0
C101: 홈페이지관리외 | E101: 0 | F101: 393000 | G101: 100000 | H101: 100000 | I101: =SUM(F101:H101) -> 593000 | J101: 100000 | K101: 100000 | L101: 100000 | M101: =SUM(J101:L101) -> 300000 | N101: 100000 | O101: 100000 | P101: 100000 | Q101: =SUM(N101:P101) -> 300000 | R101: 100000 | S101: 100000 | T101: 100000 | U101: =SUM(R101:T101) -> 300000 | V101: =I101+M101+Q101+U101 -> 1493000
C102: 보증보험 | E102: 0 | I102: =SUM(F102:H102) -> 0 | M102: =SUM(J102:L102) -> 0 | Q102: =SUM(N102:P102) -> 0 | U102: =SUM(R102:T102) -> 0 | V102: =I102+M102+Q102+U102 -> 0
C103: 보험료-차량+여행자 | E103: 0 | I103: =SUM(F103:H103) -> 0 | M103: =SUM(J103:L103) -> 0 | Q103: =SUM(N103:P103) -> 0 | U103: =SUM(R103:T103) -> 0 | V103: =I103+M103+Q103+U103 -> 0
...

Sheet JGChoi
F1: 1월 | G1: 2월 | H1: 3월 | I1: Q1 | J1: 4월 | K1: 5월 | L1: 6월 | M1: Q2 | N1: 7월 | O1: 8월 | P1: 9월 | Q1: Q3 | R1: 10월 | S1: 11월 | T1: 12월 | U1: Q4 | V1: 2026
F2: Actual | G2: Actual | H2: Actual | I2: Total | J2: Actual | K2: Actual | L2: Actual | M2: Total | N2: Actual | O2: Actual | P2: Actual | Q2: Total | R2: Actual | S2: Actual | T2: Actual | U2: Total | V2: Total
A3: 매 출
B4: Solution Business
D5: Lease | E5: 1 | I5: =H5+G5+F5 -> 0 | M5: =L5+K5+J5 -> 0 | Q5: =P5+O5+N5 -> 0 | U5: =T5+S5+R5 -> 0 | V5: =U5+Q5+M5+I5 -> 0
D6: E&S | E6: 1 | I6: =H6+G6+F6 -> 0 | M6: =L6+K6+J6 -> 0 | Q6: =P6+O6+N6 -> 0 | U6: =T6+S6+R6 -> 0 | V6: =U6+Q6+M6+I6 -> 0
D7: Paid-up | E7: 1 | I7: =H7+G7+F7 -> 0 | M7: =L7+K7+J7 -> 0 | Q7: =P7+O7+N7 -> 0 | U7: =T7+S7+R7 -> 0 | V7: =U7+Q7+M7+I7 -> 0
D8: 기타_HW Transfer | I8: =H8+G8+F8 -> 0 | M8: =L8+K8+J8 -> 0 | Q8: =P8+O8+N8 -> 0 | U8: =T8+S8+R8 -> 0 | V8: =U8+Q8+M8+I8 -> 0
D9: Service | I9: =H9+G9+F9 -> 0 | M9: =L9+K9+J9 -> 0 | Q9: =P9+O9+N9 -> 0 | U9: =T9+S9+R9 -> 0 | V9: =U9+Q9+M9+I9 -> 0
D10: Seminar/Training | I10: =H10+G10+F10 -> 0 | M10: =L10+K10+J10 -> 0 | Q10: =P10+O10+N10 -> 0 | U10: =T10+S10+R10 -> 0 | V10: =U10+Q10+M10+I10 -> 0
A12: 매 출 합 계 | F12: =SUM(F5:F10) -> 0 | G12: =SUM(G5:G10) -> 0 | H12: =SUM(H5:H10) -> 0 | I12: =SUM(I5:I10) -> 0 | J12: =SUM(J5:J10) -> 0 | K12: =SUM(K5:K10) -> 0 | L12: =SUM(L5:L10) -> 0 | M12: =SUM(M5:M10) -> 0 | ... V12: =SUM(V5:V10) -> 0
A14: 매 출 원 가
C15: Royalty
D16: MSC Software | E16: 0 | I16: =H16+G16+F16 -> 0 | M16: =L16+K16+J16 -> 0 | Q16: =P16+O16+N16 -> 0 | U16: =T16+S16+R16 -> 0 | V16: =U16+Q16+M16+I16 -> 0
D17: SVD Software | I17: =H17+G17+F17 -> 0 | M17: =L17+K17+J17 -> 0 | Q17: =P17+O17+N17 -> 0 | U17: =T17+S17+R17 -> 0 | V17: =U17+Q17+M17+I17 -> 0
D18: TechSoft3D | I18: =H18+G18+F18 -> 0 | M18: =L18+K18+J18 -> 0 | Q18: =P18+O18+N18 -> 0 | U18: =T18+S18+R18 -> 0 | V18: =U18+Q18+M18+I18 -> 0
D19: TSV+KTM+그외 | I19: =H19+G19+F19 -> 0 | M19: =L19+K19+J19 -> 0 | Q19: =P19+O19+N19 -> 0 | U19: =T19+S19+R19 -> 0 | V19: =U19+Q19+M19+I19 -> 0
D20: 기타_System | E20: 0 | I20: =H20+G20+F20 -> 0 | M20: =L20+K20+J20 -> 0 | Q20: =P20+O20+N20 -> 0 | U20: =T20+S20+R20 -> 0 | V20: =U20+Q20+M20+I20 -> 0
C21: Outside Consultant | I21: =H21+G21+F21 -> 0 | M21: =L21+K21+J21 -> 0 | Q21: =P21+O21+N21 -> 0 | U21: =T21+S21+R21 -> 0 | V21: =U21+Q21+M21+I21 -> 0
C22: Finder commission | I22: =H22+G22+F22 -> 0 | M22: =L22+K22+J22 -> 0 | Q22: =P22+O22+N22 -> 0 | U22: =T22+S22+R22 -> 0 | V22: =U22+Q22+M22+I22 -> 0
C23: S/W+H/W 감가상각 | I23: =H23+G23+F23 -> 0 | M23: =L23+K23+J23 -> 0 | Q23: =P23+O23+N23 -> 0 | U23: =T23+S23+R23 -> 0 | V23: =U23+Q23+M23+I23 -> 0
C24: 지급수수료_기타+임차료 | I24: =H24+G24+F24 -> 0 | M24: =L24+K24+J24 -> 0 | Q24: =P24+O24+N24 -> 0 | U24: =T24+S24+R24 -> 0 | V24: =U24+Q24+M24+I24 -> 0
C25: 보증보험+세금과공과 | E25: 0 | I25: =H25+G25+F25 -> 0 | M25: =L25+K25+J25 -> 0 | Q25: =P25+O25+N25 -> 0 | U25: =T25+S25+R25 -> 0 | V25: =U25+Q25+M25+I25 -> 0
A26: 매 출 원 가 합 계 | F26: =SUM(F16:F25) -> 0 | G26: =SUM(G16:G25) -> 0 | H26: =SUM(H16:H25) -> 0 | I26: =SUM(I16:I25) -> 0 | J26: =SUM(J16:J25) -> 0 | K26: =SUM(K16:K25) -> 0 | L26: =SUM(L16:L25) -> 0 | M26: =SUM(M16:M25) -> 0 | ... V26: =SUM(V16:V25) -> 0
A28: 매 출 이 익 (%)
C29: 총 매출이익 | F29: =F12-F26 -> 0 | G29: =G12-G26 -> 0 | H29: =H12-H26 -> 0 | I29: =I12-I26 -> 0 | J29: =J12-J26 -> 0 | K29: =K12-K26 -> 0 | L29: =L12-L26 -> 0 | M29: =M12-M26 -> 0 | ... V29: =V12-V26 -> 0
D30: 총매출이익률 | F30: =IF(F12=0,0,F29/F12) -> 0 | G30: =IF(G12=0,0,G29/G12) -> 0 | H30: =IF(H12=0,0,H29/H12) -> 0 | I30: =IF(I12=0,0,I29/I12) -> 0 | J30: =IF(J12=0,0,J29/J12) -> 0 | K30: =IF(K12=0,0,K29/K12) -> 0 | L30: =IF(L12=0,0,L29/L12) -> 0 | M30: =IF(M12=0,0,M29/M12) -> 0 | ... V30: =IF(V12=0,0,V29/V12) -> 0
A31: CONTROLLABLE EXPENSE
C32: Salary & Wages
D33: 직원급여 | E33: 0 | F33: 10000000 | G33: 10000000 | H33: 10000000 | I33: =SUM(F33:H33) -> 30000000 | J33: 10000000 | K33: 10000000 | L33: 10000000 | M33: =SUM(J33:L33) -> 30000000 | N33: 10000000 | O33: 10000000 | P33: 10000000 | Q33: =SUM(N33:P33) -> 30000000 | R33: 10000000 | S33: 10000000 | T33: 10000000 | U33: =SUM(R33:T33) -> 30000000 | V33: =I33+M33+Q33+U33 -> 120000000
D34: 특별상여 | F34: 0 | G34: 0 | H34: 0 | I34: =SUM(F34:H34) -> 0 | J34: 0 | K34: 0 | L34: 0 | M34: =SUM(J34:L34) -> 0 | N34: 0 | O34: 0 | P34: 0 | Q34: =SUM(N34:P34) -> 0 | R34: 0 | S34: 0 | T34: 0 | U34: =SUM(R34:T34) -> 0 | V34: =I34+M34+Q34+U34 -> 0
D35: 기타-연차 | E35: 0 | I35: =SUM(F35:H35) -> 0 | M35: =SUM(J35:L35) -> 0 | Q35: =SUM(N35:P35) -> 0 | U35: =SUM(R35:T35) -> 0 | V35: =I35+M35+Q35+U35 -> 0
D36: 퇴직급여 | E36: 0 | F36: 1000000 | G36: 1000000 | H36: 1000000 | I36: =SUM(F36:H36) -> 3000000 | J36: 1000000 | K36: 1000000 | L36: 1000000 | M36: =SUM(J36:L36) -> 3000000 | N36: 1000000 | O36: 1000000 | P36: 1000000 | Q36: =SUM(N36:P36) -> 3000000 | R36: 1000000 | S36: 1000000 | T36: 1000000 | U36: =SUM(R36:T36) -> 3000000 | V36: =I36+M36+Q36+U36 -> 12000000
B37: Total Salary & Wages | F37: =SUM(F33:F36) -> 11000000 | G37: =SUM(G33:G36) -> 11000000 | H37: =SUM(H33:H36) -> 11000000 | I37: =SUM(I33:I36) -> 33000000 | J37: =SUM(J33:J36) -> 11000000 | K37: =SUM(K33:K36) -> 11000000 | L37: =SUM(L33:L36) -> 11000000 | M37: =SUM(M33:M36) -> 33000000 | ... U37: =SUM(U33:U36) -> 33000000 | V37: =I37+M37+Q37+U37 -> 132000000
C38: Benefits
D39: 국민연금 | E39: 0 | F39: 300000 | G39: 300000 | H39: 300000 | I39: =SUM(F39:H39) -> 900000 | J39: 300000 | K39: 300000 | L39: 300000 | M39: =SUM(J39:L39) -> 900000 | N39: 300000 | O39: 300000 | P39: 300000 | Q39: =SUM(N39:P39) -> 900000 | R39: 300000 | S39: 300000 | T39: 300000 | U39: =SUM(R39:T39) -> 900000 | V39: =I39+M39+Q39+U39 -> 3600000
D40: 건강보험 | E40: 0 | F40: 300000 | G40: 300000 | H40: 300000 | I40: =SUM(F40:H40) -> 900000 | J40: 300000 | K40: 300000 | L40: 300000 | M40: =SUM(J40:L40) -> 900000 | N40: 300000 | O40: 300000 | P40: 300000 | Q40: =SUM(N40:P40) -> 900000 | R40: 300000 | S40: 300000 | T40: 300000 | U40: =SUM(R40:T40) -> 900000 | V40: =I40+M40+Q40+U40 -> 3600000
D41: 고용보험 | E41: 0 | F41: 100000 | G41: 100000 | H41: 100000 | I41: =SUM(F41:H41) -> 300000 | J41: 100000 | K41: 100000 | L41: 100000 | M41: =SUM(J41:L41) -> 300000 | N41: 100000 | O41: 100000 | P41: 100000 | Q41: =SUM(N41:P41) -> 300000 | R41: 100000 | S41: 100000 | T41: 100000 | U41: =SUM(R41:T41) -> 300000 | V41: =I41+M41+Q41+U41 -> 1200000
D42: 산재보험 | E42: 0 | F42: 54000 | G42: 54000 | H42: 54000 | I42: =SUM(F42:H42) -> 162000 | J42: 54000 | K42: 54000 | L42: 54000 | M42: =SUM(J42:L42) -> 162000 | N42: 54000 | O42: 54000 | P42: 54000 | Q42: =SUM(N42:P42) -> 162000 | R42: 54000 | S42: 54000 | T42: 54000 | U42: =SUM(R42:T42) -> 162000 | V42: =I42+M42+Q42+U42 -> 648000
D43: 야근식대 | E43: 0 | F43: 39000 | G43: 39000 | H43: 39000 | I43: =SUM(F43:H43) -> 117000 | J43: 39000 | K43: 39000 | L43: 39000 | M43: =SUM(J43:L43) -> 117000 | N43: 39000 | O43: 39000 | P43: 39000 | Q43: =SUM(N43:P43) -> 117000 | R43: 39000 | S43: 39000 | T43: 39000 | U43: =SUM(R43:T43) -> 117000 | V43: =I43+M43+Q43+U43 -> 468000
D44: 회식대 | G44: 100000 | H44: 100000 | I44: =SUM(F44:H44) -> 200000 | J44: 100000 | K44: 100000 | L44: 100000 | M44: =SUM(J44:L44) -> 300000 | N44: 100000 | O44: 100000 | P44: 100000 | Q44: =SUM(N44:P44) -> 300000 | R44: 100000 | S44: 100000 | T44: 100000 | U44: =SUM(R44:T44) -> 300000 | V44: =I44+M44+Q44+U44 -> 1100000
D45: 경조사 | E45: 0 | I45: =SUM(F45:H45) -> 0 | M45: =SUM(J45:L45) -> 0 | Q45: =SUM(N45:P45) -> 0 | U45: =SUM(R45:T45) -> 0 | V45: =I45+M45+Q45+U45 -> 0
D46: 교육지원비 | E46: 0 | I46: =SUM(F46:H46) -> 0 | M46: =SUM(J46:L46) -> 0 | Q46: =SUM(N46:P46) -> 0 | U46: =SUM(R46:T46) -> 0 | V46: =I46+M46+Q46+U46 -> 0
D47: 직원상해보험 | E47: 0 | I47: =SUM(F47:H47) -> 0 | M47: =SUM(J47:L47) -> 0 | Q47: =SUM(N47:P47) -> 0 | U47: =SUM(R47:T47) -> 0 | V47: =I47+M47+Q47+U47 -> 0
D48: 건강검진 | E48: 0 | I48: =SUM(F48:H48) -> 0 | M48: =SUM(J48:L48) -> 0 | Q48: =SUM(N48:P48) -> 0 | U48: =SUM(R48:T48) -> 0 | V48: =I48+M48+Q48+U48 -> 0
D49: 통신비(핸드폰) | F49: 65000 | G49: 65000 | H49: 65000 | I49: =SUM(F49:H49) -> 195000 | J49: 65000 | K49: 65000 | L49: 65000 | M49: =SUM(J49:L49) -> 195000 | N49: 65000 | O49: 65000 | P49: 65000 | Q49: =SUM(N49:P49) -> 195000 | R49: 65000 | S49: 65000 | T49: 65000 | U49: =SUM(R49:T49) -> 195000 | V49: =I49+M49+Q49+U49 -> 780000
D50: 체력단련비 | F50: 60000 | G50: 60000 | H50: 60000 | I50: =SUM(F50:H50) -> 180000 | J50: 60000 | K50: 60000 | L50: 60000 | M50: =SUM(J50:L50) -> 180000 | N50: 60000 | O50: 60000 | P50: 60000 | Q50: =SUM(N50:P50) -> 180000 | R50: 60000 | S50: 60000 | T50: 60000 | U50: =SUM(R50:T50) -> 180000 | V50: =I50+M50+Q50+U50 -> 720000
B51: Total Benefits | F51: =SUM(F39:F50) -> 918000 | G51: =SUM(G39:G50) -> 1018000 | H51: =SUM(H39:H50) -> 1018000 | I51: =SUM(I39:I50) -> 2954000 | J51: =SUM(J39:J50) -> 1018000 | K51: =SUM(K39:K50) -> 1018000 | L51: =SUM(L39:L50) -> 1018000 | M51: =SUM(M39:M50) -> 3054000 | ... U51: =SUM(U39:U50) -> 3054000 | V51: =I51+M51+Q51+U51 -> 12116000
B52: Total Compensation & Benefits | F52: =F37+F51 -> 11918000 | G52: =G37+G51 -> 12018000 | H52: =H37+H51 -> 12018000 | I52: =I51+I37 -> 35954000 | J52: =J37+J51 -> 12018000 | K52: =K37+K51 -> 12018000 | L52: =L37+L51 -> 12018000 | M52: =M51+M37 -> 36054000 | N52: =N37+N51 -> 12018000 | O52: =O37+O51 -> 12018000 | P52: =P37+P51 -> 12018000 | Q52: =Q51+Q37 -> 36054000 | R52: =R37+R51 -> 12018000 | S52: =S37+S51 -> 12018000 | T52: =T37+T51 -> 12018000 | U52: =U51+U37 -> 36054000 | V52: =I52+M52+Q52+U52 -> 144116000
B53: Unfunded Consulting Expenses | E53: 0 | F53: 0 | G53: 0 | H53: 0 | I53: 0 | J53: 0 | K53: 0 | L53: 0 | M53: 0 | N53: 0 | O53: 0 | P53: 0 | Q53: 0 | R53: 0 | S53: 0 | T53: 0 | U53: 0 | V53: =I53+M53+Q53+U53 -> 0
B54: Travel & Entertainment
C55: 여비교통비(출장일비) | E55: 0 | I55: =SUM(F55:H55) -> 0 | M55: =SUM(J55:L55) -> 0 | Q55: =SUM(N55:P55) -> 0 | U55: =SUM(R55:T55) -> 0 | V55: =I55+M55+Q55+U55 -> 0
C56: 여비교통비(출장식대) | F56: 44000 | G56: 44000 | H56: 44000 | I56: =SUM(F56:H56) -> 132000 | J56: 44000 | K56: 44000 | L56: 44000 | M56: =SUM(J56:L56) -> 132000 | N56: 44000 | O56: 44000 | P56: 44000 | Q56: =SUM(N56:P56) -> 132000 | R56: 44000 | S56: 44000 | T56: 44000 | U56: =SUM(R56:T56) -> 132000 | V56: =I56+M56+Q56+U56 -> 528000
C57: 여비교통비(통행,주차) | F57: 28000 | G57: 28000 | H57: 28000 | I57: =SUM(F57:H57) -> 84000 | J57: 28000 | K57: 28000 | L57: 28000 | M57: =SUM(J57:L57) -> 84000 | N57: 28000 | O57: 28000 | P57: 28000 | Q57: =SUM(N57:P57) -> 84000 | R57: 28000 | S57: 28000 | T57: 28000 | U57: =SUM(R57:T57) -> 84000 | V57: =I57+M57+Q57+U57 -> 336000
C58: 여비교통비(항공,고속버스등) | F58: 252000 | G58: 252000 | H58: 252000 | I58: =SUM(F58:H58) -> 756000 | J58: 252000 | K58: 252000 | L58: 252000 | M58: =SUM(J58:L58) -> 756000 | N58: 252000 | O58: 252000 | P58: 252000 | Q58: =SUM(N58:P58) -> 756000 | R58: 252000 | S58: 252000 | T58: 252000 | U58: =SUM(R58:T58) -> 756000 | V58: =I58+M58+Q58+U58 -> 3024000
C59: 여비교통비(숙박) | F59: 170000 | G59: 170000 | H59: 170000 | I59: =SUM(F59:H59) -> 510000 | J59: 170000 | K59: 170000 | L59: 170000 | M59: =SUM(J59:L59) -> 510000 | N59: 170000 | O59: 170000 | P59: 170000 | Q59: =SUM(N59:P59) -> 510000 | R59: 170000 | S59: 170000 | T59: 170000 | U59: =SUM(R59:T59) -> 510000 | V59: =I59+M59+Q59+U59 -> 2040000
C60: 여비교통비(차량지원) | F60: 248000 | G60: 248000 | H60: 248000 | I60: =SUM(F60:H60) -> 744000 | J60: 248000 | K60: 248000 | L60: 248000 | M60: =SUM(J60:L60) -> 744000 | N60: 248000 | O60: 248000 | P60: 248000 | Q60: =SUM(N60:P60) -> 744000 | R60: 248000 | S60: 248000 | T60: 248000 | U60: =SUM(R60:T60) -> 744000 | V60: =I60+M60+Q60+U60 -> 2976000
C61: 여비교통비(국책과제_연구활동비) | I61: =SUM(F61:H61) -> 0 | M61: =SUM(J61:L61) -> 0 | Q61: =SUM(N61:P61) -> 0 | U61: =SUM(R61:T61) -> 0 | V61: =I61+M61+Q61+U61 -> 0
C62: 차량유지비 | E62: 0 | I62: =SUM(F62:H62) -> 0 | M62: =SUM(J62:L62) -> 0 | Q62: =SUM(N62:P62) -> 0 | U62: =SUM(R62:T62) -> 0 | V62: =I62+M62+Q62+U62 -> 0
C63: 해외출장비 | E63: 0 | I63: =SUM(F63:H63) -> 0 | M63: =SUM(J63:L63) -> 0 | Q63: =SUM(N63:P63) -> 0 | U63: =SUM(R63:T63) -> 0 | V63: =I63+M63+Q63+U63 -> 0
C64: 회의비 | E64: 0 | F64: 38000 | G64: 30000 | H64: 30000 | I64: =SUM(F64:H64) -> 98000 | J64: 30000 | K64: 30000 | L64: 30000 | M64: =SUM(J64:L64) -> 90000 | N64: 30000 | O64: 30000 | P64: 30000 | Q64: =SUM(N64:P64) -> 90000 | R64: 30000 | S64: 30000 | T64: 30000 | U64: =SUM(R64:T64) -> 90000 | V64: =I64+M64+Q64+U64 -> 368000
C65: 접대비 | E65: 0 | F65: 122000 | G65: 100000 | H65: 100000 | I65: =SUM(F65:H65) -> 322000 | J65: 100000 | K65: 100000 | L65: 100000 | M65: =SUM(J65:L65) -> 300000 | N65: 100000 | O65: 100000 | P65: 100000 | Q65: =SUM(N65:P65) -> 300000 | R65: 100000 | S65: 100000 | T65: 100000 | U65: =SUM(R65:T65) -> 300000 | V65: =I65+M65+Q65+U65 -> 1222000
B66: Total Travel & Entertainment | F66: =SUM(F55:F65) -> 902000 | G66: =SUM(G55:G65) -> 872000 | H66: =SUM(H55:H65) -> 872000 | I66: =SUM(I55:I65) -> 2646000 | J66: =SUM(J55:J65) -> 872000 | K66: =SUM(K55:K65) -> 872000 | L66: =SUM(L55:L65) -> 872000 | M66: =SUM(M55:M65) -> 2616000 | ... U66: =SUM(U55:U65) -> 2616000 | V66: =I66+M66+Q66+U66 -> 10494000
B67: Product Marketing
C68: 행사비 | E68: 0 | F68: 0 | I68: =SUM(F68:H68) -> 0 | M68: =SUM(J68:L68) -> 0 | Q68: =SUM(N68:P68) -> 0 | U68: =SUM(R68:T68) -> 0 | V68: =I68+M68+Q68+U68 -> 0
C69: 마케팅 | E69: 0 | F69: 0 | I69: =SUM(F69:H69) -> 0 | M69: =SUM(J69:L69) -> 0 | Q69: =SUM(N69:P69) -> 0 | U69: =SUM(R69:T69) -> 0 | V69: =I69+M69+Q69+U69 -> 0
C70: 기타 | E70: 0 | I70: =SUM(F70:H70) -> 0 | M70: =SUM(J70:L70) -> 0 | Q70: =SUM(N70:P70) -> 0 | U70: =SUM(R70:T70) -> 0 | V70: =I70+M70+Q70+U70 -> 0
B71: Total Product Marketing | F71: =SUM(F68:F70) -> 0 | G71: =SUM(G68:G70) -> 0 | H71: =SUM(H68:H70) -> 0 | I71: =SUM(I68:I70) -> 0 | J71: =SUM(J68:J70) -> 0 | K71: =SUM(K68:K70) -> 0 | L71: =SUM(L68:L70) -> 0 | M71: =SUM(M68:M70) -> 0 | ... U71: =SUM(U68:U70) -> 0 | V71: =I71+M71+Q71+U71 -> 0
B72: Sales Activities
C73: 고객교육훈련비 | E73: 0 | I73: =SUM(F73:H73) -> 0 | M73: =SUM(J73:L73) -> 0 | Q73: =SUM(N73:P73) -> 0 | U73: =SUM(R73:T73) -> 0 | V73: =I73+M73+Q73+U73 -> 0
C74: Sales Promotions | E74: 0 | I74: =SUM(F74:H74) -> 0 | M74: =SUM(J74:L74) -> 0 | Q74: =SUM(N74:P74) -> 0 | U74: =SUM(R74:T74) -> 0 | V74: =I74+M74+Q74+U74 -> 0
C75: Other Sales Activities | E75: 0 | I75: =SUM(F75:H75) -> 0 | M75: =SUM(J75:L75) -> 0 | Q75: =SUM(N75:P75) -> 0 | U75: =SUM(R75:T75) -> 0 | V75: =I75+M75+Q75+U75 -> 0
B76: Total Sales Activities | F76: =SUM(F73:F75) -> 0 | G76: =SUM(G73:G75) -> 0 | H76: =SUM(H73:H75) -> 0 | I76: =SUM(I73:I75) -> 0 | J76: =SUM(J73:J75) -> 0 | K76: =SUM(K73:K75) -> 0 | L76: =SUM(L73:L75) -> 0 | M76: =SUM(M73:M75) -> 0 | ... U76: =SUM(U73:U75) -> 0 | V76: =I76+M76+Q76+U76 -> 0
D77: TOTAL CONTROLLABLE EXP. | F77: =F52+F53+F66+F71+F76 -> 12820000 | G77: =G52+G53+G66+G71+G76 -> 12890000 | H77: =H52+H53+H66+H71+H76 -> 12890000 | I77: =I76+I71+I66+I53+I52 -> 38600000 | J77: =J52+J53+J66+J71+J76 -> 12890000 | K77: =K52+K53+K66+K71+K76 -> 12890000 | L77: =L52+L53+L66+L71+L76 -> 12890000 | M77: =M76+M71+M66+M53+M52 -> 38670000 | N77: =N52+N53+N66+N71+N76 -> 12890000 | O77: =O52+O53+O66+O71+O76 -> 12890000 | P77: =P52+P53+P66+P71+P76 -> 12890000 | Q77: =Q76+Q71+Q66+Q53+Q52 -> 38670000 | R77: =R52+R53+R66+R71+R76 -> 12890000 | S77: =S52+S53+S66+S71+S76 -> 12890000 | T77: =T52+T53+T66+T71+T76 -> 12890000 | U77: =U76+U71+U66+U53+U52 -> 38670000 | V77: =I77+M77+Q77+U77 -> 154610000
A78: FIXED EXPENSE
B79: Facility & Equipment
C80: 사무실-임차료 | E80: 0 | F80: 0 | I80: =SUM(F80:H80) -> 0 | M80: =SUM(J80:L80) -> 0 | Q80: =SUM(N80:P80) -> 0 | U80: =SUM(R80:T80) -> 0 | V80: =I80+M80+Q80+U80 -> 0
C81: 사무실-관리비 | E81: 0 | I81: =SUM(F81:H81) -> 0 | M81: =SUM(J81:L81) -> 0 | Q81: =SUM(N81:P81) -> 0 | U81: =SUM(R81:T81) -> 0 | V81: =I81+M81+Q81+U81 -> 0
C82: 비품 감가상각 | E82: 0 | I82: =SUM(F82:H82) -> 0 | M82: =SUM(J82:L82) -> 0 | Q82: =SUM(N82:P82) -> 0 | U82: =SUM(R82:T82) -> 0 | V82: =I82+M82+Q82+U82 -> 0
C83: 시설물 감가상각 | I83: =SUM(F83:H83) -> 0 | M83: =SUM(J83:L83) -> 0 | Q83: =SUM(N83:P83) -> 0 | U83: =SUM(R83:T83) -> 0 | V83: =I83+M83+Q83+U83 -> 0
C84: 기계설비 임차료 | I84: =SUM(F84:H84) -> 0 | M84: =SUM(J84:L84) -> 0 | Q84: =SUM(N84:P84) -> 0 | U84: =SUM(R84:T84) -> 0 | V84: =I84+M84+Q84+U84 -> 0
C85: 전화요금 | E85: 0 | I85: =SUM(F85:H85) -> 0 | M85: =SUM(J85:L85) -> 0 | Q85: =SUM(N85:P85) -> 0 | U85: =SUM(R85:T85) -> 0 | V85: =I85+M85+Q85+U85 -> 0
C86: 사무실관리비 | E86: 0 | I86: =SUM(F86:H86) -> 0 | M86: =SUM(J86:L86) -> 0 | Q86: =SUM(N86:P86) -> 0 | U86: =SUM(R86:T86) -> 0 | V86: =I86+M86+Q86+U86 -> 0
C87: 기타_프로그램임차 | E87: 0 | I87: =SUM(F87:H87) -> 0 | M87: =SUM(J87:L87) -> 0 | Q87: =SUM(N87:P87) -> 0 | U87: =SUM(R87:T87) -> 0 | V87: =I87+M87+Q87+U87 -> 0
B88: Total Facility Expense | F88: =SUM(F80:F87) -> 0 | G88: =SUM(G80:G87) -> 0 | H88: =SUM(H80:H87) -> 0 | I88: =SUM(I80:I87) -> 0 | J88: =SUM(J80:J87) -> 0 | K88: =SUM(K80:K87) -> 0 | L88: =SUM(L80:L87) -> 0 | M88: =SUM(M80:M87) -> 0 | ... U88: =SUM(U80:U87) -> 0 | V88: =I88+M88+Q88+U88 -> 0
B89: Total Software License for Internal Use | E89: 0 | F89: 0 | G89: 0 | H89: 0 | I89: =SUM(I81:I88) -> 0 | J89: 0 | K89: 0 | L89: 0 | M89: =SUM(M81:M88) -> 0 | N89: 0 | O89: 0 | P89: 0 | Q89: =SUM(Q81:Q88) -> 0 | R89: 0 | S89: 0 | T89: 0 | U89: 0 | V89: =I89+M89+Q89+U89 -> 0
B90: Office Expense | I90: =SUM(F90:H90) -> 0 | M90: =SUM(J90:L90) -> 0 | Q90: =SUM(N90:P90) -> 0 | U90: =SUM(R90:T90) -> 0 | V90: =I90+M90+Q90+U90 -> 0
C91: 도서인쇄비 | E91: 0 | I91: =SUM(F91:H91) -> 0 | M91: =SUM(J91:L91) -> 0 | Q91: =SUM(N91:P91) -> 0 | U91: =SUM(R91:T91) -> 0 | V91: =I91+M91+Q91+U91 -> 0
C92: 사무용품비 | E92: 0 | F92: 23000 | I92: =SUM(F92:H92) -> 23000 | M92: =SUM(J92:L92) -> 0 | Q92: =SUM(N92:P92) -> 0 | U92: =SUM(R92:T92) -> 0 | V92: =I92+M92+Q92+U92 -> 23000
C93: 소모품비 | E93: 0 | I93: =SUM(F93:H93) -> 0 | M93: =SUM(J93:L93) -> 0 | Q93: =SUM(N93:P93) -> 0 | U93: =SUM(R93:T93) -> 0 | V93: =I93+M93+Q93+U93 -> 0
C94: 우편료 | E94: 0 | I94: =SUM(F94:H94) -> 0 | M94: =SUM(J94:L94) -> 0 | Q94: =SUM(N94:P94) -> 0 | U94: =SUM(R94:T94) -> 0 | V94: =I94+M94+Q94+U94 -> 0
C95: 운반비 | E95: 0 | F95: 0 | I95: =SUM(F95:H95) -> 0 | M95: =SUM(J95:L95) -> 0 | Q95: =SUM(N95:P95) -> 0 | U95: =SUM(R95:T95) -> 0 | V95: =I95+M95+Q95+U95 -> 0
C96: 수선비 | E96: 0 | I96: =SUM(F96:H96) -> 0 | M96: =SUM(J96:L96) -> 0 | Q96: =SUM(N96:P96) -> 0 | U96: =SUM(R96:T96) -> 0 | V96: =I96+M96+Q96+U96 -> 0
B97: Total Office Expense | F97: =SUM(F91:F96) -> 23000 | G97: =SUM(G91:G96) -> 0 | H97: =SUM(H91:H96) -> 0 | I97: =SUM(I91:I96) -> 23000 | J97: =SUM(J91:J96) -> 0 | K97: =SUM(K91:K96) -> 0 | L97: =SUM(L91:L96) -> 0 | M97: =SUM(M91:M96) -> 0 | ... U97: =SUM(U91:U96) -> 0 | V97: =I97+M97+Q97+U97 -> 23000
B98: Business Expense
C99: 기술고문료 | E99: 0 | I99: =SUM(F99:H99) -> 0 | M99: =SUM(J99:L99) -> 0 | Q99: =SUM(N99:P99) -> 0 | U99: =SUM(R99:T99) -> 0 | V99: =I99+M99+Q99+U99 -> 0
C100: 세무감사료 | E100: 0 | I100: =SUM(F100:H100) -> 0 | M100: =SUM(J100:L100) -> 0 | Q100: =SUM(N100:P100) -> 0 | U100: =SUM(R100:T100) -> 0 | V100: =I100+M100+Q100+U100 -> 0
C101: 홈페이지관리외 | E101: 0 | F101: 0 | I101: =SUM(F101:H101) -> 0 | M101: =SUM(J101:L101) -> 0 | Q101: =SUM(N101:P101) -> 0 | U101: =SUM(R101:T101) -> 0 | V101: =I101+M101+Q101+U101 -> 0
C102: 보증보험 | E102: 0 | I102: =SUM(F102:H102) -> 0 | M102: =SUM(J102:L102) -> 0 | Q102: =SUM(N102:P102) -> 0 | U102: =SUM(R102:T102) -> 0 | V102: =I102+M102+Q102+U102 -> 0
C103: 보험료-차량+여행자 | E103: 0 | I103: =SUM(F103:H103) -> 0 | M103: =SUM(J103:L103) -> 0 | Q103: =SUM(N103:P103) -> 0 | U103: =SUM(R103:T103) -> 0 | V103: =I103+M103+Q103+U103 -> 0
...

Sheet SYShin
F1: 1월 | G1: 2월 | H1: 3월 | I1: Q1 | J1: 4월 | K1: 5월 | L1: 6월 | M1: Q2 | N1: 7월 | O1: 8월 | P1: 9월 | Q1: Q3 | R1: 10월 | S1: 11월 | T1: 12월 | U1: Q4 | V1: 2026
F2: Actual | G2: Actual | H2: Actual | I2: Total | J2: Actual | K2: Actual | L2: Actual | M2: Total | N2: Actual | O2: Actual | P2: Actual | Q2: Total | R2: Actual | S2: Actual | T2: Actual | U2: Total | V2: Total
A3: 매 출
B4: Solution Business
D5: Lease | E5: 1 | I5: =H5+G5+F5 -> 0 | M5: =L5+K5+J5 -> 0 | Q5: =P5+O5+N5 -> 0 | U5: =T5+S5+R5 -> 0 | V5: =U5+Q5+M5+I5 -> 0
D6: E&S | E6: 1 | I6: =H6+G6+F6 -> 0 | M6: =L6+K6+J6 -> 0 | Q6: =P6+O6+N6 -> 0 | U6: =T6+S6+R6 -> 0 | V6: =U6+Q6+M6+I6 -> 0
D7: Paid-up | E7: 1 | I7: =H7+G7+F7 -> 0 | M7: =L7+K7+J7 -> 0 | Q7: =P7+O7+N7 -> 0 | U7: =T7+S7+R7 -> 0 | V7: =U7+Q7+M7+I7 -> 0
D8: 기타_HW Transfer | I8: =H8+G8+F8 -> 0 | M8: =L8+K8+J8 -> 0 | Q8: =P8+O8+N8 -> 0 | U8: =T8+S8+R8 -> 0 | V8: =U8+Q8+M8+I8 -> 0
D9: Service | I9: =H9+G9+F9 -> 0 | M9: =L9+K9+J9 -> 0 | Q9: =P9+O9+N9 -> 0 | U9: =T9+S9+R9 -> 0 | V9: =U9+Q9+M9+I9 -> 0
D10: Seminar/Training | I10: =H10+G10+F10 -> 0 | M10: =L10+K10+J10 -> 0 | Q10: =P10+O10+N10 -> 0 | U10: =T10+S10+R10 -> 0 | V10: =U10+Q10+M10+I10 -> 0
A12: 매 출 합 계 | F12: =SUM(F5:F10) -> 0 | G12: =SUM(G5:G10) -> 0 | H12: =SUM(H5:H10) -> 0 | I12: =SUM(I5:I10) -> 0 | J12: =SUM(J5:J10) -> 0 | K12: =SUM(K5:K10) -> 0 | L12: =SUM(L5:L10) -> 0 | M12: =SUM(M5:M10) -> 0 | ... V12: =SUM(V5:V10) -> 0
A14: 매 출 원 가
C15: Royalty
D16: MSC Software | E16: 0 | I16: =H16+G16+F16 -> 0 | M16: =L16+K16+J16 -> 0 | Q16: =P16+O16+N16 -> 0 | U16: =T16+S16+R16 -> 0 | V16: =U16+Q16+M16+I16 -> 0
D17: SVD Software | I17: =H17+G17+F17 -> 0 | M17: =L17+K17+J17 -> 0 | Q17: =P17+O17+N17 -> 0 | U17: =T17+S17+R17 -> 0 | V17: =U17+Q17+M17+I17 -> 0
D18: TechSoft3D | I18: =H18+G18+F18 -> 0 | M18: =L18+K18+J18 -> 0 | Q18: =P18+O18+N18 -> 0 | U18: =T18+S18+R18 -> 0 | V18: =U18+Q18+M18+I18 -> 0
D19: TSV+KTM+그외 | I19: =H19+G19+F19 -> 0 | M19: =L19+K19+J19 -> 0 | Q19: =P19+O19+N19 -> 0 | U19: =T19+S19+R19 -> 0 | V19: =U19+Q19+M19+I19 -> 0
D20: 기타_System | E20: 0 | I20: =H20+G20+F20 -> 0 | M20: =L20+K20+J20 -> 0 | Q20: =P20+O20+N20 -> 0 | U20: =T20+S20+R20 -> 0 | V20: =U20+Q20+M20+I20 -> 0
C21: Outside Consultant | I21: =H21+G21+F21 -> 0 | M21: =L21+K21+J21 -> 0 | Q21: =P21+O21+N21 -> 0 | U21: =T21+S21+R21 -> 0 | V21: =U21+Q21+M21+I21 -> 0
C22: Finder commission | I22: =H22+G22+F22 -> 0 | M22: =L22+K22+J22 -> 0 | Q22: =P22+O22+N22 -> 0 | U22: =T22+S22+R22 -> 0 | V22: =U22+Q22+M22+I22 -> 0
C23: S/W+H/W 감가상각 | I23: =H23+G23+F23 -> 0 | M23: =L23+K23+J23 -> 0 | Q23: =P23+O23+N23 -> 0 | U23: =T23+S23+R23 -> 0 | V23: =U23+Q23+M23+I23 -> 0
C24: 지급수수료_기타+임차료 | I24: =H24+G24+F24 -> 0 | M24: =L24+K24+J24 -> 0 | Q24: =P24+O24+N24 -> 0 | U24: =T24+S24+R24 -> 0 | V24: =U24+Q24+M24+I24 -> 0
C25: 보증보험+세금과공과 | E25: 0 | I25: =H25+G25+F25 -> 0 | M25: =L25+K25+J25 -> 0 | Q25: =P25+O25+N25 -> 0 | U25: =T25+S25+R25 -> 0 | V25: =U25+Q25+M25+I25 -> 0
A26: 매 출 원 가 합 계 | F26: =SUM(F16:F25) -> 0 | G26: =SUM(G16:G25) -> 0 | H26: =SUM(H16:H25) -> 0 | I26: =SUM(I16:I25) -> 0 | J26: =SUM(J16:J25) -> 0 | K26: =SUM(K16:K25) -> 0 | L26: =SUM(L16:L25) -> 0 | M26: =SUM(M16:M25) -> 0 | ... V26: =SUM(V16:V25) -> 0
A28: 매 출 이 익 (%)
C29: 총 매출이익 | F29: =F12-F26 -> 0 | G29: =G12-G26 -> 0 | H29: =H12-H26 -> 0 | I29: =I12-I26 -> 0 | J29: =J12-J26 -> 0 | K29: =K12-K26 -> 0 | L29: =L12-L26 -> 0 | M29: =M12-M26 -> 0 | ... V29: =V12-V26 -> 0
D30: 총매출이익률 | F30: =IF(F12=0,0,F29/F12) -> 0 | G30: =IF(G12=0,0,G29/G12) -> 0 | H30: =IF(H12=0,0,H29/H12) -> 0 | I30: =IF(I12=0,0,I29/I12) -> 0 | J30: =IF(J12=0,0,J29/J12) -> 0 | K30: =IF(K12=0,0,K29/K12) -> 0 | L30: =IF(L12=0,0,L29/L12) -> 0 | M30: =IF(M12=0,0,M29/M12) -> 0 | ... V30: =IF(V12=0,0,V29/V12) -> 0
A31: CONTROLLABLE EXPENSE
C32: Salary & Wages
D33: 직원급여 | E33: 0 | F33: 10000000 | G33: 10000000 | H33: 10000000 | I33: =SUM(F33:H33) -> 30000000 | J33: 10000000 | K33: 10000000 | L33: 10000000 | M33: =SUM(J33:L33) -> 30000000 | N33: 10000000 | O33: 10000000 | P33: 10000000 | Q33: =SUM(N33:P33) -> 30000000 | R33: 10000000 | S33: 10000000 | T33: 10000000 | U33: =SUM(R33:T33) -> 30000000 | V33: =I33+M33+Q33+U33 -> 120000000
D34: 특별상여 | F34: 0 | G34: 0 | H34: 0 | I34: =SUM(F34:H34) -> 0 | J34: 0 | K34: 0 | L34: 0 | M34: =SUM(J34:L34) -> 0 | N34: 0 | O34: 0 | P34: 0 | Q34: =SUM(N34:P34) -> 0 | R34: 0 | S34: 0 | T34: 0 | U34: =SUM(R34:T34) -> 0 | V34: =I34+M34+Q34+U34 -> 0
D35: 기타-연차 | E35: 0 | I35: =SUM(F35:H35) -> 0 | M35: =SUM(J35:L35) -> 0 | Q35: =SUM(N35:P35) -> 0 | U35: =SUM(R35:T35) -> 0 | V35: =I35+M35+Q35+U35 -> 0
D36: 퇴직급여 | E36: 0 | F36: 1000000 | G36: 1000000 | H36: 1000000 | I36: =SUM(F36:H36) -> 3000000 | J36: 1000000 | K36: 1000000 | L36: 1000000 | M36: =SUM(J36:L36) -> 3000000 | N36: 1000000 | O36: 1000000 | P36: 1000000 | Q36: =SUM(N36:P36) -> 3000000 | R36: 1000000 | S36: 1000000 | T36: 1000000 | U36: =SUM(R36:T36) -> 3000000 | V36: =I36+M36+Q36+U36 -> 12000000
B37: Total Salary & Wages | F37: =SUM(F33:F36) -> 11000000 | G37: =SUM(G33:G36) -> 11000000 | H37: =SUM(H33:H36) -> 11000000 | I37: =SUM(I33:I36) -> 33000000 | J37: =SUM(J33:J36) -> 11000000 | K37: =SUM(K33:K36) -> 11000000 | L37: =SUM(L33:L36) -> 11000000 | M37: =SUM(M33:M36) -> 33000000 | ... U37: =SUM(U33:U36) -> 33000000 | V37: =I37+M37+Q37+U37 -> 132000000
C38: Benefits
D39: 국민연금 | E39: 0 | F39: 300000 | G39: 300000 | H39: 300000 | I39: =SUM(F39:H39) -> 900000 | J39: 300000 | K39: 300000 | L39: 300000 | M39: =SUM(J39:L39) -> 900000 | N39: 300000 | O39: 300000 | P39: 300000 | Q39: =SUM(N39:P39) -> 900000 | R39: 300000 | S39: 300000 | T39: 300000 | U39: =SUM(R39:T39) -> 900000 | V39: =I39+M39+Q39+U39 -> 3600000
D40: 건강보험 | E40: 0 | F40: 300000 | G40: 300000 | H40: 300000 | I40: =SUM(F40:H40) -> 900000 | J40: 300000 | K40: 300000 | L40: 300000 | M40: =SUM(J40:L40) -> 900000 | N40: 300000 | O40: 300000 | P40: 300000 | Q40: =SUM(N40:P40) -> 900000 | R40: 300000 | S40: 300000 | T40: 300000 | U40: =SUM(R40:T40) -> 900000 | V40: =I40+M40+Q40+U40 -> 3600000
D41: 고용보험 | E41: 0 | F41: 100000 | G41: 100000 | H41: 100000 | I41: =SUM(F41:H41) -> 300000 | J41: 100000 | K41: 100000 | L41: 100000 | M41: =SUM(J41:L41) -> 300000 | N41: 100000 | O41: 100000 | P41: 100000 | Q41: =SUM(N41:P41) -> 300000 | R41: 100000 | S41: 100000 | T41: 100000 | U41: =SUM(R41:T41) -> 300000 | V41: =I41+M41+Q41+U41 -> 1200000
D42: 산재보험 | E42: 0 | F42: 54000 | G42: 54000 | H42: 54000 | I42: =SUM(F42:H42) -> 162000 | J42: 54000 | K42: 54000 | L42: 54000 | M42: =SUM(J42:L42) -> 162000 | N42: 54000 | O42: 54000 | P42: 54000 | Q42: =SUM(N42:P42) -> 162000 | R42: 54000 | S42: 54000 | T42: 54000 | U42: =SUM(R42:T42) -> 162000 | V42: =I42+M42+Q42+U42 -> 648000
D43: 야근식대 | E43: 0 | F43: 15000 | G43: 15000 | H43: 15000 | I43: =SUM(F43:H43) -> 45000 | J43: 15000 | K43: 15000 | L43: 15000 | M43: =SUM(J43:L43) -> 45000 | N43: 15000 | O43: 15000 | P43: 15000 | Q43: =SUM(N43:P43) -> 45000 | R43: 15000 | S43: 15000 | T43: 15000 | U43: =SUM(R43:T43) -> 45000 | V43: =I43+M43+Q43+U43 -> 180000
D44: 회식대 | F44: 40000 | G44: 150000 | H44: 150000 | I44: =SUM(F44:H44) -> 340000 | J44: 150000 | K44: 150000 | L44: 150000 | M44: =SUM(J44:L44) -> 450000 | N44: 150000 | O44: 150000 | P44: 150000 | Q44: =SUM(N44:P44) -> 450000 | R44: 150000 | S44: 150000 | T44: 150000 | U44: =SUM(R44:T44) -> 450000 | V44: =I44+M44+Q44+U44 -> 1690000
D45: 경조사 | E45: 0 | I45: =SUM(F45:H45) -> 0 | M45: =SUM(J45:L45) -> 0 | Q45: =SUM(N45:P45) -> 0 | U45: =SUM(R45:T45) -> 0 | V45: =I45+M45+Q45+U45 -> 0
D46: 교육지원비 | E46: 0 | I46: =SUM(F46:H46) -> 0 | M46: =SUM(J46:L46) -> 0 | Q46: =SUM(N46:P46) -> 0 | U46: =SUM(R46:T46) -> 0 | V46: =I46+M46+Q46+U46 -> 0
D47: 직원상해보험 | E47: 0 | I47: =SUM(F47:H47) -> 0 | M47: =SUM(J47:L47) -> 0 | Q47: =SUM(N47:P47) -> 0 | U47: =SUM(R47:T47) -> 0 | V47: =I47+M47+Q47+U47 -> 0
D48: 건강검진 | E48: 0 | I48: =SUM(F48:H48) -> 0 | M48: =SUM(J48:L48) -> 0 | Q48: =SUM(N48:P48) -> 0 | U48: =SUM(R48:T48) -> 0 | V48: =I48+M48+Q48+U48 -> 0
D49: 통신비(핸드폰) | F49: 65000 | G49: 65000 | H49: 65000 | I49: =SUM(F49:H49) -> 195000 | J49: 65000 | K49: 65000 | L49: 65000 | M49: =SUM(J49:L49) -> 195000 | N49: 65000 | O49: 65000 | P49: 65000 | Q49: =SUM(N49:P49) -> 195000 | R49: 65000 | S49: 65000 | T49: 65000 | U49: =SUM(R49:T49) -> 195000 | V49: =I49+M49+Q49+U49 -> 780000
D50: 체력단련비 | I50: =SUM(F50:H50) -> 0 | M50: =SUM(J50:L50) -> 0 | Q50: =SUM(N50:P50) -> 0 | U50: =SUM(R50:T50) -> 0 | V50: =I50+M50+Q50+U50 -> 0
B51: Total Benefits | F51: =SUM(F39:F50) -> 874000 | G51: =SUM(G39:G50) -> 984000 | H51: =SUM(H39:H50) -> 984000 | I51: =SUM(I39:I50) -> 2842000 | J51: =SUM(J39:J50) -> 984000 | K51: =SUM(K39:K50) -> 984000 | L51: =SUM(L39:L50) -> 984000 | M51: =SUM(M39:M50) -> 2952000 | ... U51: =SUM(U39:U50) -> 2952000 | V51: =I51+M51+Q51+U51 -> 11698000
B52: Total Compensation & Benefits | F52: =F37+F51 -> 11874000 | G52: =G37+G51 -> 11984000 | H52: =H37+H51 -> 11984000 | I52: =I51+I37 -> 35842000 | J52: =J37+J51 -> 11984000 | K52: =K37+K51 -> 11984000 | L52: =L37+L51 -> 11984000 | M52: =M51+M37 -> 35952000 | N52: =N37+N51 -> 11984000 | O52: =O37+O51 -> 11984000 | P52: =P37+P51 -> 11984000 | Q52: =Q51+Q37 -> 35952000 | R52: =R37+R51 -> 11984000 | S52: =S37+S51 -> 11984000 | T52: =T37+T51 -> 11984000 | U52: =U51+U37 -> 35952000 | V52: =I52+M52+Q52+U52 -> 143698000
B53: Unfunded Consulting Expenses | E53: 0 | F53: 0 | G53: 0 | H53: 0 | I53: 0 | J53: 0 | K53: 0 | L53: 0 | M53: 0 | N53: 0 | O53: 0 | P53: 0 | Q53: 0 | R53: 0 | S53: 0 | T53: 0 | U53: 0 | V53: =I53+M53+Q53+U53 -> 0
B54: Travel & Entertainment
C55: 여비교통비(출장일비) | E55: 0 | I55: =SUM(F55:H55) -> 0 | M55: =SUM(J55:L55) -> 0 | Q55: =SUM(N55:P55) -> 0 | U55: =SUM(R55:T55) -> 0 | V55: =I55+M55+Q55+U55 -> 0
C56: 여비교통비(출장식대) | F56: 96000 | G56: 96000 | H56: 96000 | I56: =SUM(F56:H56) -> 288000 | J56: 96000 | K56: 96000 | L56: 96000 | M56: =SUM(J56:L56) -> 288000 | N56: 96000 | O56: 96000 | P56: 96000 | Q56: =SUM(N56:P56) -> 288000 | R56: 96000 | S56: 96000 | T56: 96000 | U56: =SUM(R56:T56) -> 288000 | V56: =I56+M56+Q56+U56 -> 1152000
C57: 여비교통비(통행,주차) | F57: 54000 | G57: 54000 | H57: 54000 | I57: =SUM(F57:H57) -> 162000 | J57: 54000 | K57: 54000 | L57: 54000 | M57: =SUM(J57:L57) -> 162000 | N57: 54000 | O57: 54000 | P57: 54000 | Q57: =SUM(N57:P57) -> 162000 | R57: 54000 | S57: 54000 | T57: 54000 | U57: =SUM(R57:T57) -> 162000 | V57: =I57+M57+Q57+U57 -> 648000
C58: 여비교통비(항공,고속버스등) | F58: 233000 | G58: 233000 | H58: 233000 | I58: =SUM(F58:H58) -> 699000 | J58: 233000 | K58: 233000 | L58: 233000 | M58: =SUM(J58:L58) -> 699000 | N58: 233000 | O58: 233000 | P58: 233000 | Q58: =SUM(N58:P58) -> 699000 | R58: 233000 | S58: 233000 | T58: 233000 | U58: =SUM(R58:T58) -> 699000 | V58: =I58+M58+Q58+U58 -> 2796000
C59: 여비교통비(숙박) | F59: 71000 | G59: 71000 | H59: 71000 | I59: =SUM(F59:H59) -> 213000 | J59: 71000 | K59: 71000 | L59: 71000 | M59: =SUM(J59:L59) -> 213000 | N59: 71000 | O59: 71000 | P59: 71000 | Q59: =SUM(N59:P59) -> 213000 | R59: 71000 | S59: 71000 | T59: 71000 | U59: =SUM(R59:T59) -> 213000 | V59: =I59+M59+Q59+U59 -> 852000
C60: 여비교통비(차량지원) | I60: =SUM(F60:H60) -> 0 | M60: =SUM(J60:L60) -> 0 | Q60: =SUM(N60:P60) -> 0 | U60: =SUM(R60:T60) -> 0 | V60: =I60+M60+Q60+U60 -> 0
C61: 여비교통비(국책과제_연구활동비) | I61: =SUM(F61:H61) -> 0 | M61: =SUM(J61:L61) -> 0 | Q61: =SUM(N61:P61) -> 0 | U61: =SUM(R61:T61) -> 0 | V61: =I61+M61+Q61+U61 -> 0
C62: 차량유지비 | E62: 0 | I62: =SUM(F62:H62) -> 0 | M62: =SUM(J62:L62) -> 0 | Q62: =SUM(N62:P62) -> 0 | U62: =SUM(R62:T62) -> 0 | V62: =I62+M62+Q62+U62 -> 0
C63: 해외출장비 | E63: 0 | I63: =SUM(F63:H63) -> 0 | M63: =SUM(J63:L63) -> 0 | Q63: =SUM(N63:P63) -> 0 | U63: =SUM(R63:T63) -> 0 | V63: =I63+M63+Q63+U63 -> 0
C64: 회의비 | E64: 0 | F64: 47000 | G64: 50000 | H64: 50000 | I64: =SUM(F64:H64) -> 147000 | J64: 50000 | K64: 50000 | L64: 50000 | M64: =SUM(J64:L64) -> 150000 | N64: 50000 | O64: 50000 | P64: 50000 | Q64: =SUM(N64:P64) -> 150000 | R64: 50000 | S64: 50000 | T64: 50000 | U64: =SUM(R64:T64) -> 150000 | V64: =I64+M64+Q64+U64 -> 597000
C65: 접대비 | E65: 0 | F65: 253000 | G65: 200000 | H65: 200000 | I65: =SUM(F65:H65) -> 653000 | J65: 200000 | K65: 200000 | L65: 200000 | M65: =SUM(J65:L65) -> 600000 | N65: 200000 | O65: 200000 | P65: 200000 | Q65: =SUM(N65:P65) -> 600000 | R65: 200000 | S65: 200000 | T65: 200000 | U65: =SUM(R65:T65) -> 600000 | V65: =I65+M65+Q65+U65 -> 2453000
B66: Total Travel & Entertainment | F66: =SUM(F55:F65) -> 754000 | G66: =SUM(G55:G65) -> 704000 | H66: =SUM(H55:H65) -> 704000 | I66: =SUM(I55:I65) -> 2162000 | J66: =SUM(J55:J65) -> 704000 | K66: =SUM(K55:K65) -> 704000 | L66: =SUM(L55:L65) -> 704000 | M66: =SUM(M55:M65) -> 2112000 | ... U66: =SUM(U55:U65) -> 2112000 | V66: =I66+M66+Q66+U66 -> 8498000
B67: Product Marketing
C68: 행사비 | E68: 0 | I68: =SUM(F68:H68) -> 0 | M68: =SUM(J68:L68) -> 0 | Q68: =SUM(N68:P68) -> 0 | U68: =SUM(R68:T68) -> 0 | V68: =I68+M68+Q68+U68 -> 0
C69: 마케팅 | E69: 0 | I69: =SUM(F69:H69) -> 0 | M69: =SUM(J69:L69) -> 0 | Q69: =SUM(N69:P69) -> 0 | U69: =SUM(R69:T69) -> 0 | V69: =I69+M69+Q69+U69 -> 0
C70: 기타 | E70: 0 | I70: =SUM(F70:H70) -> 0 | M70: =SUM(J70:L70) -> 0 | Q70: =SUM(N70:P70) -> 0 | U70: =SUM(R70:T70) -> 0 | V70: =I70+M70+Q70+U70 -> 0
B71: Total Product Marketing | F71: =SUM(F68:F70) -> 0 | G71: =SUM(G68:G70) -> 0 | H71: =SUM(H68:H70) -> 0 | I71: =SUM(I68:I70) -> 0 | J71: =SUM(J68:J70) -> 0 | K71: =SUM(K68:K70) -> 0 | L71: =SUM(L68:L70) -> 0 | M71: =SUM(M68:M70) -> 0 | ... U71: =SUM(U68:U70) -> 0 | V71: =I71+M71+Q71+U71 -> 0
B72: Sales Activities
C73: 고객교육훈련비 | E73: 0 | I73: =SUM(F73:H73) -> 0 | M73: =SUM(J73:L73) -> 0 | Q73: =SUM(N73:P73) -> 0 | U73: =SUM(R73:T73) -> 0 | V73: =I73+M73+Q73+U73 -> 0
C74: Sales Promotions | E74: 0 | I74: =SUM(F74:H74) -> 0 | M74: =SUM(J74:L74) -> 0 | Q74: =SUM(N74:P74) -> 0 | U74: =SUM(R74:T74) -> 0 | V74: =I74+M74+Q74+U74 -> 0
C75: Other Sales Activities | E75: 0 | I75: =SUM(F75:H75) -> 0 | M75: =SUM(J75:L75) -> 0 | Q75: =SUM(N75:P75) -> 0 | U75: =SUM(R75:T75) -> 0 | V75: =I75+M75+Q75+U75 -> 0
B76: Total Sales Activities | F76: =SUM(F73:F75) -> 0 | G76: =SUM(G73:G75) -> 0 | H76: =SUM(H73:H75) -> 0 | I76: =SUM(I73:I75) -> 0 | J76: =SUM(J73:J75) -> 0 | K76: =SUM(K73:K75) -> 0 | L76: =SUM(L73:L75) -> 0 | M76: =SUM(M73:M75) -> 0 | ... U76: =SUM(U73:U75) -> 0 | V76: =I76+M76+Q76+U76 -> 0
D77: TOTAL CONTROLLABLE EXP. | F77: =F52+F53+F66+F71+F76 -> 12628000 | G77: =G52+G53+G66+G71+G76 -> 12688000 | H77: =H52+H53+H66+H71+H76 -> 12688000 | I77: =I76+I71+I66+I53+I52 -> 38004000 | J77: =J52+J53+J66+J71+J76 -> 12688000 | K77: =K52+K53+K66+K71+K76 -> 12688000 | L77: =L52+L53+L66+L71+L76 -> 12688000 | M77: =M76+M71+M66+M53+M52 -> 38064000 | N77: =N52+N53+N66+N71+N76 -> 12688000 | O77: =O52+O53+O66+O71+O76 -> 12688000 | P77: =P52+P53+P66+P71+P76 -> 12688000 | Q77: =Q76+Q71+Q66+Q53+Q52 -> 38064000 | R77: =R52+R53+R66+R71+R76 -> 12688000 | S77: =S52+S53+S66+S71+S76 -> 12688000 | T77: =T52+T53+T66+T71+T76 -> 12688000 | U77: =U76+U71+U66+U53+U52 -> 38064000 | V77: =I77+M77+Q77+U77 -> 152196000
A78: FIXED EXPENSE
B79: Facility & Equipment
C80: 사무실-임차료 | E80: 0 | F80: 0 | I80: =SUM(F80:H80) -> 0 | M80: =SUM(J80:L80) -> 0 | Q80: =SUM(N80:P80) -> 0 | U80: =SUM(R80:T80) -> 0 | V80: =I80+M80+Q80+U80 -> 0
C81: 사무실-관리비 | E81: 0 | I81: =SUM(F81:H81) -> 0 | M81: =SUM(J81:L81) -> 0 | Q81: =SUM(N81:P81) -> 0 | U81: =SUM(R81:T81) -> 0 | V81: =I81+M81+Q81+U81 -> 0
C82: 비품 감가상각 | E82: 0 | I82: =SUM(F82:H82) -> 0 | M82: =SUM(J82:L82) -> 0 | Q82: =SUM(N82:P82) -> 0 | U82: =SUM(R82:T82) -> 0 | V82: =I82+M82+Q82+U82 -> 0
C83: 시설물 감가상각 | I83: =SUM(F83:H83) -> 0 | M83: =SUM(J83:L83) -> 0 | Q83: =SUM(N83:P83) -> 0 | U83: =SUM(R83:T83) -> 0 | V83: =I83+M83+Q83+U83 -> 0
C84: 기계설비 임차료 | I84: =SUM(F84:H84) -> 0 | M84: =SUM(J84:L84) -> 0 | Q84: =SUM(N84:P84) -> 0 | U84: =SUM(R84:T84) -> 0 | V84: =I84+M84+Q84+U84 -> 0
C85: 전화요금 | E85: 0 | I85: =SUM(F85:H85) -> 0 | M85: =SUM(J85:L85) -> 0 | Q85: =SUM(N85:P85) -> 0 | U85: =SUM(R85:T85) -> 0 | V85: =I85+M85+Q85+U85 -> 0
C86: 사무실관리비 | E86: 0 | I86: =SUM(F86:H86) -> 0 | M86: =SUM(J86:L86) -> 0 | Q86: =SUM(N86:P86) -> 0 | U86: =SUM(R86:T86) -> 0 | V86: =I86+M86+Q86+U86 -> 0
C87: 기타_프로그램임차 | E87: 0 | I87: =SUM(F87:H87) -> 0 | M87: =SUM(J87:L87) -> 0 | Q87: =SUM(N87:P87) -> 0 | U87: =SUM(R87:T87) -> 0 | V87: =I87+M87+Q87+U87 -> 0
B88: Total Facility Expense | F88: =SUM(F80:F87) -> 0 | G88: =SUM(G80:G87) -> 0 | H88: =SUM(H80:H87) -> 0 | I88: =SUM(I80:I87) -> 0 | J88: =SUM(J80:J87) -> 0 | K88: =SUM(K80:K87) -> 0 | L88: =SUM(L80:L87) -> 0 | M88: =SUM(M80:M87) -> 0 | ... U88: =SUM(U80:U87) -> 0 | V88: =I88+M88+Q88+U88 -> 0
B89: Total Software License for Internal Use | E89: 0 | F89: 0 | G89: 0 | H89: 0 | I89: =SUM(I81:I88) -> 0 | J89: 0 | K89: 0 | L89: 0 | M89: =SUM(M81:M88) -> 0 | N89: 0 | O89: 0 | P89: 0 | Q89: =SUM(Q81:Q88) -> 0 | R89: 0 | S89: 0 | T89: 0 | U89: 0 | V89: =I89+M89+Q89+U89 -> 0
B90: Office Expense | I90: =SUM(F90:H90) -> 0 | M90: =SUM(J90:L90) -> 0 | Q90: =SUM(N90:P90) -> 0 | U90: =SUM(R90:T90) -> 0 | V90: =I90+M90+Q90+U90 -> 0
C91: 도서인쇄비 | E91: 0 | F91: 19000 | I91: =SUM(F91:H91) -> 19000 | M91: =SUM(J91:L91) -> 0 | Q91: =SUM(N91:P91) -> 0 | U91: =SUM(R91:T91) -> 0 | V91: =I91+M91+Q91+U91 -> 19000
C92: 사무용품비 | E92: 0 | I92: =SUM(F92:H92) -> 0 | M92: =SUM(J92:L92) -> 0 | Q92: =SUM(N92:P92) -> 0 | U92: =SUM(R92:T92) -> 0 | V92: =I92+M92+Q92+U92 -> 0
C93: 소모품비 | E93: 0 | I93: =SUM(F93:H93) -> 0 | M93: =SUM(J93:L93) -> 0 | Q93: =SUM(N93:P93) -> 0 | U93: =SUM(R93:T93) -> 0 | V93: =I93+M93+Q93+U93 -> 0
C94: 우편료 | E94: 0 | I94: =SUM(F94:H94) -> 0 | M94: =SUM(J94:L94) -> 0 | Q94: =SUM(N94:P94) -> 0 | U94: =SUM(R94:T94) -> 0 | V94: =I94+M94+Q94+U94 -> 0
C95: 운반비 | E95: 0 | I95: =SUM(F95:H95) -> 0 | M95: =SUM(J95:L95) -> 0 | Q95: =SUM(N95:P95) -> 0 | U95: =SUM(R95:T95) -> 0 | V95: =I95+M95+Q95+U95 -> 0
C96: 수선비 | E96: 0 | I96: =SUM(F96:H96) -> 0 | M96: =SUM(J96:L96) -> 0 | Q96: =SUM(N96:P96) -> 0 | U96: =SUM(R96:T96) -> 0 | V96: =I96+M96+Q96+U96 -> 0
B97: Total Office Expense | F97: =SUM(F91:F96) -> 19000 | G97: =SUM(G91:G96) -> 0 | H97: =SUM(H91:H96) -> 0 | I97: =SUM(I91:I96) -> 19000 | J97: =SUM(J91:J96) -> 0 | K97: =SUM(K91:K96) -> 0 | L97: =SUM(L91:L96) -> 0 | M97: =SUM(M91:M96) -> 0 | ... U97: =SUM(U91:U96) -> 0 | V97: =I97+M97+Q97+U97 -> 19000
B98: Business Expense
C99: 기술고문료 | E99: 0 | I99: =SUM(F99:H99) -> 0 | M99: =SUM(J99:L99) -> 0 | Q99: =SUM(N99:P99) -> 0 | U99: =SUM(R99:T99) -> 0 | V99: =I99+M99+Q99+U99 -> 0
C100: 세무감사료 | E100: 0 | I100: =SUM(F100:H100) -> 0 | M100: =SUM(J100:L100) -> 0 | Q100: =SUM(N100:P100) -> 0 | U100: =SUM(R100:T100) -> 0 | V100: =I100+M100+Q100+U100 -> 0
C101: 홈페이지관리외 | E101: 0 | I101: =SUM(F101:H101) -> 0 | M101: =SUM(J101:L101) -> 0 | Q101: =SUM(N101:P101) -> 0 | U101: =SUM(R101:T101) -> 0 | V101: =I101+M101+Q101+U101 -> 0
C102: 보증보험 | E102: 0 | I102: =SUM(F102:H102) -> 0 | M102: =SUM(J102:L102) -> 0 | Q102: =SUM(N102:P102) -> 0 | U102: =SUM(R102:T102) -> 0 | V102: =I102+M102+Q102+U102 -> 0
C103: 보험료-차량+여행자 | E103: 0 | I103: =SUM(F103:H103) -> 0 | M103: =SUM(J103:L103) -> 0 | Q103: =SUM(N103:P103) -> 0 | U103: =SUM(R103:T103) -> 0 | V103: =I103+M103+Q103+U103 -> 0
...

Sheet TST
F1: 1월 | G1: 2월 | H1: 3월 | I1: Q1 | J1: 4월 | K1: 5월 | L1: 6월 | M1: Q2 | N1: 7월 | O1: 8월 | P1: 9월 | Q1: Q3 | R1: 10월 | S1: 11월 | T1: 12월 | U1: Q4 | V1: 2026
F2: Actual | G2: Actual | H2: Actual | I2: Total | J2: Actual | K2: Actual | L2: Actual | M2: Total | N2: Actual | O2: Actual | P2: Actual | Q2: Total | R2: Actual | S2: Actual | T2: Actual | U2: Total | V2: Total
A3: 매 출
B4: Solution Business
D5: Lease | E5: 1 | F5: ='TST1'!F5+'TST2'!F5+MKT!F5+SYShin!F5+JGChoi!F5 -> 350975000 | G5: ='TST1'!G5+'TST2'!G5+MKT!G5+SYShin!G5+JGChoi!G5 -> 28000000 | H5: ='TST1'!H5+'TST2'!H5+MKT!H5+SYShin!H5+JGChoi!H5 -> 28000000 | I5: =H5+G5+F5 -> 406975000 | J5: ='TST1'!J5+'TST2'!J5+MKT!J5+SYShin!J5+JGChoi!J5 -> 28000000 | K5: ='TST1'!K5+'TST2'!K5+MKT!K5+SYShin!K5+JGChoi!K5 -> 28000000 | L5: ='TST1'!L5+'TST2'!L5+MKT!L5+SYShin!L5+JGChoi!L5 -> 28000000 | M5: =L5+K5+J5 -> 84000000 | N5: ='TST1'!N5+'TST2'!N5+MKT!N5+SYShin!N5+JGChoi!N5 -> 28000000 | O5: ='TST1'!O5+'TST2'!O5+MKT!O5+SYShin!O5+JGChoi!O5 -> 28000000 | P5: ='TST1'!P5+'TST2'!P5+MKT!P5+SYShin!P5+JGChoi!P5 -> 28000000 | Q5: =P5+O5+N5 -> 84000000 | R5: ='TST1'!R5+'TST2'!R5+MKT!R5+SYShin!R5+JGChoi!R5 -> 28000000 | S5: ='TST1'!S5+'TST2'!S5+MKT!S5+SYShin!S5+JGChoi!S5 -> 28000000 | T5: ='TST1'!T5+'TST2'!T5+MKT!T5+SYShin!T5+JGChoi!T5 -> 28000000 | U5: =T5+S5+R5 -> 84000000 | V5: =U5+Q5+M5+I5 -> 658975000
D6: E&S | E6: 1 | F6: ='TST1'!F6+'TST2'!F6+MKT!F6+SYShin!F6+JGChoi!F6 -> 672883000 | G6: ='TST1'!G6+'TST2'!G6+MKT!G6+SYShin!G6+JGChoi!G6 -> 105000000 | H6: ='TST1'!H6+'TST2'!H6+MKT!H6+SYShin!H6+JGChoi!H6 -> 105000000 | I6: =H6+G6+F6 -> 882883000 | J6: ='TST1'!J6+'TST2'!J6+MKT!J6+SYShin!J6+JGChoi!J6 -> 105000000 | K6: ='TST1'!K6+'TST2'!K6+MKT!K6+SYShin!K6+JGChoi!K6 -> 105000000 | L6: ='TST1'!L6+'TST2'!L6+MKT!L6+SYShin!L6+JGChoi!L6 -> 105000000 | M6: =L6+K6+J6 -> 315000000 | N6: ='TST1'!N6+'TST2'!N6+MKT!N6+SYShin!N6+JGChoi!N6 -> 105000000 | O6: ='TST1'!O6+'TST2'!O6+MKT!O6+SYShin!O6+JGChoi!O6 -> 105000000 | P6: ='TST1'!P6+'TST2'!P6+MKT!P6+SYShin!P6+JGChoi!P6 -> 105000000 | Q6: =P6+O6+N6 -> 315000000 | R6: ='TST1'!R6+'TST2'!R6+MKT!R6+SYShin!R6+JGChoi!R6 -> 105000000 | S6: ='TST1'!S6+'TST2'!S6+MKT!S6+SYShin!S6+JGChoi!S6 -> 105000000 | T6: ='TST1'!T6+'TST2'!T6+MKT!T6+SYShin!T6+JGChoi!T6 -> 105000000 | U6: =T6+S6+R6 -> 315000000 | V6: =U6+Q6+M6+I6 -> 1827883000
D7: Paid-up | E7: 1 | F7: ='TST1'!F7+'TST2'!F7+MKT!F7+SYShin!F7+JGChoi!F7 -> 93609000 | G7: ='TST1'!G7+'TST2'!G7+MKT!G7+SYShin!G7+JGChoi!G7 -> 90000000 | H7: ='TST1'!H7+'TST2'!H7+MKT!H7+SYShin!H7+JGChoi!H7 -> 90000000 | I7: =H7+G7+F7 -> 273609000 | J7: ='TST1'!J7+'TST2'!J7+MKT!J7+SYShin!J7+JGChoi!J7 -> 90000000 | K7: ='TST1'!K7+'TST2'!K7+MKT!K7+SYShin!K7+JGChoi!K7 -> 90000000 | L7: ='TST1'!L7+'TST2'!L7+MKT!L7+SYShin!L7+JGChoi!L7 -> 90000000 | M7: =L7+K7+J7 -> 270000000 | N7: ='TST1'!N7+'TST2'!N7+MKT!N7+SYShin!N7+JGChoi!N7 -> 90000000 | O7: ='TST1'!O7+'TST2'!O7+MKT!O7+SYShin!O7+JGChoi!O7 -> 90000000 | P7: ='TST1'!P7+'TST2'!P7+MKT!P7+SYShin!P7+JGChoi!P7 -> 90000000 | Q7: =P7+O7+N7 -> 270000000 | R7: ='TST1'!R7+'TST2'!R7+MKT!R7+SYShin!R7+JGChoi!R7 -> 90000000 | S7: ='TST1'!S7+'TST2'!S7+MKT!S7+SYShin!S7+JGChoi!S7 -> 90000000 | T7: ='TST1'!T7+'TST2'!T7+MKT!T7+SYShin!T7+JGChoi!T7 -> 90000000 | U7: =T7+S7+R7 -> 270000000 | V7: =U7+Q7+M7+I7 -> 1083609000
D8: 기타_HW Transfer | F8: ='TST1'!F8+'TST2'!F8+MKT!F8+SYShin!F8+JGChoi!F8 -> 0 | G8: ='TST1'!G8+'TST2'!G8+MKT!G8+SYShin!G8+JGChoi!G8 -> 0 | H8: ='TST1'!H8+'TST2'!H8+MKT!H8+SYShin!H8+JGChoi!H8 -> 0 | I8: =H8+G8+F8 -> 0 | J8: ='TST1'!J8+'TST2'!J8+MKT!J8+SYShin!J8+JGChoi!J8 -> 0 | K8: ='TST1'!K8+'TST2'!K8+MKT!K8+SYShin!K8+JGChoi!K8 -> 0 | L8: ='TST1'!L8+'TST2'!L8+MKT!L8+SYShin!L8+JGChoi!L8 -> 0 | M8: =L8+K8+J8 -> 0 | N8: ='TST1'!N8+'TST2'!N8+MKT!N8+SYShin!N8+JGChoi!N8 -> 0 | O8: ='TST1'!O8+'TST2'!O8+MKT!O8+SYShin!O8+JGChoi!O8 -> 0 | P8: ='TST1'!P8+'TST2'!P8+MKT!P8+SYShin!P8+JGChoi!P8 -> 0 | Q8: =P8+O8+N8 -> 0 | R8: ='TST1'!R8+'TST2'!R8+MKT!R8+SYShin!R8+JGChoi!R8 -> 0 | S8: ='TST1'!S8+'TST2'!S8+MKT!S8+SYShin!S8+JGChoi!S8 -> 0 | T8: ='TST1'!T8+'TST2'!T8+MKT!T8+SYShin!T8+JGChoi!T8 -> 0 | U8: =T8+S8+R8 -> 0 | V8: =U8+Q8+M8+I8 -> 0
D9: Service | F9: ='TST1'!F9+'TST2'!F9+MKT!F9+SYShin!F9+JGChoi!F9 -> 0 | G9: ='TST1'!G9+'TST2'!G9+MKT!G9+SYShin!G9+JGChoi!G9 -> 0 | H9: ='TST1'!H9+'TST2'!H9+MKT!H9+SYShin!H9+JGChoi!H9 -> 0 | I9: =H9+G9+F9 -> 0 | J9: ='TST1'!J9+'TST2'!J9+MKT!J9+SYShin!J9+JGChoi!J9 -> 0 | K9: ='TST1'!K9+'TST2'!K9+MKT!K9+SYShin!K9+JGChoi!K9 -> 0 | L9: ='TST1'!L9+'TST2'!L9+MKT!L9+SYShin!L9+JGChoi!L9 -> 0 | M9: =L9+K9+J9 -> 0 | N9: ='TST1'!N9+'TST2'!N9+MKT!N9+SYShin!N9+JGChoi!N9 -> 0 | O9: ='TST1'!O9+'TST2'!O9+MKT!O9+SYShin!O9+JGChoi!O9 -> 0 | P9: ='TST1'!P9+'TST2'!P9+MKT!P9+SYShin!P9+JGChoi!P9 -> 0 | Q9: =P9+O9+N9 -> 0 | R9: ='TST1'!R9+'TST2'!R9+MKT!R9+SYShin!R9+JGChoi!R9 -> 0 | S9: ='TST1'!S9+'TST2'!S9+MKT!S9+SYShin!S9+JGChoi!S9 -> 0 | T9: ='TST1'!T9+'TST2'!T9+MKT!T9+SYShin!T9+JGChoi!T9 -> 0 | U9: =T9+S9+R9 -> 0 | V9: =U9+Q9+M9+I9 -> 0
D10: Seminar/Training | F10: ='TST1'!F10+'TST2'!F10+MKT!F10+SYShin!F10+JGChoi!F10 -> 0 | G10: ='TST1'!G10+'TST2'!G10+MKT!G10+SYShin!G10+JGChoi!G10 -> 0 | H10: ='TST1'!H10+'TST2'!H10+MKT!H10+SYShin!H10+JGChoi!H10 -> 0 | I10: =H10+G10+F10 -> 0 | J10: ='TST1'!J10+'TST2'!J10+MKT!J10+SYShin!J10+JGChoi!J10 -> 0 | K10: ='TST1'!K10+'TST2'!K10+MKT!K10+SYShin!K10+JGChoi!K10 -> 0 | L10: ='TST1'!L10+'TST2'!L10+MKT!L10+SYShin!L10+JGChoi!L10 -> 0 | M10: =L10+K10+J10 -> 0 | N10: ='TST1'!N10+'TST2'!N10+MKT!N10+SYShin!N10+JGChoi!N10 -> 0 | O10: ='TST1'!O10+'TST2'!O10+MKT!O10+SYShin!O10+JGChoi!O10 -> 0 | P10: ='TST1'!P10+'TST2'!P10+MKT!P10+SYShin!P10+JGChoi!P10 -> 0 | Q10: =P10+O10+N10 -> 0 | R10: ='TST1'!R10+'TST2'!R10+MKT!R10+SYShin!R10+JGChoi!R10 -> 0 | S10: ='TST1'!S10+'TST2'!S10+MKT!S10+SYShin!S10+JGChoi!S10 -> 0 | T10: ='TST1'!T10+'TST2'!T10+MKT!T10+SYShin!T10+JGChoi!T10 -> 0 | U10: =T10+S10+R10 -> 0 | V10: =U10+Q10+M10+I10 -> 0
A12: 매 출 합 계 | F12: =SUM(F5:F10) -> 1117467000 | G12: =SUM(G5:G10) -> 223000000 | H12: =SUM(H5:H10) -> 223000000 | I12: =SUM(I5:I10) -> 1563467000 | J12: =SUM(J5:J10) -> 223000000 | K12: =SUM(K5:K10) -> 223000000 | L12: =SUM(L5:L10) -> 223000000 | M12: =SUM(M5:M10) -> 669000000 | ... V12: =SUM(V5:V10) -> 3570467000
A14: 매 출 원 가
C15: Royalty
D16: MSC Software | E16: 0 | F16: ='TST1'!F16+'TST2'!F16+MKT!F16+SYShin!F16+JGChoi!F16 -> 124632000 | G16: ='TST1'!G16+'TST2'!G16+MKT!G16+SYShin!G16+JGChoi!G16 -> 65000000 | H16: ='TST1'!H16+'TST2'!H16+MKT!H16+SYShin!H16+JGChoi!H16 -> 65000000 | I16: =H16+G16+F16 -> 254632000 | J16: ='TST1'!J16+'TST2'!J16+MKT!J16+SYShin!J16+JGChoi!J16 -> 65000000 | K16: ='TST1'!K16+'TST2'!K16+MKT!K16+SYShin!K16+JGChoi!K16 -> 65000000 | L16: ='TST1'!L16+'TST2'!L16+MKT!L16+SYShin!L16+JGChoi!L16 -> 65000000 | M16: =L16+K16+J16 -> 195000000 | N16: ='TST1'!N16+'TST2'!N16+MKT!N16+SYShin!N16+JGChoi!N16 -> 65000000 | O16: ='TST1'!O16+'TST2'!O16+MKT!O16+SYShin!O16+JGChoi!O16 -> 65000000 | P16: ='TST1'!P16+'TST2'!P16+MKT!P16+SYShin!P16+JGChoi!P16 -> 65000000 | Q16: =P16+O16+N16 -> 195000000 | R16: ='TST1'!R16+'TST2'!R16+MKT!R16+SYShin!R16+JGChoi!R16 -> 65000000 | S16: ='TST1'!S16+'TST2'!S16+MKT!S16+SYShin!S16+JGChoi!S16 -> 65000000 | T16: ='TST1'!T16+'TST2'!T16+MKT!T16+SYShin!T16+JGChoi!T16 -> 65000000 | U16: =T16+S16+R16 -> 195000000 | V16: =U16+Q16+M16+I16 -> 839632000
D17: Altair Software | F17: ='TST1'!F17+'TST2'!F17+MKT!F17+SYShin!F17+JGChoi!F17 -> 201336000 | G17: ='TST1'!G17+'TST2'!G17+MKT!G17+SYShin!G17+JGChoi!G17 -> 43000000 | H17: ='TST1'!H17+'TST2'!H17+MKT!H17+SYShin!H17+JGChoi!H17 -> 43000000 | I17: =H17+G17+F17 -> 287336000 | J17: ='TST1'!J17+'TST2'!J17+MKT!J17+SYShin!J17+JGChoi!J17 -> 43000000 | K17: ='TST1'!K17+'TST2'!K17+MKT!K17+SYShin!K17+JGChoi!K17 -> 43000000 | L17: ='TST1'!L17+'TST2'!L17+MKT!L17+SYShin!L17+JGChoi!L17 -> 43000000 | M17: =L17+K17+J17 -> 129000000 | N17: ='TST1'!N17+'TST2'!N17+MKT!N17+SYShin!N17+JGChoi!N17 -> 43000000 | O17: ='TST1'!O17+'TST2'!O17+MKT!O17+SYShin!O17+JGChoi!O17 -> 43000000 | P17: ='TST1'!P17+'TST2'!P17+MKT!P17+SYShin!P17+JGChoi!P17 -> 43000000 | Q17: =P17+O17+N17 -> 129000000 | R17: ='TST1'!R17+'TST2'!R17+MKT!R17+SYShin!R17+JGChoi!R17 -> 43000000 | S17: ='TST1'!S17+'TST2'!S17+MKT!S17+SYShin!S17+JGChoi!S17 -> 43000000 | T17: ='TST1'!T17+'TST2'!T17+MKT!T17+SYShin!T17+JGChoi!T17 -> 43000000 | U17: =T17+S17+R17 -> 129000000 | V17: =U17+Q17+M17+I17 -> 674336000
D18: SVD Software | F18: ='TST1'!F18+'TST2'!F18+MKT!F18+SYShin!F18+JGChoi!F18 -> 0 | G18: ='TST1'!G18+'TST2'!G18+MKT!G18+SYShin!G18+JGChoi!G18 -> 0 | H18: ='TST1'!H18+'TST2'!H18+MKT!H18+SYShin!H18+JGChoi!H18 -> 0 | I18: =H18+G18+F18 -> 0 | J18: ='TST1'!J18+'TST2'!J18+MKT!J18+SYShin!J18+JGChoi!J18 -> 0 | K18: ='TST1'!K18+'TST2'!K18+MKT!K18+SYShin!K18+JGChoi!K18 -> 0 | L18: ='TST1'!L18+'TST2'!L18+MKT!L18+SYShin!L18+JGChoi!L18 -> 0 | M18: =L18+K18+J18 -> 0 | N18: ='TST1'!N18+'TST2'!N18+MKT!N18+SYShin!N18+JGChoi!N18 -> 0 | O18: ='TST1'!O18+'TST2'!O18+MKT!O18+SYShin!O18+JGChoi!O18 -> 0 | P18: ='TST1'!P18+'TST2'!P18+MKT!P18+SYShin!P18+JGChoi!P18 -> 0 | Q18: =P18+O18+N18 -> 0 | R18: ='TST1'!R18+'TST2'!R18+MKT!R18+SYShin!R18+JGChoi!R18 -> 0 | S18: ='TST1'!S18+'TST2'!S18+MKT!S18+SYShin!S18+JGChoi!S18 -> 0 | T18: ='TST1'!T18+'TST2'!T18+MKT!T18+SYShin!T18+JGChoi!T18 -> 0 | U18: =T18+S18+R18 -> 0 | V18: =U18+Q18+M18+I18 -> 0
D19: TSV+KTM+그외 | F19: ='TST1'!F19+'TST2'!F19+MKT!F19+SYShin!F19+JGChoi!F19 -> 9090000 | G19: ='TST1'!G19+'TST2'!G19+MKT!G19+SYShin!G19+JGChoi!G19 -> 0 | H19: ='TST1'!H19+'TST2'!H19+MKT!H19+SYShin!H19+JGChoi!H19 -> 0 | I19: =H19+G19+F19 -> 9090000 | J19: ='TST1'!J19+'TST2'!J19+MKT!J19+SYShin!J19+JGChoi!J19 -> 0 | K19: ='TST1'!K19+'TST2'!K19+MKT!K19+SYShin!K19+JGChoi!K19 -> 0 | L19: ='TST1'!L19+'TST2'!L19+MKT!L19+SYShin!L19+JGChoi!L19 -> 0 | M19: =L19+K19+J19 -> 0 | N19: ='TST1'!N19+'TST2'!N19+MKT!N19+SYShin!N19+JGChoi!N19 -> 0 | O19: ='TST1'!O19+'TST2'!O19+MKT!O19+SYShin!O19+JGChoi!O19 -> 0 | P19: ='TST1'!P19+'TST2'!P19+MKT!P19+SYShin!P19+JGChoi!P19 -> 0 | Q19: =P19+O19+N19 -> 0 | R19: ='TST1'!R19+'TST2'!R19+MKT!R19+SYShin!R19+JGChoi!R19 -> 0 | S19: ='TST1'!S19+'TST2'!S19+MKT!S19+SYShin!S19+JGChoi!S19 -> 0 | T19: ='TST1'!T19+'TST2'!T19+MKT!T19+SYShin!T19+JGChoi!T19 -> 0 | U19: =T19+S19+R19 -> 0 | V19: =U19+Q19+M19+I19 -> 9090000
D20: 기타_System | E20: 0 | F20: ='TST1'!F20+'TST2'!F20+MKT!F20+SYShin!F20+JGChoi!F20 -> 0 | G20: ='TST1'!G20+'TST2'!G20+MKT!G20+SYShin!G20+JGChoi!G20 -> 0 | H20: ='TST1'!H20+'TST2'!H20+MKT!H20+SYShin!H20+JGChoi!H20 -> 0 | I20: =H20+G20+F20 -> 0 | J20: ='TST1'!J20+'TST2'!J20+MKT!J20+SYShin!J20+JGChoi!J20 -> 0 | K20: ='TST1'!K20+'TST2'!K20+MKT!K20+SYShin!K20+JGChoi!K20 -> 0 | L20: ='TST1'!L20+'TST2'!L20+MKT!L20+SYShin!L20+JGChoi!L20 -> 0 | M20: =L20+K20+J20 -> 0 | N20: ='TST1'!N20+'TST2'!N20+MKT!N20+SYShin!N20+JGChoi!N20 -> 0 | O20: ='TST1'!O20+'TST2'!O20+MKT!O20+SYShin!O20+JGChoi!O20 -> 0 | P20: ='TST1'!P20+'TST2'!P20+MKT!P20+SYShin!P20+JGChoi!P20 -> 0 | Q20: =P20+O20+N20 -> 0 | R20: ='TST1'!R20+'TST2'!R20+MKT!R20+SYShin!R20+JGChoi!R20 -> 0 | S20: ='TST1'!S20+'TST2'!S20+MKT!S20+SYShin!S20+JGChoi!S20 -> 0 | T20: ='TST1'!T20+'TST2'!T20+MKT!T20+SYShin!T20+JGChoi!T20 -> 0 | U20: =T20+S20+R20 -> 0 | V20: =U20+Q20+M20+I20 -> 0
C21: Outside Consultant | F21: ='TST1'!F21+'TST2'!F21+MKT!F21+SYShin!F21+JGChoi!F21 -> 0 | G21: ='TST1'!G21+'TST2'!G21+MKT!G21+SYShin!G21+JGChoi!G21 -> 0 | H21: ='TST1'!H21+'TST2'!H21+MKT!H21+SYShin!H21+JGChoi!H21 -> 0 | I21: =H21+G21+F21 -> 0 | J21: ='TST1'!J21+'TST2'!J21+MKT!J21+SYShin!J21+JGChoi!J21 -> 0 | K21: ='TST1'!K21+'TST2'!K21+MKT!K21+SYShin!K21+JGChoi!K21 -> 0 | L21: ='TST1'!L21+'TST2'!L21+MKT!L21+SYShin!L21+JGChoi!L21 -> 0 | M21: =L21+K21+J21 -> 0 | N21: ='TST1'!N21+'TST2'!N21+MKT!N21+SYShin!N21+JGChoi!N21 -> 0 | O21: ='TST1'!O21+'TST2'!O21+MKT!O21+SYShin!O21+JGChoi!O21 -> 0 | P21: ='TST1'!P21+'TST2'!P21+MKT!P21+SYShin!P21+JGChoi!P21 -> 0 | Q21: =P21+O21+N21 -> 0 | R21: ='TST1'!R21+'TST2'!R21+MKT!R21+SYShin!R21+JGChoi!R21 -> 0 | S21: ='TST1'!S21+'TST2'!S21+MKT!S21+SYShin!S21+JGChoi!S21 -> 0 | T21: ='TST1'!T21+'TST2'!T21+MKT!T21+SYShin!T21+JGChoi!T21 -> 0 | U21: =T21+S21+R21 -> 0 | V21: =U21+Q21+M21+I21 -> 0
C22: Finder commission | F22: ='TST1'!F22+'TST2'!F22+MKT!F22+SYShin!F22+JGChoi!F22 -> 0 | G22: ='TST1'!G22+'TST2'!G22+MKT!G22+SYShin!G22+JGChoi!G22 -> 0 | H22: ='TST1'!H22+'TST2'!H22+MKT!H22+SYShin!H22+JGChoi!H22 -> 0 | I22: =H22+G22+F22 -> 0 | J22: ='TST1'!J22+'TST2'!J22+MKT!J22+SYShin!J22+JGChoi!J22 -> 0 | K22: ='TST1'!K22+'TST2'!K22+MKT!K22+SYShin!K22+JGChoi!K22 -> 0 | L22: ='TST1'!L22+'TST2'!L22+MKT!L22+SYShin!L22+JGChoi!L22 -> 0 | M22: =L22+K22+J22 -> 0 | N22: ='TST1'!N22+'TST2'!N22+MKT!N22+SYShin!N22+JGChoi!N22 -> 0 | O22: ='TST1'!O22+'TST2'!O22+MKT!O22+SYShin!O22+JGChoi!O22 -> 0 | P22: ='TST1'!P22+'TST2'!P22+MKT!P22+SYShin!P22+JGChoi!P22 -> 0 | Q22: =P22+O22+N22 -> 0 | R22: ='TST1'!R22+'TST2'!R22+MKT!R22+SYShin!R22+JGChoi!R22 -> 0 | S22: ='TST1'!S22+'TST2'!S22+MKT!S22+SYShin!S22+JGChoi!S22 -> 0 | T22: ='TST1'!T22+'TST2'!T22+MKT!T22+SYShin!T22+JGChoi!T22 -> 0 | U22: =T22+S22+R22 -> 0 | V22: =U22+Q22+M22+I22 -> 0
C23: S/W+H/W 감가상각 | F23: ='TST1'!F23+'TST2'!F23+MKT!F23+SYShin!F23+JGChoi!F23 -> 57000 | G23: ='TST1'!G23+'TST2'!G23+MKT!G23+SYShin!G23+JGChoi!G23 -> 57000 | H23: ='TST1'!H23+'TST2'!H23+MKT!H23+SYShin!H23+JGChoi!H23 -> 57000 | I23: =H23+G23+F23 -> 171000 | J23: ='TST1'!J23+'TST2'!J23+MKT!J23+SYShin!J23+JGChoi!J23 -> 57000 | K23: ='TST1'!K23+'TST2'!K23+MKT!K23+SYShin!K23+JGChoi!K23 -> 57000 | L23: ='TST1'!L23+'TST2'!L23+MKT!L23+SYShin!L23+JGChoi!L23 -> 57000 | M23: =L23+K23+J23 -> 171000 | N23: ='TST1'!N23+'TST2'!N23+MKT!N23+SYShin!N23+JGChoi!N23 -> 57000 | O23: ='TST1'!O23+'TST2'!O23+MKT!O23+SYShin!O23+JGChoi!O23 -> 57000 | P23: ='TST1'!P23+'TST2'!P23+MKT!P23+SYShin!P23+JGChoi!P23 -> 57000 | Q23: =P23+O23+N23 -> 171000 | R23: ='TST1'!R23+'TST2'!R23+MKT!R23+SYShin!R23+JGChoi!R23 -> 57000 | S23: ='TST1'!S23+'TST2'!S23+MKT!S23+SYShin!S23+JGChoi!S23 -> 57000 | T23: ='TST1'!T23+'TST2'!T23+MKT!T23+SYShin!T23+JGChoi!T23 -> 57000 | U23: =T23+S23+R23 -> 171000 | V23: =U23+Q23+M23+I23 -> 684000
C24: 지급수수료_기타+임차료 | F24: ='TST1'!F24+'TST2'!F24+MKT!F24+SYShin!F24+JGChoi!F24 -> 967000 | G24: ='TST1'!G24+'TST2'!G24+MKT!G24+SYShin!G24+JGChoi!G24 -> 967000 | H24: ='TST1'!H24+'TST2'!H24+MKT!H24+SYShin!H24+JGChoi!H24 -> 967000 | I24: =H24+G24+F24 -> 2901000 | J24: ='TST1'!J24+'TST2'!J24+MKT!J24+SYShin!J24+JGChoi!J24 -> 967000 | K24: ='TST1'!K24+'TST2'!K24+MKT!K24+SYShin!K24+JGChoi!K24 -> 967000 | L24: ='TST1'!L24+'TST2'!L24+MKT!L24+SYShin!L24+JGChoi!L24 -> 967000 | M24: =L24+K24+J24 -> 2901000 | N24: ='TST1'!N24+'TST2'!N24+MKT!N24+SYShin!N24+JGChoi!N24 -> 967000 | O24: ='TST1'!O24+'TST2'!O24+MKT!O24+SYShin!O24+JGChoi!O24 -> 967000 | P24: ='TST1'!P24+'TST2'!P24+MKT!P24+SYShin!P24+JGChoi!P24 -> 967000 | Q24: =P24+O24+N24 -> 2901000 | R24: ='TST1'!R24+'TST2'!R24+MKT!R24+SYShin!R24+JGChoi!R24 -> 967000 | S24: ='TST1'!S24+'TST2'!S24+MKT!S24+SYShin!S24+JGChoi!S24 -> 967000 | T24: ='TST1'!T24+'TST2'!T24+MKT!T24+SYShin!T24+JGChoi!T24 -> 967000 | U24: =T24+S24+R24 -> 2901000 | V24: =U24+Q24+M24+I24 -> 11604000
C25: 보증보험+세금과공과 | E25: 0 | F25: ='TST1'!F25+'TST2'!F25+MKT!F25+SYShin!F25+JGChoi!F25 -> 0 | G25: ='TST1'!G25+'TST2'!G25+MKT!G25+SYShin!G25+JGChoi!G25 -> 0 | H25: ='TST1'!H25+'TST2'!H25+MKT!H25+SYShin!H25+JGChoi!H25 -> 0 | I25: =H25+G25+F25 -> 0 | J25: ='TST1'!J25+'TST2'!J25+MKT!J25+SYShin!J25+JGChoi!J25 -> 0 | K25: ='TST1'!K25+'TST2'!K25+MKT!K25+SYShin!K25+JGChoi!K25 -> 0 | L25: ='TST1'!L25+'TST2'!L25+MKT!L25+SYShin!L25+JGChoi!L25 -> 0 | M25: =L25+K25+J25 -> 0 | N25: ='TST1'!N25+'TST2'!N25+MKT!N25+SYShin!N25+JGChoi!N25 -> 0 | O25: ='TST1'!O25+'TST2'!O25+MKT!O25+SYShin!O25+JGChoi!O25 -> 0 | P25: ='TST1'!P25+'TST2'!P25+MKT!P25+SYShin!P25+JGChoi!P25 -> 0 | Q25: =P25+O25+N25 -> 0 | R25: ='TST1'!R25+'TST2'!R25+MKT!R25+SYShin!R25+JGChoi!R25 -> 0 | S25: ='TST1'!S25+'TST2'!S25+MKT!S25+SYShin!S25+JGChoi!S25 -> 0 | T25: ='TST1'!T25+'TST2'!T25+MKT!T25+SYShin!T25+JGChoi!T25 -> 0 | U25: =T25+S25+R25 -> 0 | V25: =U25+Q25+M25+I25 -> 0
A26: 매 출 원 가 합 계 | F26: =SUM(F16:F25) -> 336082000 | G26: =SUM(G16:G25) -> 109024000 | H26: =SUM(H16:H25) -> 109024000 | I26: =SUM(I16:I25) -> 554130000 | J26: =SUM(J16:J25) -> 109024000 | K26: =SUM(K16:K25) -> 109024000 | L26: =SUM(L16:L25) -> 109024000 | M26: =SUM(M16:M25) -> 327072000 | ... V26: =SUM(V16:V25) -> 1535346000
A28: 매 출 이 익 (%)
C29: 총 매출이익 | F29: =F12-F26 -> 781385000 | G29: =G12-G26 -> 113976000 | H29: =H12-H26 -> 113976000 | I29: =I12-I26 -> 1009337000 | J29: =J12-J26 -> 113976000 | K29: =K12-K26 -> 113976000 | L29: =L12-L26 -> 113976000 | M29: =M12-M26 -> 341928000 | ... V29: =V12-V26 -> 2035121000
D30: 총매출이익률 | F30: =IF(F12=0,0,F29/F12) -> 0.6992466 | G30: =IF(G12=0,0,G29/G12) -> 0.51110314 | H30: =IF(H12=0,0,H29/H12) -> 0.51110314 | I30: =IF(I12=0,0,I29/I12) -> 0.64557615 | J30: =IF(J12=0,0,J29/J12) -> 0.51110314 | K30: =IF(K12=0,0,K29/K12) -> 0.51110314 | L30: =IF(L12=0,0,L29/L12) -> 0.51110314 | M30: =IF(M12=0,0,M29/M12) -> 0.51110314 | ... V30: =IF(V12=0,0,V29/V12) -> 0.56998734
A31: CONTROLLABLE EXPENSE
C32: Salary & Wages
D33: 직원급여 | E33: 0 | F33: ='TST1'!F33+'TST2'!F33+MKT!F33+SYShin!F33+JGChoi!F33 -> 58000000 | G33: ='TST1'!G33+'TST2'!G33+MKT!G33+SYShin!G33+JGChoi!G33 -> 58000000 | H33: ='TST1'!H33+'TST2'!H33+MKT!H33+SYShin!H33+JGChoi!H33 -> 58000000 | I33: =SUM(F33:H33) -> 174000000 | J33: ='TST1'!J33+'TST2'!J33+MKT!J33+SYShin!J33+JGChoi!J33 -> 58000000 | K33: ='TST1'!K33+'TST2'!K33+MKT!K33+SYShin!K33+JGChoi!K33 -> 58000000 | L33: ='TST1'!L33+'TST2'!L33+MKT!L33+SYShin!L33+JGChoi!L33 -> 58000000 | M33: =SUM(J33:L33) -> 174000000 | N33: ='TST1'!N33+'TST2'!N33+MKT!N33+SYShin!N33+JGChoi!N33 -> 58000000 | O33: ='TST1'!O33+'TST2'!O33+MKT!O33+SYShin!O33+JGChoi!O33 -> 58000000 | P33: ='TST1'!P33+'TST2'!P33+MKT!P33+SYShin!P33+JGChoi!P33 -> 58000000 | Q33: =SUM(N33:P33) -> 174000000 | R33: ='TST1'!R33+'TST2'!R33+MKT!R33+SYShin!R33+JGChoi!R33 -> 58000000 | S33: ='TST1'!S33+'TST2'!S33+MKT!S33+SYShin!S33+JGChoi!S33 -> 58000000 | T33: ='TST1'!T33+'TST2'!T33+MKT!T33+SYShin!T33+JGChoi!T33 -> 58000000 | U33: =SUM(R33:T33) -> 174000000 | V33: =I33+M33+Q33+U33 -> 696000000
D34: 특별상여 | F34: ='TST1'!F34+'TST2'!F34+MKT!F34+SYShin!F34+JGChoi!F34 -> 0 | G34: ='TST1'!G34+'TST2'!G34+MKT!G34+SYShin!G34+JGChoi!G34 -> 0 | H34: ='TST1'!H34+'TST2'!H34+MKT!H34+SYShin!H34+JGChoi!H34 -> 0 | I34: =SUM(F34:H34) -> 0 | J34: ='TST1'!J34+'TST2'!J34+MKT!J34+SYShin!J34+JGChoi!J34 -> 0 | K34: ='TST1'!K34+'TST2'!K34+MKT!K34+SYShin!K34+JGChoi!K34 -> 0 | L34: ='TST1'!L34+'TST2'!L34+MKT!L34+SYShin!L34+JGChoi!L34 -> 0 | M34: =SUM(J34:L34) -> 0 | N34: ='TST1'!N34+'TST2'!N34+MKT!N34+SYShin!N34+JGChoi!N34 -> 0 | O34: ='TST1'!O34+'TST2'!O34+MKT!O34+SYShin!O34+JGChoi!O34 -> 0 | P34: ='TST1'!P34+'TST2'!P34+MKT!P34+SYShin!P34+JGChoi!P34 -> 0 | Q34: =SUM(N34:P34) -> 0 | R34: ='TST1'!R34+'TST2'!R34+MKT!R34+SYShin!R34+JGChoi!R34 -> 0 | S34: ='TST1'!S34+'TST2'!S34+MKT!S34+SYShin!S34+JGChoi!S34 -> 0 | T34: ='TST1'!T34+'TST2'!T34+MKT!T34+SYShin!T34+JGChoi!T34 -> 0 | U34: =SUM(R34:T34) -> 0 | V34: =I34+M34+Q34+U34 -> 0
D35: 기타-연차 | E35: 0 | F35: ='TST1'!F35+'TST2'!F35+MKT!F35+SYShin!F35+JGChoi!F35 -> 0 | G35: ='TST1'!G35+'TST2'!G35+MKT!G35+SYShin!G35+JGChoi!G35 -> 0 | H35: ='TST1'!H35+'TST2'!H35+MKT!H35+SYShin!H35+JGChoi!H35 -> 0 | I35: =SUM(F35:H35) -> 0 | J35: ='TST1'!J35+'TST2'!J35+MKT!J35+SYShin!J35+JGChoi!J35 -> 0 | K35: ='TST1'!K35+'TST2'!K35+MKT!K35+SYShin!K35+JGChoi!K35 -> 0 | L35: ='TST1'!L35+'TST2'!L35+MKT!L35+SYShin!L35+JGChoi!L35 -> 0 | M35: =SUM(J35:L35) -> 0 | N35: ='TST1'!N35+'TST2'!N35+MKT!N35+SYShin!N35+JGChoi!N35 -> 0 | O35: ='TST1'!O35+'TST2'!O35+MKT!O35+SYShin!O35+JGChoi!O35 -> 0 | P35: ='TST1'!P35+'TST2'!P35+MKT!P35+SYShin!P35+JGChoi!P35 -> 0 | Q35: =SUM(N35:P35) -> 0 | R35: ='TST1'!R35+'TST2'!R35+MKT!R35+SYShin!R35+JGChoi!R35 -> 0 | S35: ='TST1'!S35+'TST2'!S35+MKT!S35+SYShin!S35+JGChoi!S35 -> 0 | T35: ='TST1'!T35+'TST2'!T35+MKT!T35+SYShin!T35+JGChoi!T35 -> 0 | U35: =SUM(R35:T35) -> 0 | V35: =I35+M35+Q35+U35 -> 0
D36: 퇴직급여 | E36: 0 | F36: ='TST1'!F36+'TST2'!F36+MKT!F36+SYShin!F36+JGChoi!F36 -> 7000000 | G36: ='TST1'!G36+'TST2'!G36+MKT!G36+SYShin!G36+JGChoi!G36 -> 7000000 | H36: ='TST1'!H36+'TST2'!H36+MKT!H36+SYShin!H36+JGChoi!H36 -> 7000000 | I36: =SUM(F36:H36) -> 21000000 | J36: ='TST1'!J36+'TST2'!J36+MKT!J36+SYShin!J36+JGChoi!J36 -> 7000000 | K36: ='TST1'!K36+'TST2'!K36+MKT!K36+SYShin!K36+JGChoi!K36 -> 7000000 | L36: ='TST1'!L36+'TST2'!L36+MKT!L36+SYShin!L36+JGChoi!L36 -> 7000000 | M36: =SUM(J36:L36) -> 21000000 | N36: ='TST1'!N36+'TST2'!N36+MKT!N36+SYShin!N36+JGChoi!N36 -> 7000000 | O36: ='TST1'!O36+'TST2'!O36+MKT!O36+SYShin!O36+JGChoi!O36 -> 7000000 | P36: ='TST1'!P36+'TST2'!P36+MKT!P36+SYShin!P36+JGChoi!P36 -> 7000000 | Q36: =SUM(N36:P36) -> 21000000 | R36: ='TST1'!R36+'TST2'!R36+MKT!R36+SYShin!R36+JGChoi!R36 -> 7000000 | S36: ='TST1'!S36+'TST2'!S36+MKT!S36+SYShin!S36+JGChoi!S36 -> 7000000 | T36: ='TST1'!T36+'TST2'!T36+MKT!T36+SYShin!T36+JGChoi!T36 -> 7000000 | U36: =SUM(R36:T36) -> 21000000 | V36: =I36+M36+Q36+U36 -> 84000000
B37: Total Salary & Wages | F37: =SUM(F33:F36) -> 65000000 | G37: =SUM(G33:G36) -> 65000000 | H37: =SUM(H33:H36) -> 65000000 | I37: =SUM(I33:I36) -> 195000000 | J37: =SUM(J33:J36) -> 65000000 | K37: =SUM(K33:K36) -> 65000000 | L37: =SUM(L33:L36) -> 65000000 | M37: =SUM(M33:M36) -> 195000000 | ... U37: =SUM(U33:U36) -> 195000000 | V37: =I37+M37+Q37+U37 -> 780000000
C38: Benefits
D39: 국민연금 | E39: 0 | F39: ='TST1'!F39+'TST2'!F39+MKT!F39+SYShin!F39+JGChoi!F39 -> 2100000 | G39: ='TST1'!G39+'TST2'!G39+MKT!G39+SYShin!G39+JGChoi!G39 -> 2100000 | H39: ='TST1'!H39+'TST2'!H39+MKT!H39+SYShin!H39+JGChoi!H39 -> 2100000 | I39: =SUM(F39:H39) -> 6300000 | J39: ='TST1'!J39+'TST2'!J39+MKT!J39+SYShin!J39+JGChoi!J39 -> 2100000 | K39: ='TST1'!K39+'TST2'!K39+MKT!K39+SYShin!K39+JGChoi!K39 -> 2100000 | L39: ='TST1'!L39+'TST2'!L39+MKT!L39+SYShin!L39+JGChoi!L39 -> 2100000 | M39: =SUM(J39:L39) -> 6300000 | N39: ='TST1'!N39+'TST2'!N39+MKT!N39+SYShin!N39+JGChoi!N39 -> 2100000 | O39: ='TST1'!O39+'TST2'!O39+MKT!O39+SYShin!O39+JGChoi!O39 -> 2100000 | P39: ='TST1'!P39+'TST2'!P39+MKT!P39+SYShin!P39+JGChoi!P39 -> 2100000 | Q39: =SUM(N39:P39) -> 6300000 | R39: ='TST1'!R39+'TST2'!R39+MKT!R39+SYShin!R39+JGChoi!R39 -> 2100000 | S39: ='TST1'!S39+'TST2'!S39+MKT!S39+SYShin!S39+JGChoi!S39 -> 2100000 | T39: ='TST1'!T39+'TST2'!T39+MKT!T39+SYShin!T39+JGChoi!T39 -> 2100000 | U39: =SUM(R39:T39) -> 6300000 | V39: =I39+M39+Q39+U39 -> 25200000
D40: 건강보험 | E40: 0 | F40: ='TST1'!F40+'TST2'!F40+MKT!F40+SYShin!F40+JGChoi!F40 -> 2300000 | G40: ='TST1'!G40+'TST2'!G40+MKT!G40+SYShin!G40+JGChoi!G40 -> 2300000 | H40: ='TST1'!H40+'TST2'!H40+MKT!H40+SYShin!H40+JGChoi!H40 -> 2300000 | I40: =SUM(F40:H40) -> 6900000 | J40: ='TST1'!J40+'TST2'!J40+MKT!J40+SYShin!J40+JGChoi!J40 -> 2300000 | K40: ='TST1'!K40+'TST2'!K40+MKT!K40+SYShin!K40+JGChoi!K40 -> 2300000 | L40: ='TST1'!L40+'TST2'!L40+MKT!L40+SYShin!L40+JGChoi!L40 -> 2300000 | M40: =SUM(J40:L40) -> 6900000 | N40: ='TST1'!N40+'TST2'!N40+MKT!N40+SYShin!N40+JGChoi!N40 -> 2300000 | O40: ='TST1'!O40+'TST2'!O40+MKT!O40+SYShin!O40+JGChoi!O40 -> 2300000 | P40: ='TST1'!P40+'TST2'!P40+MKT!P40+SYShin!P40+JGChoi!P40 -> 2300000 | Q40: =SUM(N40:P40) -> 6900000 | R40: ='TST1'!R40+'TST2'!R40+MKT!R40+SYShin!R40+JGChoi!R40 -> 2300000 | S40: ='TST1'!S40+'TST2'!S40+MKT!S40+SYShin!S40+JGChoi!S40 -> 2300000 | T40: ='TST1'!T40+'TST2'!T40+MKT!T40+SYShin!T40+JGChoi!T40 -> 2300000 | U40: =SUM(R40:T40) -> 6900000 | V40: =I40+M40+Q40+U40 -> 27600000
D41: 고용보험 | E41: 0 | F41: ='TST1'!F41+'TST2'!F41+MKT!F41+SYShin!F41+JGChoi!F41 -> 750000 | G41: ='TST1'!G41+'TST2'!G41+MKT!G41+SYShin!G41+JGChoi!G41 -> 750000 | H41: ='TST1'!H41+'TST2'!H41+MKT!H41+SYShin!H41+JGChoi!H41 -> 750000 | I41: =SUM(F41:H41) -> 2250000 | J41: ='TST1'!J41+'TST2'!J41+MKT!J41+SYShin!J41+JGChoi!J41 -> 750000 | K41: ='TST1'!K41+'TST2'!K41+MKT!K41+SYShin!K41+JGChoi!K41 -> 750000 | L41: ='TST1'!L41+'TST2'!L41+MKT!L41+SYShin!L41+JGChoi!L41 -> 750000 | M41: =SUM(J41:L41) -> 2250000 | N41: ='TST1'!N41+'TST2'!N41+MKT!N41+SYShin!N41+JGChoi!N41 -> 750000 | O41: ='TST1'!O41+'TST2'!O41+MKT!O41+SYShin!O41+JGChoi!O41 -> 750000 | P41: ='TST1'!P41+'TST2'!P41+MKT!P41+SYShin!P41+JGChoi!P41 -> 750000 | Q41: =SUM(N41:P41) -> 2250000 | R41: ='TST1'!R41+'TST2'!R41+MKT!R41+SYShin!R41+JGChoi!R41 -> 750000 | S41: ='TST1'!S41+'TST2'!S41+MKT!S41+SYShin!S41+JGChoi!S41 -> 750000 | T41: ='TST1'!T41+'TST2'!T41+MKT!T41+SYShin!T41+JGChoi!T41 -> 750000 | U41: =SUM(R41:T41) -> 2250000 | V41: =I41+M41+Q41+U41 -> 9000000
D42: 산재보험 | E42: 0 | F42: ='TST1'!F42+'TST2'!F42+MKT!F42+SYShin!F42+JGChoi!F42 -> 358000 | G42: ='TST1'!G42+'TST2'!G42+MKT!G42+SYShin!G42+JGChoi!G42 -> 358000 | H42: ='TST1'!H42+'TST2'!H42+MKT!H42+SYShin!H42+JGChoi!H42 -> 358000 | I42: =SUM(F42:H42) -> 1074000 | J42: ='TST1'!J42+'TST2'!J42+MKT!J42+SYShin!J42+JGChoi!J42 -> 358000 | K42: ='TST1'!K42+'TST2'!K42+MKT!K42+SYShin!K42+JGChoi!K42 -> 358000 | L42: ='TST1'!L42+'TST2'!L42+MKT!L42+SYShin!L42+JGChoi!L42 -> 358000 | M42: =SUM(J42:L42) -> 1074000 | N42: ='TST1'!N42+'TST2'!N42+MKT!N42+SYShin!N42+JGChoi!N42 -> 358000 | O42: ='TST1'!O42+'TST2'!O42+MKT!O42+SYShin!O42+JGChoi!O42 -> 358000 | P42: ='TST1'!P42+'TST2'!P42+MKT!P42+SYShin!P42+JGChoi!P42 -> 358000 | Q42: =SUM(N42:P42) -> 1074000 | R42: ='TST1'!R42+'TST2'!R42+MKT!R42+SYShin!R42+JGChoi!R42 -> 358000 | S42: ='TST1'!S42+'TST2'!S42+MKT!S42+SYShin!S42+JGChoi!S42 -> 358000 | T42: ='TST1'!T42+'TST2'!T42+MKT!T42+SYShin!T42+JGChoi!T42 -> 358000 | U42: =SUM(R42:T42) -> 1074000 | V42: =I42+M42+Q42+U42 -> 4296000
D43: 야근식대 | E43: 0 | F43: ='TST1'!F43+'TST2'!F43+MKT!F43+SYShin!F43+JGChoi!F43 -> 162000 | G43: ='TST1'!G43+'TST2'!G43+MKT!G43+SYShin!G43+JGChoi!G43 -> 162000 | H43: ='TST1'!H43+'TST2'!H43+MKT!H43+SYShin!H43+JGChoi!H43 -> 162000 | I43: =SUM(F43:H43) -> 486000 | J43: ='TST1'!J43+'TST2'!J43+MKT!J43+SYShin!J43+JGChoi!J43 -> 162000 | K43: ='TST1'!K43+'TST2'!K43+MKT!K43+SYShin!K43+JGChoi!K43 -> 162000 | L43: ='TST1'!L43+'TST2'!L43+MKT!L43+SYShin!L43+JGChoi!L43 -> 162000 | M43: =SUM(J43:L43) -> 486000 | N43: ='TST1'!N43+'TST2'!N43+MKT!N43+SYShin!N43+JGChoi!N43 -> 162000 | O43: ='TST1'!O43+'TST2'!O43+MKT!O43+SYShin!O43+JGChoi!O43 -> 162000 | P43: ='TST1'!P43+'TST2'!P43+MKT!P43+SYShin!P43+JGChoi!P43 -> 162000 | Q43: =SUM(N43:P43) -> 486000 | R43: ='TST1'!R43+'TST2'!R43+MKT!R43+SYShin!R43+JGChoi!R43 -> 162000 | S43: ='TST1'!S43+'TST2'!S43+MKT!S43+SYShin!S43+JGChoi!S43 -> 162000 | T43: ='TST1'!T43+'TST2'!T43+MKT!T43+SYShin!T43+JGChoi!T43 -> 162000 | U43: =SUM(R43:T43) -> 486000 | V43: =I43+M43+Q43+U43 -> 1944000
D44: 회식대 | F44: ='TST1'!F44+'TST2'!F44+MKT!F44+SYShin!F44+JGChoi!F44 -> 227000 | G44: ='TST1'!G44+'TST2'!G44+MKT!G44+SYShin!G44+JGChoi!G44 -> 437000 | H44: ='TST1'!H44+'TST2'!H44+MKT!H44+SYShin!H44+JGChoi!H44 -> 437000 | I44: =SUM(F44:H44) -> 1101000 | J44: ='TST1'!J44+'TST2'!J44+MKT!J44+SYShin!J44+JGChoi!J44 -> 437000 | K44: ='TST1'!K44+'TST2'!K44+MKT!K44+SYShin!K44+JGChoi!K44 -> 437000 | L44: ='TST1'!L44+'TST2'!L44+MKT!L44+SYShin!L44+JGChoi!L44 -> 437000 | M44: =SUM(J44:L44) -> 1311000 | N44: ='TST1'!N44+'TST2'!N44+MKT!N44+SYShin!N44+JGChoi!N44 -> 437000 | O44: ='TST1'!O44+'TST2'!O44+MKT!O44+SYShin!O44+JGChoi!O44 -> 437000 | P44: ='TST1'!P44+'TST2'!P44+MKT!P44+SYShin!P44+JGChoi!P44 -> 437000 | Q44: =SUM(N44:P44) -> 1311000 | R44: ='TST1'!R44+'TST2'!R44+MKT!R44+SYShin!R44+JGChoi!R44 -> 437000 | S44: ='TST1'!S44+'TST2'!S44+MKT!S44+SYShin!S44+JGChoi!S44 -> 437000 | T44: ='TST1'!T44+'TST2'!T44+MKT!T44+SYShin!T44+JGChoi!T44 -> 437000 | U44: =SUM(R44:T44) -> 1311000 | V44: =I44+M44+Q44+U44 -> 5034000
D45: 경조사 | E45: 0 | F45: ='TST1'!F45+'TST2'!F45+MKT!F45+SYShin!F45+JGChoi!F45 -> 100000 | G45: ='TST1'!G45+'TST2'!G45+MKT!G45+SYShin!G45+JGChoi!G45 -> 100000 | H45: ='TST1'!H45+'TST2'!H45+MKT!H45+SYShin!H45+JGChoi!H45 -> 100000 | I45: =SUM(F45:H45) -> 300000 | J45: ='TST1'!J45+'TST2'!J45+MKT!J45+SYShin!J45+JGChoi!J45 -> 100000 | K45: ='TST1'!K45+'TST2'!K45+MKT!K45+SYShin!K45+JGChoi!K45 -> 100000 | L45: ='TST1'!L45+'TST2'!L45+MKT!L45+SYShin!L45+JGChoi!L45 -> 100000 | M45: =SUM(J45:L45) -> 300000 | N45: ='TST1'!N45+'TST2'!N45+MKT!N45+SYShin!N45+JGChoi!N45 -> 100000 | O45: ='TST1'!O45+'TST2'!O45+MKT!O45+SYShin!O45+JGChoi!O45 -> 100000 | P45: ='TST1'!P45+'TST2'!P45+MKT!P45+SYShin!P45+JGChoi!P45 -> 100000 | Q45: =SUM(N45:P45) -> 300000 | R45: ='TST1'!R45+'TST2'!R45+MKT!R45+SYShin!R45+JGChoi!R45 -> 100000 | S45: ='TST1'!S45+'TST2'!S45+MKT!S45+SYShin!S45+JGChoi!S45 -> 100000 | T45: ='TST1'!T45+'TST2'!T45+MKT!T45+SYShin!T45+JGChoi!T45 -> 100000 | U45: =SUM(R45:T45) -> 300000 | V45: =I45+M45+Q45+U45 -> 1200000
D46: 교육지원비 | E46: 0 | F46: ='TST1'!F46+'TST2'!F46+MKT!F46+SYShin!F46+JGChoi!F46 -> 0 | G46: ='TST1'!G46+'TST2'!G46+MKT!G46+SYShin!G46+JGChoi!G46 -> 0 | H46: ='TST1'!H46+'TST2'!H46+MKT!H46+SYShin!H46+JGChoi!H46 -> 0 | I46: =SUM(F46:H46) -> 0 | J46: ='TST1'!J46+'TST2'!J46+MKT!J46+SYShin!J46+JGChoi!J46 -> 0 | K46: ='TST1'!K46+'TST2'!K46+MKT!K46+SYShin!K46+JGChoi!K46 -> 0 | L46: ='TST1'!L46+'TST2'!L46+MKT!L46+SYShin!L46+JGChoi!L46 -> 0 | M46: =SUM(J46:L46) -> 0 | N46: ='TST1'!N46+'TST2'!N46+MKT!N46+SYShin!N46+JGChoi!N46 -> 0 | O46: ='TST1'!O46+'TST2'!O46+MKT!O46+SYShin!O46+JGChoi!O46 -> 0 | P46: ='TST1'!P46+'TST2'!P46+MKT!P46+SYShin!P46+JGChoi!P46 -> 0 | Q46: =SUM(N46:P46) -> 0 | R46: ='TST1'!R46+'TST2'!R46+MKT!R46+SYShin!R46+JGChoi!R46 -> 0 | S46: ='TST1'!S46+'TST2'!S46+MKT!S46+SYShin!S46+JGChoi!S46 -> 0 | T46: ='TST1'!T46+'TST2'!T46+MKT!T46+SYShin!T46+JGChoi!T46 -> 0 | U46: =SUM(R46:T46) -> 0 | V46: =I46+M46+Q46+U46 -> 0
D47: 직원상해보험 | E47: 0 | F47: ='TST1'!F47+'TST2'!F47+MKT!F47+SYShin!F47+JGChoi!F47 -> 0 | G47: ='TST1'!G47+'TST2'!G47+MKT!G47+SYShin!G47+JGChoi!G47 -> 0 | H47: ='TST1'!H47+'TST2'!H47+MKT!H47+SYShin!H47+JGChoi!H47 -> 0 | I47: =SUM(F47:H47) -> 0 | J47: ='TST1'!J47+'TST2'!J47+MKT!J47+SYShin!J47+JGChoi!J47 -> 0 | K47: ='TST1'!K47+'TST2'!K47+MKT!K47+SYShin!K47+JGChoi!K47 -> 0 | L47: ='TST1'!L47+'TST2'!L47+MKT!L47+SYShin!L47+JGChoi!L47 -> 0 | M47: =SUM(J47:L47) -> 0 | N47: ='TST1'!N47+'TST2'!N47+MKT!N47+SYShin!N47+JGChoi!N47 -> 0 | O47: ='TST1'!O47+'TST2'!O47+MKT!O47+SYShin!O47+JGChoi!O47 -> 0 | P47: ='TST1'!P47+'TST2'!P47+MKT!P47+SYShin!P47+JGChoi!P47 -> 0 | Q47: =SUM(N47:P47) -> 0 | R47: ='TST1'!R47+'TST2'!R47+MKT!R47+SYShin!R47+JGChoi!R47 -> 0 | S47: ='TST1'!S47+'TST2'!S47+MKT!S47+SYShin!S47+JGChoi!S47 -> 0 | T47: ='TST1'!T47+'TST2'!T47+MKT!T47+SYShin!T47+JGChoi!T47 -> 0 | U47: =SUM(R47:T47) -> 0 | V47: =I47+M47+Q47+U47 -> 0
D48: 건강검진 | E48: 0 | F48: ='TST1'!F48+'TST2'!F48+MKT!F48+SYShin!F48+JGChoi!F48 -> 0 | G48: ='TST1'!G48+'TST2'!G48+MKT!G48+SYShin!G48+JGChoi!G48 -> 0 | H48: ='TST1'!H48+'TST2'!H48+MKT!H48+SYShin!H48+JGChoi!H48 -> 0 | I48: =SUM(F48:H48) -> 0 | J48: ='TST1'!J48+'TST2'!J48+MKT!J48+SYShin!J48+JGChoi!J48 -> 0 | K48: ='TST1'!K48+'TST2'!K48+MKT!K48+SYShin!K48+JGChoi!K48 -> 0 | L48: ='TST1'!L48+'TST2'!L48+MKT!L48+SYShin!L48+JGChoi!L48 -> 0 | M48: =SUM(J48:L48) -> 0 | N48: ='TST1'!N48+'TST2'!N48+MKT!N48+SYShin!N48+JGChoi!N48 -> 0 | O48: ='TST1'!O48+'TST2'!O48+MKT!O48+SYShin!O48+JGChoi!O48 -> 0 | P48: ='TST1'!P48+'TST2'!P48+MKT!P48+SYShin!P48+JGChoi!P48 -> 0 | Q48: =SUM(N48:P48) -> 0 | R48: ='TST1'!R48+'TST2'!R48+MKT!R48+SYShin!R48+JGChoi!R48 -> 0 | S48: ='TST1'!S48+'TST2'!S48+MKT!S48+SYShin!S48+JGChoi!S48 -> 0 | T48: ='TST1'!T48+'TST2'!T48+MKT!T48+SYShin!T48+JGChoi!T48 -> 0 | U48: =SUM(R48:T48) -> 0 | V48: =I48+M48+Q48+U48 -> 0
D49: 통신비(핸드폰) | F49: ='TST1'!F49+'TST2'!F49+MKT!F49+SYShin!F49+JGChoi!F49 -> 545000 | G49: ='TST1'!G49+'TST2'!G49+MKT!G49+SYShin!G49+JGChoi!G49 -> 545000 | H49: ='TST1'!H49+'TST2'!H49+MKT!H49+SYShin!H49+JGChoi!H49 -> 545000 | I49: =SUM(F49:H49) -> 1635000 | J49: ='TST1'!J49+'TST2'!J49+MKT!J49+SYShin!J49+JGChoi!J49 -> 545000 | K49: ='TST1'!K49+'TST2'!K49+MKT!K49+SYShin!K49+JGChoi!K49 -> 545000 | L49: ='TST1'!L49+'TST2'!L49+MKT!L49+SYShin!L49+JGChoi!L49 -> 545000 | M49: =SUM(J49:L49) -> 1635000 | N49: ='TST1'!N49+'TST2'!N49+MKT!N49+SYShin!N49+JGChoi!N49 -> 545000 | O49: ='TST1'!O49+'TST2'!O49+MKT!O49+SYShin!O49+JGChoi!O49 -> 545000 | P49: ='TST1'!P49+'TST2'!P49+MKT!P49+SYShin!P49+JGChoi!P49 -> 545000 | Q49: =SUM(N49:P49) -> 1635000 | R49: ='TST1'!R49+'TST2'!R49+MKT!R49+SYShin!R49+JGChoi!R49 -> 545000 | S49: ='TST1'!S49+'TST2'!S49+MKT!S49+SYShin!S49+JGChoi!S49 -> 545000 | T49: ='TST1'!T49+'TST2'!T49+MKT!T49+SYShin!T49+JGChoi!T49 -> 545000 | U49: =SUM(R49:T49) -> 1635000 | V49: =I49+M49+Q49+U49 -> 6540000
D50: 체력단련비 | F50: ='TST1'!F50+'TST2'!F50+MKT!F50+SYShin!F50+JGChoi!F50 -> 188000 | G50: ='TST1'!G50+'TST2'!G50+MKT!G50+SYShin!G50+JGChoi!G50 -> 188000 | H50: ='TST1'!H50+'TST2'!H50+MKT!H50+SYShin!H50+JGChoi!H50 -> 188000 | I50: =SUM(F50:H50) -> 564000 | J50: ='TST1'!J50+'TST2'!J50+MKT!J50+SYShin!J50+JGChoi!J50 -> 188000 | K50: ='TST1'!K50+'TST2'!K50+MKT!K50+SYShin!K50+JGChoi!K50 -> 188000 | L50: ='TST1'!L50+'TST2'!L50+MKT!L50+SYShin!L50+JGChoi!L50 -> 188000 | M50: =SUM(J50:L50) -> 564000 | N50: ='TST1'!N50+'TST2'!N50+MKT!N50+SYShin!N50+JGChoi!N50 -> 188000 | O50: ='TST1'!O50+'TST2'!O50+MKT!O50+SYShin!O50+JGChoi!O50 -> 188000 | P50: ='TST1'!P50+'TST2'!P50+MKT!P50+SYShin!P50+JGChoi!P50 -> 188000 | Q50: =SUM(N50:P50) -> 564000 | R50: ='TST1'!R50+'TST2'!R50+MKT!R50+SYShin!R50+JGChoi!R50 -> 188000 | S50: ='TST1'!S50+'TST2'!S50+MKT!S50+SYShin!S50+JGChoi!S50 -> 188000 | T50: ='TST1'!T50+'TST2'!T50+MKT!T50+SYShin!T50+JGChoi!T50 -> 188000 | U50: =SUM(R50:T50) -> 564000 | V50: =I50+M50+Q50+U50 -> 2256000
B51: Total Benefits | F51: =SUM(F39:F50) -> 6730000 | G51: =SUM(G39:G50) -> 6940000 | H51: =SUM(H39:H50) -> 6940000 | I51: =SUM(I39:I50) -> 20610000 | J51: =SUM(J39:J50) -> 6940000 | K51: =SUM(K39:K50) -> 6940000 | L51: =SUM(L39:L50) -> 6940000 | M51: =SUM(M39:M50) -> 20820000 | ... U51: =SUM(U39:U50) -> 20820000 | V51: =I51+M51+Q51+U51 -> 83070000
B52: Total Compensation & Benefits | F52: =F37+F51 -> 71730000 | G52: =G37+G51 -> 71940000 | H52: =H37+H51 -> 71940000 | I52: =I51+I37 -> 215610000 | J52: =J37+J51 -> 71940000 | K52: =K37+K51 -> 71940000 | L52: =L37+L51 -> 71940000 | M52: =M51+M37 -> 215820000 | N52: =N37+N51 -> 71940000 | O52: =O37+O51 -> 71940000 | P52: =P37+P51 -> 71940000 | Q52: =Q51+Q37 -> 215820000 | R52: =R37+R51 -> 71940000 | S52: =S37+S51 -> 71940000 | T52: =T37+T51 -> 71940000 | U52: =U51+U37 -> 215820000 | V52: =I52+M52+Q52+U52 -> 863070000
B53: Unfunded Consulting Expenses | E53: 0 | F53: 0 | G53: 0 | H53: 0 | I53: 0 | J53: 0 | K53: 0 | L53: 0 | M53: 0 | N53: 0 | O53: 0 | P53: 0 | Q53: 0 | R53: 0 | S53: 0 | T53: 0 | U53: 0 | V53: =I53+M53+Q53+U53 -> 0
B54: Travel & Entertainment
C55: 여비교통비(출장일비) | E55: 0 | F55: ='TST1'!F55+'TST2'!F55+MKT!F55+SYShin!F55+JGChoi!F55 -> 0 | G55: ='TST1'!G55+'TST2'!G55+MKT!G55+SYShin!G55+JGChoi!G55 -> 0 | H55: ='TST1'!H55+'TST2'!H55+MKT!H55+SYShin!H55+JGChoi!H55 -> 0 | I55: =SUM(F55:H55) -> 0 | J55: ='TST1'!J55+'TST2'!J55+MKT!J55+SYShin!J55+JGChoi!J55 -> 0 | K55: ='TST1'!K55+'TST2'!K55+MKT!K55+SYShin!K55+JGChoi!K55 -> 0 | L55: ='TST1'!L55+'TST2'!L55+MKT!L55+SYShin!L55+JGChoi!L55 -> 0 | M55: =SUM(J55:L55) -> 0 | N55: ='TST1'!N55+'TST2'!N55+MKT!N55+SYShin!N55+JGChoi!N55 -> 0 | O55: ='TST1'!O55+'TST2'!O55+MKT!O55+SYShin!O55+JGChoi!O55 -> 0 | P55: ='TST1'!P55+'TST2'!P55+MKT!P55+SYShin!P55+JGChoi!P55 -> 0 | Q55: =SUM(N55:P55) -> 0 | R55: ='TST1'!R55+'TST2'!R55+MKT!R55+SYShin!R55+JGChoi!R55 -> 0 | S55: ='TST1'!S55+'TST2'!S55+MKT!S55+SYShin!S55+JGChoi!S55 -> 0 | T55: ='TST1'!T55+'TST2'!T55+MKT!T55+SYShin!T55+JGChoi!T55 -> 0 | U55: =SUM(R55:T55) -> 0 | V55: =I55+M55+Q55+U55 -> 0
C56: 여비교통비(출장식대) | F56: ='TST1'!F56+'TST2'!F56+MKT!F56+SYShin!F56+JGChoi!F56 -> 697000 | G56: ='TST1'!G56+'TST2'!G56+MKT!G56+SYShin!G56+JGChoi!G56 -> 697000 | H56: ='TST1'!H56+'TST2'!H56+MKT!H56+SYShin!H56+JGChoi!H56 -> 697000 | I56: =SUM(F56:H56) -> 2091000 | J56: ='TST1'!J56+'TST2'!J56+MKT!J56+SYShin!J56+JGChoi!J56 -> 697000 | K56: ='TST1'!K56+'TST2'!K56+MKT!K56+SYShin!K56+JGChoi!K56 -> 697000 | L56: ='TST1'!L56+'TST2'!L56+MKT!L56+SYShin!L56+JGChoi!L56 -> 697000 | M56: =SUM(J56:L56) -> 2091000 | N56: ='TST1'!N56+'TST2'!N56+MKT!N56+SYShin!N56+JGChoi!N56 -> 697000 | O56: ='TST1'!O56+'TST2'!O56+MKT!O56+SYShin!O56+JGChoi!O56 -> 697000 | P56: ='TST1'!P56+'TST2'!P56+MKT!P56+SYShin!P56+JGChoi!P56 -> 697000 | Q56: =SUM(N56:P56) -> 2091000 | R56: ='TST1'!R56+'TST2'!R56+MKT!R56+SYShin!R56+JGChoi!R56 -> 697000 | S56: ='TST1'!S56+'TST2'!S56+MKT!S56+SYShin!S56+JGChoi!S56 -> 697000 | T56: ='TST1'!T56+'TST2'!T56+MKT!T56+SYShin!T56+JGChoi!T56 -> 697000 | U56: =SUM(R56:T56) -> 2091000 | V56: =I56+M56+Q56+U56 -> 8364000
C57: 여비교통비(통행,주차) | F57: ='TST1'!F57+'TST2'!F57+MKT!F57+SYShin!F57+JGChoi!F57 -> 343000 | G57: ='TST1'!G57+'TST2'!G57+MKT!G57+SYShin!G57+JGChoi!G57 -> 343000 | H57: ='TST1'!H57+'TST2'!H57+MKT!H57+SYShin!H57+JGChoi!H57 -> 343000 | I57: =SUM(F57:H57) -> 1029000 | J57: ='TST1'!J57+'TST2'!J57+MKT!J57+SYShin!J57+JGChoi!J57 -> 343000 | K57: ='TST1'!K57+'TST2'!K57+MKT!K57+SYShin!K57+JGChoi!K57 -> 343000 | L57: ='TST1'!L57+'TST2'!L57+MKT!L57+SYShin!L57+JGChoi!L57 -> 343000 | M57: =SUM(J57:L57) -> 1029000 | N57: ='TST1'!N57+'TST2'!N57+MKT!N57+SYShin!N57+JGChoi!N57 -> 343000 | O57: ='TST1'!O57+'TST2'!O57+MKT!O57+SYShin!O57+JGChoi!O57 -> 343000 | P57: ='TST1'!P57+'TST2'!P57+MKT!P57+SYShin!P57+JGChoi!P57 -> 343000 | Q57: =SUM(N57:P57) -> 1029000 | R57: ='TST1'!R57+'TST2'!R57+MKT!R57+SYShin!R57+JGChoi!R57 -> 343000 | S57: ='TST1'!S57+'TST2'!S57+MKT!S57+SYShin!S57+JGChoi!S57 -> 343000 | T57: ='TST1'!T57+'TST2'!T57+MKT!T57+SYShin!T57+JGChoi!T57 -> 343000 | U57: =SUM(R57:T57) -> 1029000 | V57: =I57+M57+Q57+U57 -> 4116000
C58: 여비교통비(항공,고속버스등) | F58: ='TST1'!F58+'TST2'!F58+MKT!F58+SYShin!F58+JGChoi!F58 -> 1359000 | G58: ='TST1'!G58+'TST2'!G58+MKT!G58+SYShin!G58+JGChoi!G58 -> 1359000 | H58: ='TST1'!H58+'TST2'!H58+MKT!H58+SYShin!H58+JGChoi!H58 -> 1359000 | I58: =SUM(F58:H58) -> 4077000 | J58: ='TST1'!J58+'TST2'!J58+MKT!J58+SYShin!J58+JGChoi!J58 -> 1359000 | K58: ='TST1'!K58+'TST2'!K58+MKT!K58+SYShin!K58+JGChoi!K58 -> 1359000 | L58: ='TST1'!L58+'TST2'!L58+MKT!L58+SYShin!L58+JGChoi!L58 -> 1359000 | M58: =SUM(J58:L58) -> 4077000 | N58: ='TST1'!N58+'TST2'!N58+MKT!N58+SYShin!N58+JGChoi!N58 -> 1359000 | O58: ='TST1'!O58+'TST2'!O58+MKT!O58+SYShin!O58+JGChoi!O58 -> 1359000 | P58: ='TST1'!P58+'TST2'!P58+MKT!P58+SYShin!P58+JGChoi!P58 -> 1359000 | Q58: =SUM(N58:P58) -> 4077000 | R58: ='TST1'!R58+'TST2'!R58+MKT!R58+SYShin!R58+JGChoi!R58 -> 1359000 | S58: ='TST1'!S58+'TST2'!S58+MKT!S58+SYShin!S58+JGChoi!S58 -> 1359000 | T58: ='TST1'!T58+'TST2'!T58+MKT!T58+SYShin!T58+JGChoi!T58 -> 1359000 | U58: =SUM(R58:T58) -> 4077000 | V58: =I58+M58+Q58+U58 -> 16308000
C59: 여비교통비(숙박) | F59: ='TST1'!F59+'TST2'!F59+MKT!F59+SYShin!F59+JGChoi!F59 -> 808000 | G59: ='TST1'!G59+'TST2'!G59+MKT!G59+SYShin!G59+JGChoi!G59 -> 808000 | H59: ='TST1'!H59+'TST2'!H59+MKT!H59+SYShin!H59+JGChoi!H59 -> 808000 | I59: =SUM(F59:H59) -> 2424000 | J59: ='TST1'!J59+'TST2'!J59+MKT!J59+SYShin!J59+JGChoi!J59 -> 808000 | K59: ='TST1'!K59+'TST2'!K59+MKT!K59+SYShin!K59+JGChoi!K59 -> 808000 | L59: ='TST1'!L59+'TST2'!L59+MKT!L59+SYShin!L59+JGChoi!L59 -> 808000 | M59: =SUM(J59:L59) -> 2424000 | N59: ='TST1'!N59+'TST2'!N59+MKT!N59+SYShin!N59+JGChoi!N59 -> 808000 | O59: ='TST1'!O59+'TST2'!O59+MKT!O59+SYShin!O59+JGChoi!O59 -> 808000 | P59: ='TST1'!P59+'TST2'!P59+MKT!P59+SYShin!P59+JGChoi!P59 -> 808000 | Q59: =SUM(N59:P59) -> 2424000 | R59: ='TST1'!R59+'TST2'!R59+MKT!R59+SYShin!R59+JGChoi!R59 -> 808000 | S59: ='TST1'!S59+'TST2'!S59+MKT!S59+SYShin!S59+JGChoi!S59 -> 808000 | T59: ='TST1'!T59+'TST2'!T59+MKT!T59+SYShin!T59+JGChoi!T59 -> 808000 | U59: =SUM(R59:T59) -> 2424000 | V59: =I59+M59+Q59+U59 -> 9696000
C60: 여비교통비(차량지원) | F60: ='TST1'!F60+'TST2'!F60+MKT!F60+SYShin!F60+JGChoi!F60 -> 1398000 | G60: ='TST1'!G60+'TST2'!G60+MKT!G60+SYShin!G60+JGChoi!G60 -> 1398000 | H60: ='TST1'!H60+'TST2'!H60+MKT!H60+SYShin!H60+JGChoi!H60 -> 1398000 | I60: =SUM(F60:H60) -> 4194000 | J60: ='TST1'!J60+'TST2'!J60+MKT!J60+SYShin!J60+JGChoi!J60 -> 1398000 | K60: ='TST1'!K60+'TST2'!K60+MKT!K60+SYShin!K60+JGChoi!K60 -> 1398000 | L60: ='TST1'!L60+'TST2'!L60+MKT!L60+SYShin!L60+JGChoi!L60 -> 1398000 | M60: =SUM(J60:L60) -> 4194000 | N60: ='TST1'!N60+'TST2'!N60+MKT!N60+SYShin!N60+JGChoi!N60 -> 1398000 | O60: ='TST1'!O60+'TST2'!O60+MKT!O60+SYShin!O60+JGChoi!O60 -> 1398000 | P60: ='TST1'!P60+'TST2'!P60+MKT!P60+SYShin!P60+JGChoi!P60 -> 1398000 | Q60: =SUM(N60:P60) -> 4194000 | R60: ='TST1'!R60+'TST2'!R60+MKT!R60+SYShin!R60+JGChoi!R60 -> 1398000 | S60: ='TST1'!S60+'TST2'!S60+MKT!S60+SYShin!S60+JGChoi!S60 -> 1398000 | T60: ='TST1'!T60+'TST2'!T60+MKT!T60+SYShin!T60+JGChoi!T60 -> 1398000 | U60: =SUM(R60:T60) -> 4194000 | V60: =I60+M60+Q60+U60 -> 16776000
C61: 여비교통비(국책과제_연구활동비) | F61: ='TST1'!F61+'TST2'!F61+MKT!F61+SYShin!F61+JGChoi!F61 -> 0 | G61: ='TST1'!G61+'TST2'!G61+MKT!G61+SYShin!G61+JGChoi!G61 -> 0 | H61: ='TST1'!H61+'TST2'!H61+MKT!H61+SYShin!H61+JGChoi!H61 -> 0 | I61: =SUM(F61:H61) -> 0 | J61: ='TST1'!J61+'TST2'!J61+MKT!J61+SYShin!J61+JGChoi!J61 -> 0 | K61: ='TST1'!K61+'TST2'!K61+MKT!K61+SYShin!K61+JGChoi!K61 -> 0 | L61: ='TST1'!L61+'TST2'!L61+MKT!L61+SYShin!L61+JGChoi!L61 -> 0 | M61: =SUM(J61:L61) -> 0 | N61: ='TST1'!N61+'TST2'!N61+MKT!N61+SYShin!N61+JGChoi!N61 -> 0 | O61: ='TST1'!O61+'TST2'!O61+MKT!O61+SYShin!O61+JGChoi!O61 -> 0 | P61: ='TST1'!P61+'TST2'!P61+MKT!P61+SYShin!P61+JGChoi!P61 -> 0 | Q61: =SUM(N61:P61) -> 0 | R61: ='TST1'!R61+'TST2'!R61+MKT!R61+SYShin!R61+JGChoi!R61 -> 0 | S61: ='TST1'!S61+'TST2'!S61+MKT!S61+SYShin!S61+JGChoi!S61 -> 0 | T61: ='TST1'!T61+'TST2'!T61+MKT!T61+SYShin!T61+JGChoi!T61 -> 0 | U61: =SUM(R61:T61) -> 0 | V61: =I61+M61+Q61+U61 -> 0
C62: 차량유지비 | E62: 0 | F62: ='TST1'!F62+'TST2'!F62+MKT!F62+SYShin!F62+JGChoi!F62 -> 504000 | G62: ='TST1'!G62+'TST2'!G62+MKT!G62+SYShin!G62+JGChoi!G62 -> 504000 | H62: ='TST1'!H62+'TST2'!H62+MKT!H62+SYShin!H62+JGChoi!H62 -> 504000 | I62: =SUM(F62:H62) -> 1512000 | J62: ='TST1'!J62+'TST2'!J62+MKT!J62+SYShin!J62+JGChoi!J62 -> 504000 | K62: ='TST1'!K62+'TST2'!K62+MKT!K62+SYShin!K62+JGChoi!K62 -> 504000 | L62: ='TST1'!L62+'TST2'!L62+MKT!L62+SYShin!L62+JGChoi!L62 -> 504000 | M62: =SUM(J62:L62) -> 1512000 | N62: ='TST1'!N62+'TST2'!N62+MKT!N62+SYShin!N62+JGChoi!N62 -> 504000 | O62: ='TST1'!O62+'TST2'!O62+MKT!O62+SYShin!O62+JGChoi!O62 -> 504000 | P62: ='TST1'!P62+'TST2'!P62+MKT!P62+SYShin!P62+JGChoi!P62 -> 504000 | Q62: =SUM(N62:P62) -> 1512000 | R62: ='TST1'!R62+'TST2'!R62+MKT!R62+SYShin!R62+JGChoi!R62 -> 504000 | S62: ='TST1'!S62+'TST2'!S62+MKT!S62+SYShin!S62+JGChoi!S62 -> 504000 | T62: ='TST1'!T62+'TST2'!T62+MKT!T62+SYShin!T62+JGChoi!T62 -> 504000 | U62: =SUM(R62:T62) -> 1512000 | V62: =I62+M62+Q62+U62 -> 6048000
C63: 해외출장비 | E63: 0 | F63: ='TST1'!F63+'TST2'!F63+MKT!F63+SYShin!F63+JGChoi!F63 -> 1448000 | G63: ='TST1'!G63+'TST2'!G63+MKT!G63+SYShin!G63+JGChoi!G63 -> 1448000 | H63: ='TST1'!H63+'TST2'!H63+MKT!H63+SYShin!H63+JGChoi!H63 -> 1448000 | I63: =SUM(F63:H63) -> 4344000 | J63: ='TST1'!J63+'TST2'!J63+MKT!J63+SYShin!J63+JGChoi!J63 -> 1448000 | K63: ='TST1'!K63+'TST2'!K63+MKT!K63+SYShin!K63+JGChoi!K63 -> 1448000 | L63: ='TST1'!L63+'TST2'!L63+MKT!L63+SYShin!L63+JGChoi!L63 -> 1448000 | M63: =SUM(J63:L63) -> 4344000 | N63: ='TST1'!N63+'TST2'!N63+MKT!N63+SYShin!N63+JGChoi!N63 -> 1448000 | O63: ='TST1'!O63+'TST2'!O63+MKT!O63+SYShin!O63+JGChoi!O63 -> 1448000 | P63: ='TST1'!P63+'TST2'!P63+MKT!P63+SYShin!P63+JGChoi!P63 -> 1448000 | Q63: =SUM(N63:P63) -> 4344000 | R63: ='TST1'!R63+'TST2'!R63+MKT!R63+SYShin!R63+JGChoi!R63 -> 1448000 | S63: ='TST1'!S63+'TST2'!S63+MKT!S63+SYShin!S63+JGChoi!S63 -> 1448000 | T63: ='TST1'!T63+'TST2'!T63+MKT!T63+SYShin!T63+JGChoi!T63 -> 1448000 | U63: =SUM(R63:T63) -> 4344000 | V63: =I63+M63+Q63+U63 -> 17376000
C64: 회의비 | E64: 0 | F64: ='TST1'!F64+'TST2'!F64+MKT!F64+SYShin!F64+JGChoi!F64 -> 774000 | G64: ='TST1'!G64+'TST2'!G64+MKT!G64+SYShin!G64+JGChoi!G64 -> 769000 | H64: ='TST1'!H64+'TST2'!H64+MKT!H64+SYShin!H64+JGChoi!H64 -> 769000 | I64: =SUM(F64:H64) -> 2312000 | J64: ='TST1'!J64+'TST2'!J64+MKT!J64+SYShin!J64+JGChoi!J64 -> 769000 | K64: ='TST1'!K64+'TST2'!K64+MKT!K64+SYShin!K64+JGChoi!K64 -> 769000 | L64: ='TST1'!L64+'TST2'!L64+MKT!L64+SYShin!L64+JGChoi!L64 -> 769000 | M64: =SUM(J64:L64) -> 2307000 | N64: ='TST1'!N64+'TST2'!N64+MKT!N64+SYShin!N64+JGChoi!N64 -> 769000 | O64: ='TST1'!O64+'TST2'!O64+MKT!O64+SYShin!O64+JGChoi!O64 -> 769000 | P64: ='TST1'!P64+'TST2'!P64+MKT!P64+SYShin!P64+JGChoi!P64 -> 769000 | Q64: =SUM(N64:P64) -> 2307000 | R64: ='TST1'!R64+'TST2'!R64+MKT!R64+SYShin!R64+JGChoi!R64 -> 769000 | S64: ='TST1'!S64+'TST2'!S64+MKT!S64+SYShin!S64+JGChoi!S64 -> 769000 | T64: ='TST1'!T64+'TST2'!T64+MKT!T64+SYShin!T64+JGChoi!T64 -> 769000 | U64: =SUM(R64:T64) -> 2307000 | V64: =I64+M64+Q64+U64 -> 9233000
C65: 접대비 | E65: 0 | F65: ='TST1'!F65+'TST2'!F65+MKT!F65+SYShin!F65+JGChoi!F65 -> 2116000 | G65: ='TST1'!G65+'TST2'!G65+MKT!G65+SYShin!G65+JGChoi!G65 -> 2041000 | H65: ='TST1'!H65+'TST2'!H65+MKT!H65+SYShin!H65+JGChoi!H65 -> 2041000 | I65: =SUM(F65:H65) -> 6198000 | J65: ='TST1'!J65+'TST2'!J65+MKT!J65+SYShin!J65+JGChoi!J65 -> 2041000 | K65: ='TST1'!K65+'TST2'!K65+MKT!K65+SYShin!K65+JGChoi!K65 -> 2041000 | L65: ='TST1'!L65+'TST2'!L65+MKT!L65+SYShin!L65+JGChoi!L65 -> 2041000 | M65: =SUM(J65:L65) -> 6123000 | N65: ='TST1'!N65+'TST2'!N65+MKT!N65+SYShin!N65+JGChoi!N65 -> 2041000 | O65: ='TST1'!O65+'TST2'!O65+MKT!O65+SYShin!O65+JGChoi!O65 -> 2041000 | P65: ='TST1'!P65+'TST2'!P65+MKT!P65+SYShin!P65+JGChoi!P65 -> 2041000 | Q65: =SUM(N65:P65) -> 6123000 | R65: ='TST1'!R65+'TST2'!R65+MKT!R65+SYShin!R65+JGChoi!R65 -> 2041000 | S65: ='TST1'!S65+'TST2'!S65+MKT!S65+SYShin!S65+JGChoi!S65 -> 2041000 | T65: ='TST1'!T65+'TST2'!T65+MKT!T65+SYShin!T65+JGChoi!T65 -> 2041000 | U65: =SUM(R65:T65) -> 6123000 | V65: =I65+M65+Q65+U65 -> 24567000
B66: Total Travel & Entertainment | F66: =SUM(F55:F65) -> 9447000 | G66: =SUM(G55:G65) -> 9367000 | H66: =SUM(H55:H65) -> 9367000 | I66: =SUM(I55:I65) -> 28181000 | J66: =SUM(J55:J65) -> 9367000 | K66: =SUM(K55:K65) -> 9367000 | L66: =SUM(L55:L65) -> 9367000 | M66: =SUM(M55:M65) -> 28101000 | ... U66: =SUM(U55:U65) -> 28101000 | V66: =I66+M66+Q66+U66 -> 112484000
B67: Product Marketing
C68: 행사비 | E68: 0 | F68: ='TST1'!F68+'TST2'!F68+MKT!F68+SYShin!F68+JGChoi!F68 -> 0 | G68: ='TST1'!G68+'TST2'!G68+MKT!G68+SYShin!G68+JGChoi!G68 -> 0 | H68: ='TST1'!H68+'TST2'!H68+MKT!H68+SYShin!H68+JGChoi!H68 -> 0 | I68: =SUM(F68:H68) -> 0 | J68: ='TST1'!J68+'TST2'!J68+MKT!J68+SYShin!J68+JGChoi!J68 -> 0 | K68: ='TST1'!K68+'TST2'!K68+MKT!K68+SYShin!K68+JGChoi!K68 -> 0 | L68: ='TST1'!L68+'TST2'!L68+MKT!L68+SYShin!L68+JGChoi!L68 -> 0 | M68: =SUM(J68:L68) -> 0 | N68: ='TST1'!N68+'TST2'!N68+MKT!N68+SYShin!N68+JGChoi!N68 -> 0 | O68: ='TST1'!O68+'TST2'!O68+MKT!O68+SYShin!O68+JGChoi!O68 -> 0 | P68: ='TST1'!P68+'TST2'!P68+MKT!P68+SYShin!P68+JGChoi!P68 -> 0 | Q68: =SUM(N68:P68) -> 0 | R68: ='TST1'!R68+'TST2'!R68+MKT!R68+SYShin!R68+JGChoi!R68 -> 0 | S68: ='TST1'!S68+'TST2'!S68+MKT!S68+SYShin!S68+JGChoi!S68 -> 0 | T68: ='TST1'!T68+'TST2'!T68+MKT!T68+SYShin!T68+JGChoi!T68 -> 0 | U68: =SUM(R68:T68) -> 0 | V68: =I68+M68+Q68+U68 -> 0
C69: 마케팅 | E69: 0 | F69: ='TST1'!F69+'TST2'!F69+MKT!F69+SYShin!F69+JGChoi!F69 -> 15000 | G69: ='TST1'!G69+'TST2'!G69+MKT!G69+SYShin!G69+JGChoi!G69 -> 1000000 | H69: ='TST1'!H69+'TST2'!H69+MKT!H69+SYShin!H69+JGChoi!H69 -> 1000000 | I69: =SUM(F69:H69) -> 2015000 | J69: ='TST1'!J69+'TST2'!J69+MKT!J69+SYShin!J69+JGChoi!J69 -> 1000000 | K69: ='TST1'!K69+'TST2'!K69+MKT!K69+SYShin!K69+JGChoi!K69 -> 1000000 | L69: ='TST1'!L69+'TST2'!L69+MKT!L69+SYShin!L69+JGChoi!L69 -> 1000000 | M69: =SUM(J69:L69) -> 3000000 | N69: ='TST1'!N69+'TST2'!N69+MKT!N69+SYShin!N69+JGChoi!N69 -> 1000000 | O69: ='TST1'!O69+'TST2'!O69+MKT!O69+SYShin!O69+JGChoi!O69 -> 1000000 | P69: ='TST1'!P69+'TST2'!P69+MKT!P69+SYShin!P69+JGChoi!P69 -> 1000000 | Q69: =SUM(N69:P69) -> 3000000 | R69: ='TST1'!R69+'TST2'!R69+MKT!R69+SYShin!R69+JGChoi!R69 -> 1000000 | S69: ='TST1'!S69+'TST2'!S69+MKT!S69+SYShin!S69+JGChoi!S69 -> 1000000 | T69: ='TST1'!T69+'TST2'!T69+MKT!T69+SYShin!T69+JGChoi!T69 -> 1000000 | U69: =SUM(R69:T69) -> 3000000 | V69: =I69+M69+Q69+U69 -> 11015000
C70: 기타 | E70: 0 | F70: ='TST1'!F70+'TST2'!F70+MKT!F70+SYShin!F70+JGChoi!F70 -> 0 | G70: ='TST1'!G70+'TST2'!G70+MKT!G70+SYShin!G70+JGChoi!G70 -> 0 | H70: ='TST1'!H70+'TST2'!H70+MKT!H70+SYShin!H70+JGChoi!H70 -> 0 | I70: =SUM(F70:H70) -> 0 | J70: ='TST1'!J70+'TST2'!J70+MKT!J70+SYShin!J70+JGChoi!J70 -> 0 | K70: ='TST1'!K70+'TST2'!K70+MKT!K70+SYShin!K70+JGChoi!K70 -> 0 | L70: ='TST1'!L70+'TST2'!L70+MKT!L70+SYShin!L70+JGChoi!L70 -> 0 | M70: =SUM(J70:L70) -> 0 | N70: ='TST1'!N70+'TST2'!N70+MKT!N70+SYShin!N70+JGChoi!N70 -> 0 | O70: ='TST1'!O70+'TST2'!O70+MKT!O70+SYShin!O70+JGChoi!O70 -> 0 | P70: ='TST1'!P70+'TST2'!P70+MKT!P70+SYShin!P70+JGChoi!P70 -> 0 | Q70: =SUM(N70:P70) -> 0 | R70: ='TST1'!R70+'TST2'!R70+MKT!R70+SYShin!R70+JGChoi!R70 -> 0 | S70: ='TST1'!S70+'TST2'!S70+MKT!S70+SYShin!S70+JGChoi!S70 -> 0 | T70: ='TST1'!T70+'TST2'!T70+MKT!T70+SYShin!T70+JGChoi!T70 -> 0 | U70: =SUM(R70:T70) -> 0 | V70: =I70+M70+Q70+U70 -> 0
B71: Total Product Marketing | F71: =SUM(F68:F70) -> 15000 | G71: =SUM(G68:G70) -> 1000000 | H71: =SUM(H68:H70) -> 1000000 | I71: =SUM(I68:I70) -> 2015000 | J71: =SUM(J68:J70) -> 1000000 | K71: =SUM(K68:K70) -> 1000000 | L71: =SUM(L68:L70) -> 1000000 | M71: =SUM(M68:M70) -> 3000000 | ... U71: =SUM(U68:U70) -> 3000000 | V71: =I71+M71+Q71+U71 -> 11015000
B72: Sales Activities
C73: 고객교육훈련비 | E73: 0 | F73: ='TST1'!F73+'TST2'!F73+MKT!F73+SYShin!F73+JGChoi!F73 -> 0 | G73: ='TST1'!G73+'TST2'!G73+MKT!G73+SYShin!G73+JGChoi!G73 -> 0 | H73: ='TST1'!H73+'TST2'!H73+MKT!H73+SYShin!H73+JGChoi!H73 -> 0 | I73: =SUM(F73:H73) -> 0 | J73: ='TST1'!J73+'TST2'!J73+MKT!J73+SYShin!J73+JGChoi!J73 -> 0 | K73: ='TST1'!K73+'TST2'!K73+MKT!K73+SYShin!K73+JGChoi!K73 -> 0 | L73: ='TST1'!L73+'TST2'!L73+MKT!L73+SYShin!L73+JGChoi!L73 -> 0 | M73: =SUM(J73:L73) -> 0 | N73: ='TST1'!N73+'TST2'!N73+MKT!N73+SYShin!N73+JGChoi!N73 -> 0 | O73: ='TST1'!O73+'TST2'!O73+MKT!O73+SYShin!O73+JGChoi!O73 -> 0 | P73: ='TST1'!P73+'TST2'!P73+MKT!P73+SYShin!P73+JGChoi!P73 -> 0 | Q73: =SUM(N73:P73) -> 0 | R73: ='TST1'!R73+'TST2'!R73+MKT!R73+SYShin!R73+JGChoi!R73 -> 0 | S73: ='TST1'!S73+'TST2'!S73+MKT!S73+SYShin!S73+JGChoi!S73 -> 0 | T73: ='TST1'!T73+'TST2'!T73+MKT!T73+SYShin!T73+JGChoi!T73 -> 0 | U73: =SUM(R73:T73) -> 0 | V73: =I73+M73+Q73+U73 -> 0
C74: Sales Promotions | E74: 0 | F74: ='TST1'!F74+'TST2'!F74+MKT!F74+SYShin!F74+JGChoi!F74 -> 0 | G74: ='TST1'!G74+'TST2'!G74+MKT!G74+SYShin!G74+JGChoi!G74 -> 0 | H74: ='TST1'!H74+'TST2'!H74+MKT!H74+SYShin!H74+JGChoi!H74 -> 0 | I74: =SUM(F74:H74) -> 0 | J74: ='TST1'!J74+'TST2'!J74+MKT!J74+SYShin!J74+JGChoi!J74 -> 0 | K74: ='TST1'!K74+'TST2'!K74+MKT!K74+SYShin!K74+JGChoi!K74 -> 0 | L74: ='TST1'!L74+'TST2'!L74+MKT!L74+SYShin!L74+JGChoi!L74 -> 0 | M74: =SUM(J74:L74) -> 0 | N74: ='TST1'!N74+'TST2'!N74+MKT!N74+SYShin!N74+JGChoi!N74 -> 0 | O74: ='TST1'!O74+'TST2'!O74+MKT!O74+SYShin!O74+JGChoi!O74 -> 0 | P74: ='TST1'!P74+'TST2'!P74+MKT!P74+SYShin!P74+JGChoi!P74 -> 0 | Q74: =SUM(N74:P74) -> 0 | R74: ='TST1'!R74+'TST2'!R74+MKT!R74+SYShin!R74+JGChoi!R74 -> 0 | S74: ='TST1'!S74+'TST2'!S74+MKT!S74+SYShin!S74+JGChoi!S74 -> 0 | T74: ='TST1'!T74+'TST2'!T74+MKT!T74+SYShin!T74+JGChoi!T74 -> 0 | U74: =SUM(R74:T74) -> 0 | V74: =I74+M74+Q74+U74 -> 0
